Workbook

Sheet Export Summary
B3: This document was exported from Numbers. Each table was converted to an Excel worksheet. All other objects on each Numbers sheet were placed on separate worksheets. Please be aware that formula calculations may differ in Excel.
B7: Numbers Sheet Name | C7: Numbers Table Name | D7: Excel Worksheet Name
B9: presupuesto
C10: Gastos | D10: presupuesto - Gastos
C11: Table 2 | D11: presupuesto - Table 2
C12: Table 1 | D12: presupuesto - Table 1
C13: Table 3 | D13: presupuesto - Table 3
C14: Ingreso líquido | D14: presupuesto - Ingreso líquido
C15: Capacidad ahorro | D15: presupuesto - Capacidad ahorro
C16: APV - simulación régimen B | D16: presupuesto - APV - simulación
C17: apv - rebaja impuestos interés hipotecario | D17: presupuesto - apv - rebaja impu
B18: flujos
C19: Gasto mes actual | D19: flujos - Gasto mes actual
C20: Table 1-3 | D20: flujos - Table 1-3
C21: Table 1-2 | D21: flujos - Table 1-2
C22: Table 1-4 | D22: flujos - Table 1-4
C23: Table 3-1-1 | D23: flujos - Table 3-1-1
C24: Table 3-1-1-1 | D24: flujos - Table 3-1-1-1
C25: Table 3-1 | D25: flujos - Table 3-1
C26: Totales | D26: flujos - Totales
C27: Table 2-1 | D27: flujos - Table 2-1
C28: Table 3-2 | D28: flujos - Table 3-2
C29: Gasto mensual | D29: flujos - Gasto mensual
C30: Table 1 | D30: flujos - Table 1
... C37: “All Drawings from the Sheet” | D37: flujos - Drawings
B38: anual
C39: Table 1-1 | D39: anual - Table 1-1
B40: net worth
C41: Table 2 | D41: net worth - Table 2
C42: dap-1 | D42: net worth - dap-1
C43: net worth | D43: net worth - net worth
C44: cash | D44: net worth - cash
C45: balances | D45: net worth - balances
C46: Table 1 | D46: net worth - Table 1
C47: resumen | depósitos - actual | D47: net worth - resumen | depósitos
C48: retiro | D48: net worth - retiro
C49: brokerage | D49: net worth - brokerage
C50: cash and cash equivalents | D50: net worth - cash and cash equiv
C51: criptomonedas | D51: net worth - criptomonedas
C52: Aporte APV | D52: net worth - Aporte APV
... C59: “All Drawings from the Sheet” | D59: net worth - Drawings
B60: depto
C61: Departamento | D61: depto - Departamento
C62: Table 3 | D62: depto - Table 3
C63: Gastos-1 | D63: depto - Gastos-1
C64: Table 5-2-1 | D64: depto - Table 5-2-1
C65: Table 6 | D65: depto - Table 6
C66: Table 1 | D66: depto - Table 1
C67: Table 1-1 | D67: depto - Table 1-1
C68: Table 2 | D68: depto - Table 2
C69: Table 2-1 | D69: depto - Table 2-1
C70: Table 7 | D70: depto - Table 7
C71: Table 3-3-1 | D71: depto - Table 3-3-1
C72: Table 5 | D72: depto - Table 5
... C79: “All Drawings from the Sheet” | D79: depto - Drawings
B80: variables
C81: Table 1 | D81: variables - Table 1
C82: Table 1-1 | D82: variables - Table 1-1
C83: Table 2 | D83: variables - Table 2
C84: Table 1-4 | D84: variables - Table 1-4
C85: Table 3 | D85: variables - Table 3
C86: “All Drawings from the Sheet” | D86: variables - Drawings
B87: cripto
C88: Fees | D88: cripto - Fees
C89: Bitcoin – BTC | D89: cripto - Bitcoin – BTC
C90: Ether – ETH | D90: cripto - Ether – ETH
B91: watchlist
C92: anime | D92: watchlist - anime
C93: Movies | D93: watchlist - Movies
C94: dramas | D94: watchlist - dramas
C95: dramedies | D95: watchlist - dramedies
C96: sitcoms | D96: watchlist - sitcoms
C97: Games | D97: watchlist - Games
C98: accion | D98: watchlist - accion
C99: animacion | D99: watchlist - animacion
B100: tracking
C101: Table 2-1-2-1 | D101: tracking - Table 2-1-2-1
C102: Table 4 | D102: tracking - Table 4
C103: Table 1 | D103: tracking - Table 1
C104: Days since last-1 | D104: tracking - Days since last-1
C105: Trackers | D105: tracking - Trackers
C106: Table 1-2 | D106: tracking - Table 1-2
C107: Table 2-1 | D107: tracking - Table 2-1
C108: Table 2-1-2 | D108: tracking - Table 2-1-2
C109: Table 1-1 | D109: tracking - Table 1-1
C110: Deudas | D110: tracking - Deudas
C111: Table 3-1 | D111: tracking - Table 3-1
C112: Table 2 | D112: tracking - Table 2
... C118: “All Drawings from the Sheet” | D118: tracking - Drawings
B119: Trees
C120: Table 1 | D120: Trees - Table 1
C121: Table 1-1 | D121: Trees - Table 1-1
C122: Table 1-1-1 | D122: Trees - Table 1-1-1
C123: Table 3 | D123: Trees - Table 3
C124: Table 3-1 | D124: Trees - Table 3-1
C125: Table 4 | D125: Trees - Table 4
C126: Table 2 | D126: Trees - Table 2
C127: Table 5 | D127: Trees - Table 5
C128: Table 3-1-1 | D128: Trees - Table 3-1-1
B129: Sheet 3
...

Sheet presupuesto - Gastos
E1: CLP
A2: Credito hipotecario | B2: TRUE | C2: {=IF(B2,E2/'presupuesto - Ingreso líquido'!$B$31,0)} -> 0.52205009 | D2: {=IF(B2,E2/'presupuesto - Ingreso líquido'!$B$32,0)} -> 0.63278043 | E2: 2000000 | F2: {=SUMIF(B2:B4,"=TRUE",E2:E4)} -> 2230990 | G2: {=IF(F2,F2/'presupuesto - Ingreso líquido'!$B$31,0)} -> 0.58234426 | H2: Internet | I2: 20990
A3: Arriendo | B3: FALSE | C3: {=IF(B3,E3/'presupuesto - Ingreso líquido'!$B$31,0)} -> 0 | D3: {=IF(B3,E3/'presupuesto - Ingreso líquido'!$B$32,0)} -> 0 | E3: - | F3: 18 | G3: {=IF(F2,F2/'presupuesto - Ingreso líquido'!$B$32,0)} -> 0.70586341 | H3: Agua | I3: -
A4: Cuentas | B4: TRUE | C4: {=IF(B4,E4/'presupuesto - Ingreso líquido'!$B$31,0)} -> 0.060294175 | D4: {=IF(B4,E4/'presupuesto - Ingreso líquido'!$B$32,0)} -> 0.073082976 | E4: {=SUM(I2:I7)} -> 230990 | H4: Luz | I4: 40000
C5: {=IF(B5,E5/'presupuesto - Ingreso líquido'!$B$31,0)} -> 0 | D5: {=IF(B5,E5/'presupuesto - Ingreso líquido'!$B$32,0)} -> 0 | H5: Gas | I5: 30000
A6: Supermercado | B6: TRUE | C6: {=IF(B6,E6/'presupuesto - Ingreso líquido'!$B$31,0)} -> 0.039153756 | D6: {=IF(B6,E6/'presupuesto - Ingreso líquido'!$B$32,0)} -> 0.047458532 | E6: {=150000} -> 150000 | H6: Gastos comunes | I6: 90000
C7: {=IF(B7,E7/'presupuesto - Ingreso líquido'!$B$31,0)} -> 0 | D7: {=IF(B7,E7/'presupuesto - Ingreso líquido'!$B$32,0)} -> 0 | H7: Estacionamiento | I7: 50000
A8: Celular | B8: FALSE | C8: {=IF(B8,E8/'presupuesto - Ingreso líquido'!$B$31,0)} -> 0 | D8: {=IF(B8,E8/'presupuesto - Ingreso líquido'!$B$32,0)} -> 0 | E8: 20000
A9: Bip | B9: FALSE | C9: {=IF(B9,E9/'presupuesto - Ingreso líquido'!$B$31,0)} -> 0 | D9: {=IF(B9,E9/'presupuesto - Ingreso líquido'!$B$32,0)} -> 0 | E9: 5000 | H9: Arriendo máximo | I9: {='presupuesto - Ingreso líquido'!B32*30%} -> 948196.2
A10: Uber | B10: FALSE | C10: {=IF(B10,E10/'presupuesto - Ingreso líquido'!$B$31,0)} -> 0 | D10: {=IF(B10,E10/'presupuesto - Ingreso líquido'!$B$32,0)} -> 0 | E10: 10000 | I10: {='presupuesto - Ingreso líquido'!B32/3} -> 1053551.3
A11: Suscripciones | B11: TRUE | C11: {=IF(B11,E11/'presupuesto - Ingreso líquido'!$B$31,0)} -> 0.0020278383 | D11: {=IF(B11,E11/'presupuesto - Ingreso líquido'!$B$32,0)} -> 0.0024579565 | E11: {=SUMIF('presupuesto - Table 2'!B2:B13,"=TRUE",'presupuesto - Table 2'!C2:C13)} -> 7768.75 | I11: {='presupuesto - Ingreso líquido'!B31*30%} -> 1149315
A12: Gimnasio | B12: FALSE | C12: {=IF(B12,E12/'presupuesto - Ingreso líquido'!$B$31,0)} -> 0 | D12: {=IF(B12,E12/'presupuesto - Ingreso líquido'!$B$32,0)} -> 0 | E12: 15000 | H12: Sueldo liq ideal | I12: {=SUM(E3:E4)/30%} -> 769966.67
B13: FALSE | C13: {=IF(B13,E13/'presupuesto - Ingreso líquido'!$B$31,0)} -> 0 | D13: {=IF(B13,E13/'presupuesto - Ingreso líquido'!$B$32,0)} -> 0 | I13: {=I12-'presupuesto - Ingreso líquido'!B32} -> -2390687.3
A14: Salud | B14: FALSE | C14: {=IF(B14,E14/'presupuesto - Ingreso líquido'!$B$31,0)} -> 0 | D14: {=IF(B14,E14/'presupuesto - Ingreso líquido'!$B$32,0)} -> 0 | E14: 50000
A15: Isapre | B15: TRUE | C15: {=IF(B15,E15/'presupuesto - Ingreso líquido'!$B$31,0)} -> 0.066782474 | D15: {=IF(B15,E15/'presupuesto - Ingreso líquido'!$B$32,0)} -> 0.080947487 | E15: {='presupuesto - Ingreso líquido'!B18} -> 255847
B16: FALSE | C16: {=IF(B16,E16/'presupuesto - Ingreso líquido'!$B$31,0)} -> 0 | D16: {=IF(B16,E16/'presupuesto - Ingreso líquido'!$B$32,0)} -> 0
B17: FALSE | C17: {=IF(B17,E17/'presupuesto - Ingreso líquido'!$B$31,0)} -> 0 | D17: {=IF(B17,E17/'presupuesto - Ingreso líquido'!$B$32,0)} -> 0
A18: Estacionamiento | B18: FALSE | C18: {=IF(B18,E18/'presupuesto - Ingreso líquido'!$B$31,0)} -> 0 | D18: {=IF(B18,E18/'presupuesto - Ingreso líquido'!$B$32,0)} -> 0 | E18: {=F18*'variables - Table 1'!B2} -> 119801.54 | F18: 2.95 | I18: Marzo auto
A19: Estacionar casual | B19: FALSE | C19: {=IF(B19,E19/'presupuesto - Ingreso líquido'!$B$31,0)} -> 0 | D19: {=IF(B19,E19/'presupuesto - Ingreso líquido'!$B$32,0)} -> 0 | E19: 5000 | H19: SOAP | I19: 5000
A20: Mantencion | B20: TRUE | C20: {=IF(B20,E20/'presupuesto - Ingreso líquido'!$B$31,0)} -> 0.0065256261 | D20: {=IF(B20,E20/'presupuesto - Ingreso líquido'!$B$32,0)} -> 0.0079097554 | E20: 25000 | H20: Patente | I20: 221288
A21: Bencina | B21: TRUE | C21: {=IF(B21,E21/'presupuesto - Ingreso líquido'!$B$31,0)} -> 0.0078307513 | D21: {=IF(B21,E21/'presupuesto - Ingreso líquido'!$B$32,0)} -> 0.0094917065 | E21: 30000 | H21: Revisión técnica | I21: 20000
A22: Seguro auto | B22: FALSE | C22: {=IF(B22,E22/'presupuesto - Ingreso líquido'!$B$31,0)} -> 0 | D22: {=IF(B22,E22/'presupuesto - Ingreso líquido'!$B$32,0)} -> 0 | E22: {=515577/12} -> 42964.75 | F22: {=SUM(E18:E24)} -> 248290.29 | I22: {=SUM(I19:I21)} -> 246288
A23: Marzo / 12 | B23: TRUE | C23: {=IF(B23,E23/'presupuesto - Ingreso líquido'!$B$31,0)} -> 0.005357278 | D23: {=IF(B23,E23/'presupuesto - Ingreso líquido'!$B$32,0)} -> 0.0064935928 | E23: {=I23} -> 20524 | F23: {=F24*12} -> 906288 | H23: Por mes | I23: {=I22/12} -> 20524
A24: Tag | B24: FALSE | C24: {=IF(B24,E24/'presupuesto - Ingreso líquido'!$B$31,0)} -> 0 | D24: {=IF(B24,E24/'presupuesto - Ingreso líquido'!$B$32,0)} -> 0 | E24: 5000 | F24: {=SUMIF(B18:B24,"=TRUE",E18:E24)} -> 75524 | G24: {=IF(F24,F24/'presupuesto - Ingreso líquido'!$B$31,0)} -> 0.019713655
B25: FALSE | C25: {=IF(B25,E25/'presupuesto - Ingreso líquido'!$B$31,0)} -> 0 | D25: {=IF(B25,E25/'presupuesto - Ingreso líquido'!$B$32,0)} -> 0
A26: take out | B26: TRUE | C26: {=IF(B26,E26/'presupuesto - Ingreso líquido'!$B$31,0)} -> 0.026102504 | D26: {=IF(B26,E26/'presupuesto - Ingreso líquido'!$B$32,0)} -> 0.031639022 | E26: 100000
A27: Carrete | B27: TRUE | C27: {=IF(B27,E27/'presupuesto - Ingreso líquido'!$B$31,0)} -> 0.026102504 | D27: {=IF(B27,E27/'presupuesto - Ingreso líquido'!$B$32,0)} -> 0.031639022 | E27: 100000
A28: Fun | B28: TRUE | C28: {=IF(B28,E28/'presupuesto - Ingreso líquido'!$B$31,0)} -> 0.031323005 | D28: {=IF(B28,E28/'presupuesto - Ingreso líquido'!$B$32,0)} -> 0.037966826 | E28: 120000
A29: Drugs | B29: TRUE | C29: {=IF(B29,E29/'presupuesto - Ingreso líquido'!$B$31,0)} -> 0.052205009 | D29: {=IF(B29,E29/'presupuesto - Ingreso líquido'!$B$32,0)} -> 0.063278043 | E29: 200000
B30: FALSE | C30: {=IF(B30,E30/'presupuesto - Ingreso líquido'!$B$31,0)} -> 0 | D30: {=IF(B30,E30/'presupuesto - Ingreso líquido'!$B$32,0)} -> 0
A31: Limpieza | B31: FALSE | C31: {=IF(B31,E31/'presupuesto - Ingreso líquido'!$B$31,0)} -> 0 | D31: {=IF(B31,E31/'presupuesto - Ingreso líquido'!$B$32,0)} -> 0
A32: Lavanderia | B32: FALSE | C32: {=IF(B32,E32/'presupuesto - Ingreso líquido'!$B$31,0)} -> 0 | D32: {=IF(B32,E32/'presupuesto - Ingreso líquido'!$B$32,0)} -> 0
A33: Shit | B33: TRUE | C33: {=IF(B33,E33/'presupuesto - Ingreso líquido'!$B$31,0)} -> 0.031323005 | D33: {=IF(B33,E33/'presupuesto - Ingreso líquido'!$B$32,0)} -> 0.037966826 | E33: 120000
A34: Gasto mensual | C34: {=$E34/'presupuesto - Ingreso líquido'!$B$35} -> 1.0631122 | E34: {=SUMIF(B2:B33,"=TRUE",E2:E33)} -> 3360129.8 | F34: {=E$34/'variables - Table 1'!$B$5} -> 3481.9997 | H34: Gasto anual | I34: Ahorro anual
A35: Disponible | C35: {=$E35/'presupuesto - Ingreso líquido'!$B$35} -> 0.14899457 | E35: {='presupuesto - Ingreso líquido'!B31-E$34} -> 470920.29 | F35: {=E$35/'variables - Table 1'!$B$5} -> 488.0003 | H35: {=E$34*12} -> 40321557 | I35: {=E$35*12} -> 5651043.5
A36: Disponible liq | C36: {=$E36/'presupuesto - Ingreso líquido'!$B$35} -> -0.063112176 | E36: {='presupuesto - Ingreso líquido'!B32-E$34} -> -199475.75 | H36: {=H$35/'variables - Table 1'!$B$5} -> 41783.997 | I36: {=I$35/'variables - Table 1'!$B$5} -> 5856.0036
H37: Tasa de ahorro | I37: {=E$35/'presupuesto - Ingreso líquido'!B31} -> 0.12292199

Sheet presupuesto - Table 2
A1: Suscripciones
A2: Netflix | B2: FALSE | C2: 7390
A3: Apple Music | B3: TRUE | C3: 3500
A4: iCloud | B4: TRUE | C4: 650
A5: apple tv+ | B5: TRUE
A6: paramount+ | B6: TRUE
B7: FALSE
A8: uber one | B8: FALSE | C8: 5000
A9: 1password | B9: TRUE | C9: {='variables - Table 1'!B5*D9} -> 3618.75 | D9: {=45/12} -> 3.75
B10: FALSE
B11: FALSE
B12: FALSE
B13: FALSE

Sheet presupuesto - Table 1
A1: Wishlist | B1: Chile | D1: {=SUM(D2:D21)} -> 3179.99 | E1: {=SUM(E2:E21)} -> 3360215.9 | F1: Diferencia
A2: iPhone SE2 128 GB | B2: FALSE | C2: 450000 | D2: 449 | E2: {=D2*1.095*'variables - Table 1'!$B$5} -> 474447.08 | F2: {=C2-E2} -> -24447.075
A3: Mac Mini | B3: FALSE | C3: 999990 | D3: 999 | E3: {=D3*1.095*'variables - Table 1'!$B$5} -> 1055618.3 | F3: {=C3-E3} -> -55628.325
A4: Volcano digital | B4: TRUE | C4: 379000 | D4: 599 | E4: {=D4*1.095*'variables - Table 1'!$B$5} -> 632948.32 | F4: {=C4-E4} -> -253948.33
A5: Pax 3 | B5: FALSE | C5: 299990 | D5: 274.99 | E5: {=D5*1.095*'variables - Table 1'!$B$5} -> 290575.06 | F5: {=C5-E5} -> 9414.9417
A6: MFLB | B6: TRUE | C6: 95000 | D6: 129 | E6: {=D6*1.095*'variables - Table 1'!$B$5} -> 136311.08 | F6: {=C6-E6} -> -41311.075
A7: Bongs | B7: FALSE
A8: DaVinci IQ | B8: TRUE | C8: 210000 | D8: 200 | E8: {=D8*1.095*'variables - Table 1'!$B$5} -> 211335 | F8: {=C8-E8} -> -1335
B9: FALSE
A10: Barbour Ashby Waxed Jacket | B10: FALSE
B11: FALSE
A12: Escritorio | B12: TRUE | C12: 100000
A13: Silla | B13: TRUE | C13: 50000
A14: Pantalla | B14: TRUE | C14: 160000
A15: Repuestos PC | B15: TRUE | C15: 160000
A16: tv | B16: FALSE | C16: 179990 | D16: 179 | E16: {=D16*1.095*'variables - Table 1'!$B$5} -> 189144.83 | F16: {=C16-E16} -> -9154.825
B17: FALSE
B18: FALSE
B19: FALSE
A20: Sony 1000XM3 | B20: FALSE | C20: 250000 | D20: 350 | E20: {=D20*1.095*'variables - Table 1'!$B$5} -> 369836.25 | F20: {=C20-E20} -> -119836.25
B21: FALSE
A22: {=SUM(C$22:E$22)} -> 3533621.5 | C22: {=SUMIF(B2:B21,"=TRUE",C2:C21)} -> 1154000 | E22: {=SUMIF(B2:B21,"=FALSE",E2:E21)} -> 2379621.5

Sheet presupuesto - Table 3
A1: Ahorro | B1: Mensual | C1: Anual
A2: Fintual | B2: 400000 | C2: {=B2*12} -> 4800000
A3: AFP | B3: {='presupuesto - Ingreso líquido'!B17} -> 365496 | C3: {=B3*12} -> 4385952
A4: APV - a | B4: {='presupuesto - APV - simulación '!B$14} -> 240627 | C4: {=B4*12} -> 2887524
A5: APV - b | B5: {=200000*0} -> 0 | C5: {=B5*12} -> 0
A6: Ahorro vivienda | B6: 250000 | C6: {=B6*12} -> 3000000
A9: Ahorro | B9: {=SUM(B2:B8)} -> 1256123
A10: Sobra | B10: {='presupuesto - Gastos'!E$35-B$9} -> -785202.71

Sheet presupuesto - Ingreso líquido
A1: Ingreso líquido
A3: Sueldo base | B3: {=3640000+14668+37770} -> 3692438
B4: {=B3/4} -> 923109.5
A5: sueldo min × 4,75÷12 | B5: {=MIN('variables - Table 1'!B8*4.75/12)} -> 213354.17 | D5: Tope 2026
A6: Gratificación | B6: {=ROUND(MIN('variables - Table 1'!B8*4.75/12,B3/4),0)} -> 213354 | C6: previsional | D6: 90
D7: {=ROUND(D6*'variables - Table 1'!$B$2,0)} -> 3654962
A8: Movilización | B8: {=19000*1} -> 19000 | C8: cesantía | D8: 135.2
A9: Colación | B9: {=57000*1} -> 57000 | D9: {=ROUND(D8*'variables - Table 1'!$B$2,0)} -> 5490565
A11: Total sueldo bruto | B11: {=B3+B6+B8+B9} -> 3981792 | C11: {=B11/'variables - Table 1'!B$13} -> 4489.3589
A12: Sueldo imponible | B12: {=SUM(B3,B6)} -> 3905792
A13: Base imponible | B13: {=ROUND(MIN(B12,D6*'variables - Table 1'!B2),0)} -> 3654962
D14: {=D15/'variables - Table 1'!B13} -> 4945.038
A15: AFP | B15: {=SUM(B16:B17)} -> 382309 | C15: Anual AFP | D15: {=B17*12} -> 4385952
A16: Comision | B16: {=ROUND(B13*D16%,0)} -> 16813 | C16: Comisión AFP | D16: 0.46
A17: AFP depositado | B17: {=ROUND(B13*10%,0)} -> 365496
A18: Previsión 7% | B18: {=ROUND(B13*7%,0)} -> 255847 | C18: {=B18/'variables - Table 1'!B2} -> 6.2999915 | D18: 4.91
C19: Isapre | D19: {=ROUND(D18*'variables - Table 1'!B2,0)} -> 199398
A20: Seguro de cesantía | B20: {=ROUND(MIN(B12,D9)*0.6%,0)} -> 23435 | C20: Excedentes | D20: {=B18-D19} -> 56449
A21: + empleador | B21: {=ROUND(MIN(B12,D9)*1.6%,0)} -> 62493 | C21: Anuales | D21: {=D20*12} -> 677388
D22: {=D21/D19} -> 3.3971655
A24: Base tributable | B24: {=B12-(B15+B18+B20)} -> 3244201
A26: Impuesto efectivo | B26: {='presupuesto - APV - simulación '!H$11} -> 133928.96 | C26: {=ROUND(B26/B11*100,0)%} -> 0.03
C27: Anual impuestos | D27: {=B26*12} -> 1607147.5
A28: Seguro colectivo | B28: 25618
A29: Total descuentos | B29: {=ROUND(B26+B20+B15+B18+B28,0)} -> 821138 | C29: {=ROUND(B29/B11*100,0)%} -> 0.21
A31: Sin impuestos | B31: {=B11-B26-B16} -> 3831050 | C31: {=B31/'variables - Table 1'!B$13} -> 4319.4016 | D31: {=B31/'variables - Table 1'!$B$14} -> 3685.1548
A32: Sueldo líquido | B32: {=B11-B29} -> 3160654 | C32: {=B32/'variables - Table 1'!B$13} -> 3563.5488 | D32: {=B32/'variables - Table 1'!$B$14} -> 3040.289
A33: Dealing | B33: 0
A35: Ingreso líquido | B35: {=SUM(B32:B33)} -> 3160654
A37: Anual tributable | B37: {=B24*12} -> 38930412
A38: Anual líquido | B38: {=B35*12} -> 37927848 | C38: {=B38/'variables - Table 1'!B$13} -> 42762.586 | D38: {=B38/'variables - Table 1'!$B$14} -> 36483.468
B39: {=(B31)*12} -> 45972600 | C39: {=B39/'variables - Table 1'!B$13} -> 51832.819 | D39: {=B39/'variables - Table 1'!$B$14} -> 44221.857
A40: Anual bruto | B40: {=B11*12} -> 47781504 | C40: {=B40/'variables - Table 1'!B$13} -> 53872.307 | D40: {=B40/'variables - Table 1'!$B$14} -> 45961.873

Sheet presupuesto - Capacidad ahorro
A1: Capacidad ahorro
A2: Meses: | B2: 1 | C2: 3 | D2: 6 | E2: 12 | F2: 18 | G2: 24
A3: 0.1 | B3: {='presupuesto - Ingreso líquido'!$B$31*$A3*B$2} -> 383105 | C3: {=$B3*C$2} -> 1149315 | D3: {=$B3*D$2} -> 2298630 | E3: {=$B3*E$2} -> 4597260 | F3: {=$B3*F$2} -> 6895890.1 | G3: {=$B3*G$2} -> 9194520.1
A4: 0.2 | B4: {='presupuesto - Ingreso líquido'!$B$31*$A4*B$2} -> 766210.01 | C4: {=$B4*C$2} -> 2298630 | D4: {=$B4*D$2} -> 4597260 | E4: {=$B4*E$2} -> 9194520.1 | F4: {=$B4*F$2} -> 13791780 | G4: {=$B4*G$2} -> 18389040
A5: 0.5 | B5: {='presupuesto - Ingreso líquido'!$B$31*$A5*B$2} -> 1915525 | C5: {=$B5*C$2} -> 5746575.1 | D5: {=$B5*D$2} -> 11493150 | E5: {=$B5*E$2} -> 22986300 | F5: {=$B5*F$2} -> 34479450 | G5: {=$B5*G$2} -> 45972600
A6: 0.6 | B6: {='presupuesto - Ingreso líquido'!$B$31*$A6*B$2} -> 2298630 | C6: {=$B6*C$2} -> 6895890.1 | D6: {=$B6*D$2} -> 13791780 | E6: {=$B6*E$2} -> 27583560 | F6: {=$B6*F$2} -> 41375340 | G6: {=$B6*G$2} -> 55167121
A7: 0.7 | B7: {='presupuesto - Ingreso líquido'!$B$31*$A7*B$2} -> 2681735 | C7: {=$B7*C$2} -> 8045205.1 | D7: {=$B7*D$2} -> 16090410 | E7: {=$B7*E$2} -> 32180820 | F7: {=$B7*F$2} -> 48271231 | G7: {=$B7*G$2} -> 64361641
A9: {='presupuesto - Gastos'!E$35} -> 470920.29 | B9: {=$A9*B$2} -> 470920.29 | C9: {=$A9*C$2} -> 1412760.9 | D9: {=$A9*D$2} -> 2825521.7 | E9: {=$A9*E$2} -> 5651043.5 | F9: {=$A9*F$2} -> 8476565.2 | G9: {=$A9*G$2} -> 11302087
A10: {=AVERAGE('net worth - resumen | depósitos'!R44:R46)} -> 525158.67 | B10: {=$A10*B$2} -> 525158.67 | C10: {=$A10*C$2} -> 1575476 | D10: {=$A10*D$2} -> 3150952 | E10: {=$A10*E$2} -> 6301904 | F10: {=$A10*F$2} -> 9452856 | G10: {=$A10*G$2} -> 12603808
A11: {=AVERAGE('net worth - resumen | depósitos'!R56:R67)} -> -833717.83 | B11: {=$A11*B$2} -> -833717.83 | C11: {=$A11*C$2} -> -2501153.5 | D11: {=$A11*D$2} -> -5002307 | E11: {=$A11*E$2} -> -10004614 | F11: {=$A11*F$2} -> -15006921 | G11: {=$A11*G$2} -> -20009228
A13: 300000 | B13: {=$A13*B$2} -> 300000 | C13: {=$A13*C$2} -> 900000 | D13: {=$A13*D$2} -> 1800000 | E13: {=$A13*E$2} -> 3600000 | F13: {=$A13*F$2} -> 5400000 | G13: {=$A13*G$2} -> 7200000
A14: 400000 | B14: {=$A14*B$2} -> 400000 | C14: {=$A14*C$2} -> 1200000 | D14: {=$A14*D$2} -> 2400000 | E14: {=$A14*E$2} -> 4800000 | F14: {=$A14*F$2} -> 7200000 | G14: {=$A14*G$2} -> 9600000
A15: 500000 | B15: {=$A15*B$2} -> 500000 | C15: {=$A15*C$2} -> 1500000 | D15: {=$A15*D$2} -> 3000000 | E15: {=$A15*E$2} -> 6000000 | F15: {=$A15*F$2} -> 9000000 | G15: {=$A15*G$2} -> 12000000
A16: 600000 | B16: {=$A16*B$2} -> 600000 | C16: {=$A16*C$2} -> 1800000 | D16: {=$A16*D$2} -> 3600000 | E16: {=$A16*E$2} -> 7200000 | F16: {=$A16*F$2} -> 10800000 | G16: {=$A16*G$2} -> 14400000
A17: 700000 | B17: {=$A17*B$2} -> 700000 | C17: {=$A17*C$2} -> 2100000 | D17: {=$A17*D$2} -> 4200000 | E17: {=$A17*E$2} -> 8400000 | F17: {=$A17*F$2} -> 12600000 | G17: {=$A17*G$2} -> 16800000
A18: 800000 | B18: {=$A18*B$2} -> 800000 | C18: {=$A18*C$2} -> 2400000 | D18: {=$A18*D$2} -> 4800000 | E18: {=$A18*E$2} -> 9600000 | F18: {=$A18*F$2} -> 14400000 | G18: {=$A18*G$2} -> 19200000
A19: 900000 | B19: {=$A19*B$2} -> 900000 | C19: {=$A19*C$2} -> 2700000 | D19: {=$A19*D$2} -> 5400000 | E19: {=$A19*E$2} -> 10800000 | F19: {=$A19*F$2} -> 16200000 | G19: {=$A19*G$2} -> 21600000

Sheet presupuesto - APV - simulación 
A1: APV - simulación régimen B
A2: Tramos | C2: Tasa | E2: Cantidad afecta | F2: con APV | H2: impuesto | I2: con apv | K2: ∆
A3: 0.01 | B3: {=13.5*'variables - Table 1'!$B$3} -> 974538 | C3: 0 | E3: {=IF('presupuesto - Ingreso líquido'!$B$24>$A3,IF('presupuesto - Ingreso líquido'!$B$24>$B3,$B3-$A3,'presupuesto - Ingreso líquido'!$B$24-$A3),0)} -> 974537.99 | F3: {=IF('presupuesto - Ingreso líquido'!$B$24-B$11>$A3,IF('presupuesto - Ingreso líquido'!$B$24-B$11>$B3,$B3-$A3,'presupuesto - Ingreso líquido'!$B$24-B$11-$A3),0)} -> 974537.99 | H3: {=E3*$C3} -> 0 | I3: {=F3*$C3} -> 0 | K3: {=H3-I3} -> 0
A4: {=13.5*'variables - Table 1'!$B$3+0.01} -> 974538.01 | B4: {=30*'variables - Table 1'!$B$3} -> 2165640 | C4: 0.04 | E4: {=IF('presupuesto - Ingreso líquido'!$B$24>$A4,IF('presupuesto - Ingreso líquido'!$B$24>$B4,$B4-$A4,'presupuesto - Ingreso líquido'!$B$24-$A4),0)} -> 1191102 | F4: {=IF('presupuesto - Ingreso líquido'!$B$24-B$11>$A4,IF('presupuesto - Ingreso líquido'!$B$24-B$11>$B4,$B4-$A4,'presupuesto - Ingreso líquido'!$B$24-B$11-$A4),0)} -> 1191102 | H4: {=E4*$C4} -> 47644.08 | I4: {=F4*$C4} -> 47644.08 | K4: {=H4-I4} -> 0
A5: {=30*'variables - Table 1'!$B$3+0.01} -> 2165640 | B5: {=50*'variables - Table 1'!$B$3} -> 3609400 | C5: 0.08 | E5: {=IF('presupuesto - Ingreso líquido'!$B$24>$A5,IF('presupuesto - Ingreso líquido'!$B$24>$B5,$B5-$A5,'presupuesto - Ingreso líquido'!$B$24-$A5),0)} -> 1078561 | F5: {=IF('presupuesto - Ingreso líquido'!$B$24-B$11>$A5,IF('presupuesto - Ingreso líquido'!$B$24-B$11>$B5,$B5-$A5,'presupuesto - Ingreso líquido'!$B$24-B$11-$A5),0)} -> 685900.99 | H5: {=E5*C5} -> 86284.879 | I5: {=F5*C5} -> 54872.079 | K5: {=H5-I5} -> 31412.8
A6: {=50*'variables - Table 1'!$B$3} -> 3609400 | B6: {=70*'variables - Table 1'!$B$3} -> 5053160 | C6: 0.135 | E6: {=IF('presupuesto - Ingreso líquido'!$B$24>$A6,IF('presupuesto - Ingreso líquido'!$B$24>$B6,$B6-$A6,'presupuesto - Ingreso líquido'!$B$24-$A6),0)} -> 0 | F6: {=IF('presupuesto - Ingreso líquido'!$B$24-B$11>$A6,IF('presupuesto - Ingreso líquido'!$B$24-B$11>$B6,$B6-$A6,'presupuesto - Ingreso líquido'!$B$24-B$11-$A6),0)} -> 0 | H6: {=E6*C6} -> 0 | I6: {=F6*C6} -> 0 | K6: {=H6-I6} -> 0
A7: 4710580 | B7: 6056460 | C7: 0.23
A11: APV-b mensual | B11: 392660 | C11: {=B$11*12} -> 4711920 | H11: {=SUM(H3:H10)} -> 133928.96 | I11: {=SUM(I3:I10)} -> 102516.16 | K11: {=SUM(K3:K10)} -> 31412.8
I12: Anual | K12: {=K$11*12} -> 376953.6
A14: 15% máx APV-a | B14: {='net worth - Aporte APV'!B10} -> 240627 | C14: {='net worth - Aporte APV'!B10*15%} -> 36094.05

Sheet presupuesto - apv - rebaja impu
A1: apv - rebaja impuestos interés hipotecario
A2: tramos | C2: tasa | E2: cantidad afecta | F2: menos interés | H2: impuesto | I2: menos interés | K2: ∆
A3: 0.01 | B3: 8038926 | C3: 0 | E3: {=IF('presupuesto - Ingreso líquido'!$B$37>$A3,IF('presupuesto - Ingreso líquido'!$B$37>$B3,$B3-$A3,'presupuesto - Ingreso líquido'!$B$37-$A3),0)} -> 8038926 | F3: {=IF('presupuesto - Ingreso líquido'!$B$37-C$11>$A3,IF('presupuesto - Ingreso líquido'!$B$37-C$11>$B3,$B3-$A3,'presupuesto - Ingreso líquido'!$B$37-C$11-$A3),0)} -> 8038926 | H3: {=E3*$C3} -> 0 | I3: {=F3*$C3} -> 0 | K3: {=H3-I3} -> 0
A4: 8038926 | B4: 17864280 | C4: 0.04 | E4: {=IF('presupuesto - Ingreso líquido'!$B$37>$A4,IF('presupuesto - Ingreso líquido'!$B$37>$B4,$B4-$A4,'presupuesto - Ingreso líquido'!$B$37-$A4),0)} -> 9825354 | F4: {=IF('presupuesto - Ingreso líquido'!$B$37-C$11>$A4,IF('presupuesto - Ingreso líquido'!$B$37-C$11>$B4,$B4-$A4,'presupuesto - Ingreso líquido'!$B$37-C$11-$A4),0)} -> 9825354 | H4: {=E4*$C4} -> 393014.16 | I4: {=F4*$C4} -> 393014.16 | K4: {=H4-I4} -> 0
A5: {=17864280.01} -> 17864280 | B5: 29773800 | C5: 0.08 | E5: {=IF('presupuesto - Ingreso líquido'!$B$37>$A5,IF('presupuesto - Ingreso líquido'!$B$37>$B5,$B5-$A5,'presupuesto - Ingreso líquido'!$B$37-$A5),0)} -> 11909520 | F5: {=IF('presupuesto - Ingreso líquido'!$B$37-C$11>$A5,IF('presupuesto - Ingreso líquido'!$B$37-C$11>$B5,$B5-$A5,'presupuesto - Ingreso líquido'!$B$37-C$11-$A5),0)} -> 11909520 | H5: {=E5*C5} -> 952761.6 | I5: {=F5*C5} -> 952761.6 | K5: {=H5-I5} -> 0
A6: 29773800 | B6: 41683320 | C6: 0.135 | E6: {=IF('presupuesto - Ingreso líquido'!$B$37>$A6,IF('presupuesto - Ingreso líquido'!$B$37>$B6,$B6-$A6,'presupuesto - Ingreso líquido'!$B$37-$A6),0)} -> 9156612 | F6: {=IF('presupuesto - Ingreso líquido'!$B$37-C$11>$A6,IF('presupuesto - Ingreso líquido'!$B$37-C$11>$B6,$B6-$A6,'presupuesto - Ingreso líquido'!$B$37-C$11-$A6),0)} -> 4444779 | H6: {=E6*C6} -> 1236142.6 | I6: {=F6*C6} -> 600045.16 | K6: {=H6-I6} -> 636097.45
A7: 41683320 | B7: 53592840 | C7: 0.23 | E7: {=IF('presupuesto - Ingreso líquido'!$B$37>$A7,IF('presupuesto - Ingreso líquido'!$B$37>$B7,$B7-$A7,'presupuesto - Ingreso líquido'!$B$37-$A7),0)} -> 0 | F7: {=IF('presupuesto - Ingreso líquido'!$B$37-C$11>$A7,IF('presupuesto - Ingreso líquido'!$B$37-C$11>$B7,$B7-$A7,'presupuesto - Ingreso líquido'!$B$37-C$11-$A7),0)} -> 0
A11: APV-b mensual | B11: {=ROUND(C$11/12,0)} -> 392653 | C11: {=SUM('depto - dividendos'!BG17:BG27,'depto - dividendos'!BG15)} -> 4711833 | H11: {=SUM(H3:H10)} -> 2581918.4 | I11: {=SUM(I3:I10)} -> 1945820.9 | K11: {=SUM(K3:K10)} -> 636097.45
A12: o intereses
A14: 15% máx APV-a | B14: {='net worth - Aporte APV'!B10} -> 240627 | C14: {='net worth - Aporte APV'!B10*15%} -> 36094.05

Sheet flujos - Gasto mes actual
A1: Gasto mes actual
A2: Agosto | B2: Total diario | C2: Supermercado | G2: Carrete | K2: Comida | O2: Ropa | S2: Otros | W2: Drugs | Z2: Cuentas | AD2: Salud | AH2: Transporte | AL2: Dólares | AN2: Repasar esta columna
A3: 44409 | B3: {=SUM(C3:AI3)} -> 800000 | E3: FALSE | I3: FALSE | M3: FALSE | Q3: FALSE | U3: FALSE | Z3: hipotecario | AA3: {='depto - dividendos'!J22} -> 800000 | AB3: FALSE | AF3: FALSE | AH3: mobike | AI3: {=ROUND(AM3*'variables - Table 1'!$B$5,0)} -> 0 | AJ3: FALSE | AL3: mobike | AM3: 0 | AN3: {=ROUND(AM3*'variables - Table 1'!$B$5,0)} -> 0 | AO3: FALSE
A4: 44410 | B4: {=SUM(C4:AI4)} -> 80000 | E4: FALSE | I4: FALSE | M4: FALSE | Q4: FALSE | U4: FALSE | Z4: gastos comunes | AA4: 80000 | AB4: FALSE | AF4: FALSE | AH4: cabify | AI4: {=AN4} -> 0 | AJ4: FALSE | AL4: cabify | AN4: {=ROUND(AM4*'variables - Table 1'!$B$5,0)} -> 0 | AO4: FALSE
A5: 44411 | B5: {=SUM(C5:AI5)} -> 21000 | E5: FALSE | I5: FALSE | M5: FALSE | Q5: FALSE | U5: FALSE | Z5: entel | AA5: 21000 | AB5: FALSE | AF5: FALSE | AH5: costanera norte | AJ5: FALSE | AN5: {=ROUND(AM5*'variables - Table 1'!$B$5,0)} -> 0 | AO5: FALSE
A6: 44412 | B6: {=SUM(C6:AI6)} -> 7465 | E6: FALSE | I6: FALSE | M6: FALSE | Q6: FALSE | U6: FALSE | Z6: electricidad | AA6: {='flujos - Table 3-1-1'!D17} -> 7465 | AB6: FALSE | AF6: FALSE | AH6: vespucio sur | AJ6: FALSE | AL6: delivery | AM6: {=0} -> 0 | AN6: {=ROUND(AM6*'variables - Table 1'!$B$5,0)} -> 0 | AO6: FALSE
A7: 44413 | B7: {=SUM(C7:AI7)} -> 22352 | E7: FALSE | I7: FALSE | M7: FALSE | Q7: FALSE | U7: FALSE | Z7: gas | AA7: {='flujos - Table 3-1-1'!D62} -> 22352 | AB7: FALSE | AF7: FALSE | AH7: bencina | AJ7: FALSE | AL7: suscripciones | AM7: {=(4.34+2.43)*0} -> 0 | AN7: {=ROUND(AM7*'variables - Table 1'!$B$5,0)} -> 0 | AO7: FALSE
A8: 44414 | B8: {=SUM(C8:AI8)} -> 0 | E8: FALSE | I8: FALSE | M8: FALSE | Q8: FALSE | U8: FALSE | Z8: suscripciones | AA8: {=AN7} -> 0 | AB8: FALSE | AF8: FALSE | AH8: bip | AJ8: FALSE | AL8: amazon | AN8: {=ROUND(AM8*'variables - Table 1'!$B$5,0)} -> 0 | AO8: FALSE
A9: 44415 | B9: {=SUM(C9:AI9)} -> 0 | E9: FALSE | I9: FALSE | M9: FALSE | Q9: FALSE | U9: FALSE | AB9: FALSE | AF9: FALSE | AH9: estacionamiento | AJ9: FALSE | AN9: {=ROUND(AM9*'variables - Table 1'!$B$5,0)} -> 0 | AO9: FALSE
A10: 44416 | B10: {=SUM(C10:AI10)} -> 0 | E10: FALSE | I10: FALSE | M10: FALSE | Q10: FALSE | U10: FALSE | AB10: FALSE | AF10: FALSE | AJ10: FALSE | AN10: {=ROUND(AM10*'variables - Table 1'!$B$5,0)} -> 0 | AO10: FALSE
A11: 44417 | B11: {=SUM(C11:AI11)} -> 0 | E11: FALSE | I11: FALSE | M11: FALSE | Q11: FALSE | U11: FALSE | AB11: FALSE | AF11: FALSE | AJ11: FALSE | AN11: {=ROUND(AM11*'variables - Table 1'!$B$5,0)} -> 0 | AO11: FALSE
A12: 44418 | B12: {=SUM(C12:AI12)} -> 0 | E12: FALSE | I12: FALSE | M12: FALSE | Q12: FALSE | U12: FALSE | AB12: FALSE | AF12: FALSE | AJ12: FALSE | AO12: FALSE
A13: 44419 | B13: {=SUM(C13:AI13)} -> 0 | E13: FALSE | I13: FALSE | M13: FALSE | Q13: FALSE | U13: FALSE | AB13: FALSE | AF13: FALSE | AJ13: FALSE | AN13: {=ROUND(AM13*'variables - Table 1'!$B$5,0)} -> 0 | AO13: FALSE
A14: 44420 | B14: {=SUM(C14:AI14)} -> 0 | E14: FALSE | I14: FALSE | M14: FALSE | Q14: FALSE | U14: FALSE | AB14: FALSE | AF14: FALSE | AJ14: FALSE | AN14: {=ROUND(AM14*'variables - Table 1'!$B$5,0)} -> 0 | AO14: FALSE
A15: 44421 | B15: {=SUM(C15:AI15)} -> 0 | E15: FALSE | I15: FALSE | M15: FALSE | Q15: FALSE | U15: FALSE | AB15: FALSE | AF15: FALSE | AJ15: FALSE | AN15: {=ROUND(AM15*'variables - Table 1'!$B$5,0)} -> 0 | AO15: FALSE
A16: 44422 | B16: {=SUM(C16:AI16)} -> 0 | E16: FALSE | I16: FALSE | M16: FALSE | Q16: FALSE | U16: FALSE | AB16: FALSE | AF16: FALSE | AJ16: FALSE | AN16: {=ROUND(AM16*'variables - Table 1'!$B$5,0)} -> 0 | AO16: FALSE
A17: 44423 | B17: {=SUM(C17:AI17)} -> 0 | E17: FALSE | I17: FALSE | M17: FALSE | Q17: FALSE | U17: FALSE | AB17: FALSE | AF17: FALSE | AJ17: FALSE | AN17: {=ROUND(AM17*'variables - Table 1'!$B$5,0)} -> 0 | AO17: FALSE
A18: 44424 | B18: {=SUM(C18:AI18)} -> 0 | E18: FALSE | I18: FALSE | M18: FALSE | Q18: FALSE | U18: FALSE | AB18: FALSE | AF18: FALSE | AJ18: FALSE | AN18: {=ROUND(AM18*'variables - Table 1'!$B$5,0)} -> 0 | AO18: FALSE
A19: 44425 | B19: {=SUM(C19:AI19)} -> 0 | E19: FALSE | I19: FALSE | M19: FALSE | Q19: FALSE | U19: FALSE | AB19: FALSE | AF19: FALSE | AJ19: FALSE | AN19: {=ROUND(AM19*'variables - Table 1'!$B$5,0)} -> 0 | AO19: FALSE
A20: 44426 | B20: {=SUM(C20:AI20)} -> 0 | E20: FALSE | I20: FALSE | M20: FALSE | Q20: FALSE | U20: FALSE | AB20: FALSE | AF20: FALSE | AJ20: FALSE | AN20: {=ROUND(AM20*'variables - Table 1'!$B$5,0)} -> 0 | AO20: FALSE
A21: 44427 | B21: {=SUM(C21:AI21)} -> 0 | E21: FALSE | I21: FALSE | M21: FALSE | Q21: FALSE | U21: FALSE | AB21: FALSE | AF21: FALSE | AJ21: FALSE | AN21: {=ROUND(AM21*'variables - Table 1'!$B$5,0)} -> 0 | AO21: FALSE
A22: 44428 | B22: {=SUM(C22:AI22)} -> 0 | E22: FALSE | I22: FALSE | M22: FALSE | Q22: FALSE | U22: FALSE | AB22: FALSE | AF22: FALSE | AJ22: FALSE | AN22: {=ROUND(AM22*'variables - Table 1'!$B$5,0)} -> 0 | AO22: FALSE
A23: 44429 | B23: {=SUM(C23:AI23)} -> 0 | E23: FALSE | I23: FALSE | M23: FALSE | Q23: FALSE | U23: FALSE | AB23: FALSE | AF23: FALSE | AJ23: FALSE | AN23: {=ROUND(AM23*'variables - Table 1'!$B$5,0)} -> 0 | AO23: FALSE
A24: 44430 | B24: {=SUM(C24:AI24)} -> 0 | E24: FALSE | I24: FALSE | M24: FALSE | Q24: FALSE | U24: FALSE | AB24: FALSE | AF24: FALSE | AJ24: FALSE | AN24: {=ROUND(AM24*'variables - Table 1'!$B$5,0)} -> 0 | AO24: FALSE
... A34: 44440 | B34: {=SUM(C34:AI34)} -> 0 | E34: FALSE | I34: FALSE | M34: FALSE | Q34: FALSE | U34: FALSE | AB34: FALSE | AF34: FALSE | AJ34: FALSE | AN34: {=ROUND(AM34*'variables - Table 1'!$B$5,0)} -> 0 | AO34: FALSE
E35: FALSE | I35: FALSE | M35: FALSE | Q35: FALSE | U35: FALSE | AB35: FALSE | AD35: Isapre | AE35: {='presupuesto - Ingreso líquido'!$D$19*0} -> 0 | AJ35: FALSE | AM35: Diferencia | AN35: {=SUM(AN3:AN34,-AN$37)} -> 0 | AO35: FALSE
E36: FALSE | I36: FALSE | M36: FALSE | Q36: FALSE | U36: FALSE | AB36: FALSE | AJ36: FALSE | AO36: FALSE
B37: {=SUM(B3:B34)+AE35} -> 930817 | C37: Supermercado | D37: {=SUM(D3:D36)} -> 0 | G37: Carrete | H37: {=SUM(H3:H36)} -> 0 | K37: Almuerzo | L37: {=SUM(L3:L36)} -> 0 | O37: Ropa | P37: {=SUM(P3:P36)} -> 0 | S37: Otros | T37: {=SUM(T3:T36)} -> 0 | W37: Mota | X37: {=SUM(X3:X36)} -> 0 | Z37: Cuentas | AA37: {=SUM(AA3:AA36)} -> 930817 | AD37: Salud | AE37: {=SUM(AE3:AE36)} -> 0 | AH37: Transporte | AI37: {=SUM(AI3:AI36)} -> 0 | AL37: Dólares | AM37: {=SUM(AM3:AM34)} -> 0 | AN37: {=ROUND(AM37*'variables - Table 1'!$B$5,0)} -> 0

Sheet flujos - Table 1-3
D1: febrero | E1: {=SUM(D2:D118)} -> 8638334
A4: 12/12/2024 | C4: 8 BITS | D4: 49990
A5: 07/02/2025 | C5: AGUA LUNA | D5: 23900
A6: 06/02/2025 | C6: AHUM L272 LOS LEONES 1160 | D6: 31534
C7: AHUM L526 ALC.INFANT 1541 | D7: 24094
C8: ALANA | D8: 1500
C9: ALMACENES BILBAO | D9: 4530
A10: 05/02/2025 | C10: ALMACENES BILBAO | D10: 2010
A11: 04/02/2025 | C11: ALMACENES BILBAO | D11: 2020
C12: ALMACENES BILBAO | D12: 5200
A13: 21/02/2025 | C13: APOTECARIO VAPE SHOP | D13: 30000
A14: 05/12/2024 | C14: APPLE.COM CL APPLE | D14: 22664
A15: 03/12/2024 | C15: APPLE.COM CL APPLE | D15: 9166
C16: APPLE.COM CL APPLE | D16: 9166
C17: APPLE.COM CL APPLE | D17: 9166
A18: 12/02/2025 | C18: B-1326 PENALOLEN | D18: 19400
A19: 23/01/2025 | C19: BEE MARKET | D19: 3450
C20: BOTILLERIA LA MALTIT | D20: 3300
A21: 22/02/2025 | C21: BOTILLERIA PORTEZUELO | D21: 4400
A22: 10/02/2025 | C22: CARNES LOS PLOMOS | D22: 8796
A23: 15/02/2025 | C23: COPEC APP | D23: 30000
C24: CORP. CULTURAL DE LA ESTA | D24: 5000
C25: DANIELA ANDREA GARCIA YAN | D25: 13800
C26: ENEL | D26: 64832
C27: ENTEL HOGAR | D27: 21990
C28: EXPRESS PLAZA LYON | D28: 33203
C29: FU XING | D29: 3000
C30: GOOGLE PLAY YOUTUBE | D30: 9200
A31: 4/02/2025 | C31: INTERESES | D31: 735
C32: JACK&JONES OPEN PLAZA | D32: 9240
A33: 28/01/2025 | C33: JUMBO COSTANERA CENTER | D33: 26876
A34: 24/01/2025 | C34: JUMBO COSTANERA CENTER | D34: 9394
C35: LA CABRERA ISIDORA | D35: 159950
A36: 20/01/2025 | C36: LATAM.COM XP INTER | D36: 618677
C37: LONDON COFFEE ALCANTARA | D37: 5460
C38: LONDON COFFEE ALCANTARA | D38: 5460
C39: LONDON COFFEE ALCANTARA | D39: 5460
C40: LONDON COFFEE ALCANTARA | D40: 5460
A41: 17/02/2025 | C41: LONDON COFFEE ALCANTARA | D41: 4680
A42: 30/01/2025 | C42: LONDON COFFEE ALCANTARA | D42: 5460
C43: LONDON COFFEE ALCANTARA | D43: 5460
C44: LONDON COFFEE ALCANTARA | D44: 5460
A45: 27/01/2025 | C45: LONDON COFFEE ALCANTARA | D45: 4680
C46: LONDON COFFEE ALCANTARA | D46: 3150
C47: LONDON COFFEE ALCANTARA | D47: 5460
C48: LYON 1 | D48: 5680
C49: LYON 1 | D49: 2100
C50: LYON 1 | D50: 5090
C51: LYON 1 | D51: 1990
A52: 26/01/2025 | C52: LYON 1 | D52: 2100
C53: MERCADO PAGO 4 TCOM | D53: 35833
A54: 21/12/2024 | C54: MERCADO PAGO 4 TCOM | D54: 8495
C55: MERCADOPAGO*MARIN | D55: 23740
C56: MERCADOPAGO*PUBLIKT | D56: 29000
C57: MERPAGO*BAZO SPA BAZO SP | D57: 6000
C58: MERPAGO*COMERCIAL GIOVAN | D58: 15000
C59: MERPAGO*MICOCACOLA | D59: 21670
A60: 31/01/2025 | C60: MERPAGO*MICOCACOLA | D60: 21681
C61: MERPAGO*MR PRETZELS ASES | D61: 5300
C62: MERPAGO*ST LOUIS FACTORY | D62: 14980
C63: MERPAGO*STREAT BURGER ME | D63: 24950
A64: 02/02/2025 | C64: MERPAGO*STREAT BURGER ME | D64: 24500
C65: MERPAGO*TAPROOM UNO TAPR | D65: 32670
C66: MERPAGO*TOLIVMARKETSPA | D66: 11190
C67: MONTO CANCELADO | E67: 3021683
C68: MP *LA DICHA | D68: 64050
C69: MP *MERCADO LIBRE | D69: 9165
A70: 27/11/2024 | C70: MP *MERCADO LIBRE | D70: 16260
A71: 22/12/2024 | C71: MP *MICOCA COLACL | D71: 2889
C72: MUTUARIA | D72: 3072815
C73: MUTUARIA | D73: 3071622
C74: MY SWEET 39 | D74: 8000
C75: OKM SUECIA | D75: 1990
C76: PARIS PARQUE ARAUCO | D76: 6990
C77: PASS LINE LTDA | D77: 29900
A78: 23/02/2025 | C78: PAYU *UBER EATS | D78: 17484
A79: 18/02/2025 | C79: PAYU *UBER EATS | E79: 1473
C80: PAYU *UBER EATS | E80: 36448
A81: 16/02/2025 | C81: PAYU *UBER EATS | D81: 9629
C82: PAYU *UBER EATS | E82: 1998
C83: PAYU *UBER EATS | E83: 57266
A84: 11/02/2025 | C84: PAYU *UBER EATS | D84: 9629
C85: PAYU *UBER EATS | D85: 9629
A86: 29/01/2025 | C86: PAYU *UBER EATS | D86: 8223
A87: 25/01/2025 | C87: PAYU *UBER EATS | E87: 1735
C88: PAYU *UBER EATS | E88: 47697
C89: PAYU *UBER TRIP | D89: 5763
A90: 08/02/2025 | C90: PUNTO TICKET WEB | D90: 57500
C91: REGISTROCIVIL PROVIDENCIA | D91: 69660
C92: RESTAURANT DON CARLOS | D92: 103740
C93: SALCOBRAND LOS LEONES | D93: 4221
A94: 19/02/2025 | C94: SERVICIOS Y COMERCIAL RA | D94: 2450
C95: STA ISABEL MAIPU PARQ | D95: 15846
A96: 01/02/2025 | C96: STA ISABEL MAIPU PARQ | D96: 30487
C97: SumUp * FARMACIAS LAFO | D97: 19500
A98: 22/01/2025 | C98: SUPERMERCADO LAS VIOLETAS | D98: 4990
A99: 14/02/2025 | C99: SUSHI HANAMI | D99: 12500
A100: 23/12/2024 | C100: TOALLAS LOURDES | D100: 17253
C101: TOTTUS KENNEDY II | D101: 28220
A102: 20/02/2025 | C102: TUU*almacenElAlcazar | D102: 5900
...

Sheet flujos - Table 1-2
D1: enero | E1: {=SUM(D2:D118)} -> 3021683
A4: 12/12/2024 | C4: 8 BITS | D4: 49990
C5: AGUA LUNA | D5: 23900
C6: AHUM L272 LOS LEONES 1160 | D6: 42710
C7: ALMACENES BILBAO | D7: 2720
C8: ALMACENES BILBAO | D8: 3130
A9: 18/01/2025 | C9: ALMACENES BILBAO | D9: 1650
C10: ALMACENES BILBAO | D10: 3510
A11: 17/01/2025 | C11: ALMACENES BILBAO | D11: 2230
C12: ALMACENES BILBAO | D12: 3380
A13: 11/01/2025 | C13: ALMACENES BILBAO | D13: 4050
A14: 10/01/2025 | C14: ALMACENES BILBAO | D14: 3500
C15: ALMACENES BILBAO | D15: 2930
A16: 08/01/2025 | C16: ALMACENES BILBAO | D16: 2400
A17: 07/01/2025 | C17: ALMACENES BILBAO | D17: 1860
A18: 06/01/2025 | C18: ALMACENES BILBAO | D18: 1330
A19: 03/01/2025 | C19: ALMACENES BILBAO | D19: 3120
C20: ALMACENES BILBAO | D20: 1250
C21: ALMACENES BILBAO | D21: 1800
A22: 24/12/2024 | C22: ALMACENES BILBAO | D22: 7250
A23: 23/12/2024 | C23: ALMACENES BILBAO | D23: 3260
C24: ALTO LAS CONDES | D24: 14500
C25: ANTARTICA COSTANERA H2H | D25: 11090
A26: 05/12/2024 | C26: APPLE.COM CL APPLE | D26: 22663
A27: 03/12/2024 | C27: APPLE.COM CL APPLE | D27: 9166
C28: APPLE.COM CL APPLE | D28: 9166
C29: APPLE.COM CL APPLE | D29: 9166
C30: C. VERDE PROVIDENC 2594 | D30: 3890
C31: CARNES LOS PLOMOS | D31: 10667
A32: 25/12/2024 | C32: COMERCIAL MAHO LIMITADA | D32: 20000
C33: COPEC APP | D33: 53580
C34: COPEC PROVIDENCIA | D34: 4400
C35: ENCANTI | D35: 10651
C36: ENEL | D36: 42263
A37: 20/12/2024 | C37: ENEL | D37: 32998
C38: ENTEL HOGAR | D38: 12990
A39: 14/01/2025 | C39: EXPRESS PLAZA LYON | D39: 16131
C40: EXPRESS PLAZA LYON | D40: 29270
A41: 28/12/2024 | C41: EXPRESS PLAZA LYON | D41: 39660
A42: 16/01/2025 | C42: FALABELLA ALTO LAS CONDES | D42: 4000
C43: FALABELLA ALTO LAS CONDES | D43: 3480
C44: FARM AHUMADA SPA L717 | D44: 12297
A45: 12/01/2025 | C45: FRUTERRA SPA | D45: 5428
C46: GALLETERIA DE LAURA R | D46: 23200
A47: 15/01/2025 | C47: GOOGLE PLAY YOUTUBE | D47: 9200
A48: 01/01/2025 | C48: GRUPO AYRES SPA | D48: 5000
C49: GRUPO AYRES SPA | D49: 5000
C50: JUMBO COSTANERA CENTER | D50: 73977
C51: JUMBO COSTANERA CENTER | D51: 31447
C52: JUMBO COSTANERA CENTER | D52: 92906
A53: 27/12/2024 | C53: JUMBO COSTANERA CENTER | D53: 57177
C54: LA DICHA | D54: 55440
C55: LATAM.COM XP INTER | D55: 618677
C56: LONDON COFFEE ALCANTARA | D56: 5460
C57: LONDON COFFEE ALCANTARA | D57: 4680
C58: LONDON COFFEE ALCANTARA | D58: 5460
C59: LONDON COFFEE ALCANTARA | D59: 5460
C60: LONDON COFFEE ALCANTARA | D60: 5866
C61: LONDON COFFEE ALCANTARA | D61: 8190
C62: LONDON COFFEE ALCANTARA | D62: 4680
C63: LONDON COFFEE ALCANTARA | D63: 5460
C64: LONDON COFFEE ALCANTARA | D64: 4550
C65: LONDON COFFEE ALCANTARA | D65: 5460
... C72: LONDON COFFEE ALCANTARA | D72: 3600
A73: 21/01/2025 | C73: LYON 1 | D73: 1990
C74: LYON 1 | D74: 2980
C75: LYON 1 | D75: 8890
C76: MERCADO PAGO 4 TCOM | D76: 8495
A77: 21/12/2024 | C77: MERCADOPAGO*PUBLIKT | D77: 29000
A78: 29/12/2024 | C78: MERPAGO*MCDONALDS | D78: 18830
A79: 20/01/2025 | C79: MERPAGO*MICOCACOLA | D79: 31836
A80: 09/01/2025 | C80: MERPAGO*MICOCACOLA | D80: 38540
C81: MERPAGO*V CARUSI V CARUS | D81: 13000
C82: METROGAS PAT | D82: 13762
A83: 30/12/2024 | C83: MONTO CANCELADO | E83: 5240425
C84: MP *LA DICHA | D84: 105070
A85: 27/11/2024 | C85: MP *MERCADO LIBRE | D85: 16260
A86: 22/12/2024 | C86: MP *MICOCA COLACL | D86: 2889
A87: 26/12/2024 | C87: OKM SUECIA | D87: 6140
C88: PARIS ALTO LAS CONDES | D88: 7990
C89: PARKING ALTO LAS CONDES | D89: 950
C90: PARKING COSTANERA | D90: 2700
C91: PASS LINE LTDA | D91: 29900
C92: PAYU *UBER EATS | D92: 8223
A93: 13/01/2025 | C93: PAYU *UBER EATS | D93: 38732
C94: PAYU *UBER EATS | D94: 1314
C95: PAYU *UBER EATS | D95: 29537
A96: 04/01/2025 | C96: PAYU *UBER EATS | D96: 37888
C97: PAYU *UBER EATS | D97: 1388
C98: PAYU *UBER EATS | D98: 12078
C99: PAYU *UBER EATS | D99: 3841
C100: PAYU *UBER EATS | D100: 1591
A101: 02/01/2025 | C101: PAYU *UBER EATS | D101: 5401
C102: PAYU *UBER EATS | D102: 1129
C103: PAYU *UBER EATS | D103: 49178
C104: PAYU *UBER EATS | D104: 1660
C105: PAYU *UBER TRIP | D105: 16786
C106: PICANTERIA | D106: 88340
C107: PICANTERIA | D107: 79240
C108: PRT LAS CONDES 2508 | D108: 4440
...

Sheet flujos - Table 1-4
D1: marzo | E1: {=SUM(D2:D118)} -> 5445661
C3: AHUM L272 LOS LEONES 1160 | D3: 15799
C4: AHUM L272 LOS LEONES 1160 | D4: 8499
C5: APOTECARIO VAPE SHOP | D5: 23000
A6: 03/12/2024 | C6: APPLE.COM CL APPLE | D6: 9166
C7: APPLE.COM CL APPLE | D7: 9166
C8: APPLE.COM CL APPLE | D8: 9166
A9: 10/03/2025 | C9: AUTOSERVICIO CL ALEMANA | D9: 10281
C10: BELLAS ARTES EXPRESS | D10: 1300
C11: BELLAS ARTES EXPRESS | D11: 2870
A12: 09/03/2025 | C12: CALVIN KLEIN PARQUE | D12: 49980
C13: CHICKEN FACTORY | D13: 19980
A14: 21/03/2025 | C14: COPEC APP | D14: 20000
C15: COPEC APP | D15: 49077
C16: COPEC APP | D16: 4580
A17: 27/02/2025 | C17: COPEC APP | D17: 52154
C18: DL*BOOKINGCOM | D18: 98304
C19: ENEL | D19: 60849
A20: 13/03/2025 | C20: ENTEL HOGAR | D20: 21990
A21: 15/03/2025 | C21: EXPRESS AVDA VALPARAI | D21: 32110
C22: EXPRESS AVDA VALPARAI | D22: 10820
A23: 26/02/2025 | C23: FLOW *PINARES.CL | D23: 200000
C24: GOOGLE PLAY YOUTUBE CL | D24: 9200
C25: HAULMER*LA BOTISHOP | D25: 800
A26: 25/03/2025 | C26: INTERESES | D26: 105
C27: JUMBO ALTO LAS CONDES | D27: 42627
C28: JUMBO ALTO LAS CONDES | D28: 36561
C29: JUMBO ALTO LAS CONDES | D29: 20900
C30: JUMBO ALTO LAS CONDES | D30: 35552
C31: JUMBO COSTANERA CENTER | D31: 32142
C32: JUMBO COSTANERA CENTER | D32: 46162
C33: LA CABRERA ISIDORA | D33: 143940
A34: 20/01/2025 | C34: LATAM.COM XP INTER | D34: 618676
A35: 24/03/2025 | C35: LONDON COFFEE ALCANTARA | D35: 4680
C36: LONDON COFFEE ALCANTARA | D36: 5460
A37: 20/03/2025 | C37: LONDON COFFEE ALCANTARA | D37: 8603
A38: 19/03/2025 | C38: LONDON COFFEE ALCANTARA | D38: 5460
C39: LONDON COFFEE ALCANTARA | D39: 5460
C40: LONDON COFFEE ALCANTARA | D40: 4680
C41: LONDON COFFEE ALCANTARA | D41: 5460
C42: LONDON COFFEE ALCANTARA | D42: 5460
C43: LONDON COFFEE ALCANTARA | D43: 4193
A44: 12/03/2025 | C44: LONDON COFFEE ALCANTARA | D44: 5460
C45: LONDON COFFEE ALCANTARA | D45: 5460
C46: LONDON COFFEE ALCANTARA | D46: 4680
C47: LONDON COFFEE ALCANTARA | D47: 5460
C48: LONDON COFFEE ALCANTARA | D48: 5460
C49: LONDON COFFEE ALCANTARA | D49: 5460
A50: 04/03/2025 | C50: LONDON COFFEE ALCANTARA | D50: 5460
A51: 03/03/2025 | C51: LONDON COFFEE ALCANTARA | D51: 4680
C52: LONDON COFFEE ALCANTARA | D52: 5866
C53: LONDON COFFEE ALCANTARA | D53: 5460
A54: 25/02/2025 | C54: LONDON COFFEE ALCANTARA | D54: 5460
C55: LONDON COFFEE ALCANTARA | D55: 4680
A56: 05/03/2025 | C56: LYON 1 | D56: 4480
C57: LYON 1 | D57: 3200
C58: MERCADO PAGO 4 TCOM | D58: 22498
C59: MERCADO PAGO 4 TCOM | D59: 63665
A60: 27/01/2025 | C60: MERCADO PAGO 4 TCOM | D60: 35833
C61: MERCADO PAGO 4 TCOM | D61: 8495
C62: MERCADOPAGO*2PRODUCTOS | D62: 8865
C63: MERCADOPAGO*2PRODUCTOS | D63: 6860
C64: MERCADOPAGO*ARCOSDEVALPAR | D64: 14080
C65: MERCADOPAGO*MCDONALDS | D65: 5990
A66: 21/12/2024 | C66: MERCADOPAGO*PUBLIKT | D66: 29000
A67: 17/03/2025 | C67: MERPAGO*PAPA JOHNS PJ CH | D67: 6690
A68: 14/03/2025 | C68: MERPAGO*PAPA JOHNS PJ CH | D68: 6690
A69: 07/03/2025 | C69: MERPAGO*PUBLIKT | D69: 120000
C70: MERPAGO*STREAT BURGER ME | D70: 28950
A71: 22/03/2025 | C71: MERPAGO*STREAT BURGER MEE | D71: 31260
C72: METROGAS PAT | D72: 18051
C73: MK WEBPAY.CL | D73: 125853
C74: MONTO CANCELADO | E74: 2784951
C75: MONTO CANCELADO | E75: 3000000
C76: MONTO CANCELADO | E76: 3000000
C77: MP *MERCADO LIBRE | D77: 52163
A78: 22/12/2024 | C78: MP *MICOCA COLACL | D78: 2889
C79: MUNICIPALIDAD DE VITACURA | D79: 13050
A80: 11/03/2025 | C80: MUTUARIA | D80: 2133674
C81: NINTENDO OF AMERICA | D81: 40990
C82: NOTA DE CREDITO | D82: 5431
A83: 07/02/2025 | C83: NOTA DE CREDITO | D83: 54990
C84: OKM SUECIA | D84: 2500
C85: PANCAKE SPA | D85: 2400
C86: PARKING ALTO LAS CONDES | D86: 350
C87: PARKING ALTO LAS CONDES | D87: 350
C88: PARKING ALTO LAS CONDES | D88: 350
C89: PARKING ALTO LAS CONDES | D89: 350
C90: PASS LINE LTDA | D90: 29900
C91: PAYU *UBER EATS | D91: 1289
C92: PAYU *UBER EATS | D92: 12890
A93: 06/03/2025 | C93: PAYU *UBER EATS | D93: 13214
C94: PAYU *UBER EATS | E94: 3216
C95: PAYU *UBER EATS | E95: 25117
A96: 24/02/2025 | C96: PAYU *UBER EATS | E96: 2026
C97: PAYU *UBER EATS | E97: 60112
C98: PESCADOS CAPITALES | D98: 165970
C99: PREPAGO EN CUOTAS | D99: 45825
C100: ROCA WEBPAY | D100: 73428
A101: 23/03/2025 | C101: SALCOBRAND AV. LAS CON | D101: 52598
...

Sheet flujos - Table 3-1-1
D1: mayo | E1: {=SUM(D2:D118)} -> 4395731
C3: ALMACENES BILBAO | D3: 2200
C4: ALMACENES BILBAO | D4: 2700
A5: 03/12/2024 | C5: APPLE.COM CL APPLE | D5: 9166
C6: APPLE.COM CL APPLE | D6: 9166
C7: APPLE.COM CL APPLE | D7: 9166
C8: AUTOSERVICIO CL ALEMANA | D8: 5512
C9: CK ECOMMERCE | D9: 79980
A10: 29/04/2025 | C10: CK ECOMMERCE | D10: 39990
A11: 10/05/2025 | C11: COPEC APP | D11: 53571
C12: DANIELA ANDREA GARCIA YAN | D12: 13800
A13: 28/04/2025 | C13: EASY COSTANERA CENTER | D13: 150
C14: EASY COSTANERA CENTER | D14: 1900
C15: EASY COSTANERA CENTER | D15: 18170
C16: EASY INTERNET | D16: 33481
A17: 22/04/2025 | C17: ENEL | D17: 7465
C18: ENTEL HOGAR | D18: 21990
C19: EXPRESS PLAZA LYON | D19: 4980
A20: 07/05/2025 | C20: EXPRESS PLAZA LYON | D20: 17100
C21: EXPRESS PLAZA LYON | D21: 24460
C22: FABRICA | D22: 8000
C23: FLOW *PINARES.CL | D23: 200000
A24: 15/05/2025 | C24: GOOGLE PLAY YOUTUBE CL | D24: 11000
C25: IKEA OPEN KENNEDY | D25: 9970
A26: 22/05/2025 | C26: INTERESES | D26: 1896
C27: INVERSIONES MONASTRELL WI | D27: 97650
A28: 21/05/2025 | C28: JUMBO COSTANERA CENTER | D28: 27401
A29: 17/05/2025 | C29: JUMBO COSTANERA CENTER | D29: 9724
C30: JUMBO COSTANERA CENTER | D30: 21695
C31: JUMBO COSTANERA CENTER | D31: 46128
C32: JUMBO COSTANERA CENTER | D32: 65514
A33: 04/05/2025 | C33: JUMBO COSTANERA CENTER | D33: 52400
C34: JUMBO COSTANERA CENTER | D34: 44885
A35: 26/04/2025 | C35: JUMBO COSTANERA CENTER | D35: 44055
C36: JUMBO COSTANERA CENTER | D36: 34246
C37: LONDON COFFEE ALCANTARA | D37: 5460
C38: LONDON COFFEE ALCANTARA | D38: 5460
C39: LONDON COFFEE ALCANTARA | D39: 5460
C40: LONDON COFFEE ALCANTARA | D40: 6300
C41: LONDON COFFEE ALCANTARA | D41: 5460
A42: 06/05/2025 | C42: LONDON COFFEE ALCANTARA | D42: 5460
A43: 05/05/2025 | C43: LONDON COFFEE ALCANTARA | D43: 4680
A44: 30/04/2025 | C44: LONDON COFFEE ALCANTARA | D44: 5460
C45: LONDON COFFEE ALCANTARA | D45: 5460
C46: LONDON COFFEE ALCANTARA | D46: 5460
C47: LONDON COFFEE ALCANTARA | D47: 9660
C48: LYON 1 | D48: 1990
C49: LYON 1 | D49: 3980
A50: 12/05/2025 | C50: LYON 1 | D50: 1990
C51: MC DONALDS PROVIDENCIA 3 | D51: 6290
A52: 06/03/2025 | C52: MERCADO PAGO 4 TCOM | D52: 22498
C53: MERCADO PAGO 4 TCOM | D53: 63665
A54: 27/01/2025 | C54: MERCADO PAGO 4 TCOM | D54: 35833
A55: 21/12/2024 | C55: MERCADO PAGO 4 TCOM | D55: 8495
A56: 11/05/2025 | C56: MERPAGO*GLOVOX GLOVOX PRO | D56: 2500
A57: 13/05/2025 | C57: MERPAGO*MICOCACOLA | D57: 22870
A58: 27/04/2025 | C58: MERPAGO*MICOCACOLA | D58: 21670
C59: MERPAGO*STREAT BURGER MEE | D59: 8290
C60: MERPAGO*V CARUSI V CARUSI | D60: 14500
C61: METLIFE CHILE SEGUROS DE | D61: 1565558
C62: METROGAS PAT | D62: 22352
C63: MK WEBPAY.CL | D63: 125853
A64: 08/05/2025 | C64: MONTO CANCELADO | E64: 3746116
A65: 26/02/2025 | C65: MP *MERCADO LIBRE | D65: 52163
A66: 22/12/2024 | C66: MP *MICOCA COLACL | D66: 2891
A67: 20/05/2025 | C67: ORTODONCIAGO SPA | D67: 125000
C68: PARIS COSTANERA CENTER | D68: 193600
A69: 03/05/2025 | C69: PASS LINE LTDA | D69: 39100
C70: PAYU *UBER EATS | D70: 6785
A71: 02/05/2025 | C71: PAYU *UBER EATS | D71: 12863
C72: PAYU *UBER TRIP | D72: 10943
C73: PUNTO TICKET WEB | D73: 59750
C74: RESTAURANT DON CARLOS | D74: 137130
C75: RESTAURANT DON CARLOS | D75: 145950
A76: 27/02/2025 | C76: ROCA WEBPAY | D76: 73428
A77: 19/05/2025 | C77: SALCOBRAND LOS LEONES | D77: 6199
A78: 09/05/2025 | C78: SALCOBRAND LOS LEONES | D78: 52896
A79: 23/04/2025 | C79: SERVICIOS Y COMERCIAL RAU | D79: 5380
C80: SUMUP * HANS CORNEJO | D80: 15000
A81: 14/05/2025 | C81: TGR | D81: 43525
C82: TGR | D82: 90033
A83: 25/04/2025 | C83: UBER EATS | D83: 20553
A84: 10/01/2025 | C84: VISTA LIBRE | D84: 275697
C85: WORK CAFE GERTRUDIS ECHEN | D85: 4680

Sheet flujos - Table 3-1-1-1
D1: {=SUM(D2:D118)} -> 4490361
A2: 13/06/2025 | C2: ALMACENES BILBAO | D2: 2680
C3: ALMACENES BILBAO | D3: 5240
A4: 26/05/2025 | C4: ALMACENES BILBAO | D4: 1360
A5: 03/12/2024 | C5: APPLE.COM CL APPLE | D5: 9166
C6: APPLE.COM CL APPLE | D6: 9166
C7: APPLE.COM CL APPLE | D7: 9166
A8: 03/06/2025 | C8: BOOKING.COM | D8: 210132
C9: DOCKERS COSTANERA CENTER | D9: 44990
A10: 23/05/2025 | C10: ENEL | D10: 42655
C11: ENTEL HOGAR | D11: 21990
C12: EXPRESS PLAZA LYON | D12: 8758
A13: 10/06/2025 | C13: FLOW *PINARES.CL | D13: 200000
A14: 27/05/2025 | C14: FLOW *PINARES.CL | D14: 200000
C15: GOOGLE PLAY YOUTUBE CL | D15: 11000
C16: IBERIA OPERADORA SA TCOMP | D16: 30000
C17: IMPTO. DECRETO LEY 3475 | D17: 1063
A18: 23/06/2025 | C18: INTERESES | D18: 1818
C19: INVERSIONES EL PARRON SA | D19: 4800
C20: JUMBO ALTO LAS CONDES | D20: 16175
C21: JUMBO COSTANERA CENTER | D21: 26864
A22: 18/06/2025 | C22: JUMBO COSTANERA CENTER | D22: 54633
A23: 14/06/2025 | C23: JUMBO COSTANERA CENTER | D23: 29254
C24: JUMBO COSTANERA CENTER | D24: 36392
A25: 08/06/2025 | C25: JUMBO COSTANERA CENTER | D25: 26432
A26: 06/06/2025 | C26: JUMBO COSTANERA CENTER | D26: 30459
A27: 04/06/2025 | C27: JUMBO COSTANERA CENTER | D27: 53404
A28: 01/06/2025 | C28: JUMBO COSTANERA CENTER | D28: 41047
C29: JUMBO COSTANERA CENTER | D29: 33943
C30: JUMBO COSTANERA CENTER | D30: 38468
A31: 25/05/2025 | C31: JUMBO COSTANERA CENTER | D31: 34880
A32: 24/05/2025 | C32: JUMBO COSTANERA CENTER | D32: 16105
C33: LA CABRERA ALONSO | D33: 158060
C34: LA CABRERA ALONSO | D34: 139080
C35: LATAM.COM XP INTER | D35: 336070
C36: LONDON COFFEE ALCANTARA | D36: 5460
C37: LONDON COFFEE ALCANTARA | D37: 9660
C38: LONDON COFFEE ALCANTARA | D38: 10920
C39: LONDON COFFEE ALCANTARA | D39: 5460
C40: LONDON COFFEE ALCANTARA | D40: 4680
A41: 05/06/2025 | C41: LONDON COFFEE ALCANTARA | D41: 6930
C42: LONDON COFFEE ALCANTARA | D42: 5460
C43: LONDON COFFEE ALCANTARA | D43: 5740
C44: LONDON COFFEE ALCANTARA | D44: 4680
C45: LONDON COFFEE ALCANTARA | D45: 4200
C46: LONDON COFFEE ALCANTARA | D46: 5460
A47: 28/05/2025 | C47: LONDON COFFEE ALCANTARA | D47: 5663
C48: LONDON COFFEE ALCANTARA | D48: 6930
C49: LONDON COFFEE ALCANTARA | D49: 21609
C50: LONDON COFFEE ALCANTARA | D50: 1470
C51: LONDON COFFEE ALCANTARA | D51: 5940
A52: 12/06/2025 | C52: LYON 1 | D52: 2380
C53: LYON 1 | D53: 1990
C54: MC DONALDS COSTANERA CENT | D54: 6290
A55: 06/03/2025 | C55: MERCADO PAGO 4 TCOM | D55: 22498
C56: MERCADO PAGO 4 TCOM | D56: 63665
A57: 27/01/2025 | C57: MERCADO PAGO 4 TCOM | D57: 35833
A58: 02/06/2025 | C58: MERCADOPAGO*ALIPAYSINGAPO | D58: 28581
A59: 22/06/2025 | C59: MERCADOPAGO*MICOCACOLA | D59: 18325
A60: 11/06/2025 | C60: MERCADOPAGO*MICOCACOLA | D60: 22070
C61: MERPAGO*COMERCIALLASI | D61: 40376
A62: 29/05/2025 | C62: MERPAGO*MICOCACOLA | D62: 18580
C63: METLIFE CHILE SEGUROS DE | D63: 1568696
C64: MK WEBPAY.CL | D64: 125853
A65: 09/06/2025 | C65: MONTO CANCELADO | F65: 4395731
C66: MP *MERCADO LIBRE | D66: 10077
A67: 26/02/2025 | C67: MP *MERCADO LIBRE | D67: 52163
C68: PARIS COSTANERA CENTER | D68: 39980
C69: PARIS COSTANERA CENTER | D69: 39990
A70: 15/06/2025 | C70: PARKING ALTO LAS CONDES | D70: 200
C71: PAYU *UBER EATS | D71: 10473
A72: 27/02/2025 | C72: ROCA WEBPAY | D72: 73428
C73: ROSEN | D73: 13665
C74: SP DIGITAL SPA | D74: 5538
A75: 30/05/2025 | C75: TUU*oggi | D75: 18500
A76: 10/01/2025 | C76: VISTA LIBRE | D76: 275698

Sheet flujos - Table 3-1
D1: abril | E1: {=SUM(D2:D118)} -> 3759856
C4: ALMACENES BILBAO | D4: 7360
A5: 08/04/2025 | C5: ALMACENES BILBAO | D5: 4360
A6: 03/12/2024 | C6: APPLE.COM CL APPLE | D6: 9166
C7: APPLE.COM CL APPLE | D7: 9166
C8: APPLE.COM CL APPLE | D8: 9166
C9: COPEC APP | D9: 48873
C10: COSTANERA CENTER | D10: 23600
C11: DP *IKEA COM | D11: 14960
A12: 02/04/2025 | C12: DP *IKEA COM | D12: 113910
A13: 17/04/2025 | C13: EASY COSTANERA CENTER | D13: 2990
C14: EASY COSTANERA CENTER | D14: 27670
C15: EASY COSTANERA CENTER | D15: 7990
A16: 14/04/2025 | C16: ENTEL HOGAR | D16: 21990
A17: 18/04/2025 | C17: EXPRESS PLAZA LYON | D17: 8430
A18: 12/04/2025 | C18: EXPRESS PLAZA LYON | D18: 21020
A19: 06/04/2025 | C19: EXPRESS PLAZA LYON | D19: 13460
A20: 04/04/2025 | C20: EXPRESS PLAZA LYON | D20: 22130
C21: EXPRESS PLAZA LYON | D21: 20160
A22: 21/04/2025 | C22: FLOW *PINARES.CL | D22: 200000
C23: FLOW *PINARES.CL | D23: 200000
C24: GOOGLE PLAY YOUTUBE CL | D24: 9200
A25: 05/04/2025 | C25: IKEA OPEN KENNEDY | D25: 8980
C26: INVERSIONES MONASTRELL WI | D26: 85120
C27: JUMBO ALTO LAS CONDES | D27: 14170
C28: JUMBO ALTO LAS CONDES | D28: 34776
A29: 19/04/2025 | C29: JUMBO COSTANERA CENTER | D29: 16678
C30: JUMBO COSTANERA CENTER | D30: 32703
C31: JUMBO COSTANERA CENTER | D31: 12135
C32: JUMBO COSTANERA CENTER | D32: 17725
C33: JUMBO COSTANERA CENTER | D33: 16719
C34: LONDON COFFEE ALCANTARA | D34: 4680
C35: LONDON COFFEE ALCANTARA | D35: 5460
C36: LONDON COFFEE ALCANTARA | D36: 5460
C37: LONDON COFFEE ALCANTARA | D37: 1470
C38: LONDON COFFEE ALCANTARA | D38: 4680
C39: LONDON COFFEE ALCANTARA | D39: 7105
A40: 10/04/2025 | C40: LONDON COFFEE ALCANTARA | D40: 5460
C41: LONDON COFFEE ALCANTARA | D41: 5460
C42: LONDON COFFEE ALCANTARA | D42: 5460
A43: 07/04/2025 | C43: LONDON COFFEE ALCANTARA | D43: 4680
C44: LONDON COFFEE ALCANTARA | D44: 5460
C45: LONDON COFFEE ALCANTARA | D45: 5460
C46: LONDON COFFEE ALCANTARA | D46: 5460
A47: 01/04/2025 | C47: LONDON COFFEE ALCANTARA | D47: 5460
A48: 31/03/2025 | C48: LONDON COFFEE ALCANTARA | D48: 2340
C49: LONDON COFFEE ALCANTARA | D49: 5460
C50: LONDON COFFEE ALCANTARA | D50: 5460
C51: LONDON COFFEE ALCANTARA | D51: 9653
A52: 29/03/2025 | C52: LOS BRAVOS SPA | D52: 38830
A53: 15/04/2025 | C53: LYON 1 | D53: 2100
C54: LYON 1 | D54: 1990
C55: LYON 1 | D55: 3480
C56: MAXIK | D56: 1290
C57: MC DONALDS 4 04 | D57: 4090
C58: MC DONALDS 4 04 | D58: 7990
C59: MC DONALDS PROVIDENCIA 3 | D59: 8690
A60: 06/03/2025 | C60: MERCADO PAGO 4 TCOM | D60: 22498
C61: MERCADO PAGO 4 TCOM | D61: 63665
A62: 27/01/2025 | C62: MERCADO PAGO 4 TCOM | D62: 35833
A63: 21/12/2024 | C63: MERCADO PAGO 4 TCOM | D63: 8495
C64: MERCADOPAGO*COMERCIANTEAU | D64: 16990
C65: MERCADOPAGO*IMPORTADORABO | D65: 5852
C66: MERCADOPAGO*MCDONALDS | D66: 6590
A67: 16/04/2025 | C67: MERPAGO*MICOCACOLA | D67: 20860
A68: 03/04/2025 | C68: MERPAGO*MICOCACOLA | D68: 21670
C69: MERPAGO*NUEVOGENESISSPA | D69: 26514
C70: MERPAGO*STREAT BURGER MEE | D70: 21780
C71: MK WEBPAY.CL | D71: 125853
A72: 28/03/2025 | C72: MONTANA SPA | D72: 3500
A73: 09/04/2025 | C73: MONTO CANCELADO | E73: 5415290
A74: 26/02/2025 | C74: MP *MERCADO LIBRE | D74: 52163
A75: 22/12/2024 | C75: MP *MICOCA COLACL | D75: 2889
A76: 25/03/2025 | C76: MUNICIPALIDAD DE MAIPU | D76: 37651
A77: 11/04/2025 | C77: MUTUARIA | D77: 1519135
C78: NOTA DE CREDITO | D78: 6870
C79: NUEVA ISIDORA | D79: 22488
C80: OKM SUECIA | D80: 5579
C81: PARKING ALTO LAS CONDES | D81: 250
C82: PARKING ALTO LAS CONDES | D82: 200
C83: PARKING COSTANERA | D83: 1550
A84: 20/04/2025 | C84: PAYU *UBER EATS | D84: 11376
C85: PAYU *UBER EATS | D85: 461
C86: PAYU *UBER EATS | D86: 2353
C87: PAYU *UBER EATS | D87: -2353
C88: PAYU *UBER EATS | D88: 2353
C89: PAYU *UBER EATS | D89: 71126
C90: PAYU *UBER EATS | D90: 10557
C91: PETROBRAS ELIOD. YA EZ | D91: 3280
A92: 27/02/2025 | C92: ROCA WEBPAY | D92: 73428
A93: 27/03/2025 | C93: SAN DAMIAN | D93: 4970
A94: 26/03/2025 | C94: SAN DAMIAN | D94: 2380
A95: 13/04/2025 | C95: SB 733 | D95: 45958
C96: TOTTUS KENNEDY II | D96: 27670
C97: UBER | D97: 3990
A98: 10/01/2025 | C98: VISTA LIBRE | D98: 275697

Sheet flujos - Totales
A1: Totales
A2: Deuda pagada | B2: {=0} -> 0 | C2: {=0} -> 0 | D2: Internet
A3: Gasto falso | B3: {='flujos - Gasto mes actual'!T9} -> 0 | D3: {=B4*1} -> 50817
A4: Deuda nacional | B4: {='flujos - Gasto mes actual'!B$37-'flujos - Gasto mes actual'!AE35-'flujos - Gasto mes actual'!AN$37-B6-B2-B9-'flujos - Gasto mes actual'!AN35+'flujos - Table 2-1'!B$9} -> 50817 | D4: {=D3-B4} -> 0
A5: Internacional | B5: {=IF('flujos - Gasto mes actual'!AM$37-C2<0,0,ROUND(C5*'variables - Table 1'!$B$5,0))} -> 0 | C5: {='flujos - Gasto mes actual'!AM$37-C2} -> 0 | D5: {=C5*1} -> 0
A6: Efectivo | B6: {='flujos - Gasto mes actual'!AA3+'flujos - Gasto mes actual'!AA4+'flujos - Gasto mes actual'!X$37+C6} -> 880000 | C6: {=0} -> 0 | D6: {=D5-C5} -> 0
A7: Cuentas | B7: {='flujos - Gasto mes actual'!AA$37} -> 930817
A9: Líder Mastercard | B9: {=SUMIF('flujos - Gasto mes actual'!E3:E36,"=TRUE",'flujos - Gasto mes actual'!D3:D36)+SUMIF('flujos - Gasto mes actual'!U3:U36,"=TRUE",'flujos - Gasto mes actual'!T3:T36)+SUMIF('flujos - Gasto mes actual'!M3:M36,"=TRUE",'flujos - Gasto mes actual'!L3:L36)+SUMIF('flujos - Gasto mes actual'!AB3:AB36,"=TRUE",'flujos - Gasto mes actual'!AA3:AA36)+SUMIF('flujos - Gasto mes actual'!I3:I36,"=TRUE",'flujos - Gasto mes actual'!H3:H36)+SUMIF('flujos - Gasto mes actual'!Q3:Q36,"=TRUE",'flujos - Gasto mes actual'!P3:P36)+SUMIF('flujos - Gasto mes actual'!AF3:AF34,"=TRUE",'flujos - Gasto mes actual'!AE3:AE34)+SUMIF('flujos - Gasto mes actual'!AO3:AO36,"=TRUE",'flujos - Gasto mes actual'!AN3:AN36)+SUMIF('flujos - Gasto mes actual'!AJ3:AJ36,"=TRUE",'flujos - Gasto mes actual'!AI3:AI36)} -> 0
A12: Salud | B12: {='flujos - Gasto mes actual'!AE$37} -> 0
A13: Transporte | B13: {='flujos - Gasto mes actual'!AI$37} -> 0
A14: Not monthly | B14: {=0} -> 0
A16: Total gastos | B16: {='flujos - Gasto mes actual'!D$37+'flujos - Gasto mes actual'!H$37+'flujos - Gasto mes actual'!L$37+'flujos - Gasto mes actual'!P$37+'flujos - Gasto mes actual'!T$37+'flujos - Gasto mes actual'!X$37+'flujos - Gasto mes actual'!AA$37+'flujos - Gasto mes actual'!AE$37+'flujos - Gasto mes actual'!AI$37} -> 930817 | C16: Cupo disponible | D16: {=12720000-B4} -> 12669183
A17: - líder | B17: {=B$16-B9-B3} -> 930817 | D17: {=7735-'flujos - Gasto mes actual'!AM$37} -> 7735

Sheet flujos - Table 2-1
A1: Cuenta corriente | B1: {='net worth - cash'!B2} -> 280744
A2: Adelantado | B2: 0
A4: Efectivo | B4: 0
A5: Mach | B5: 0
A7: Líquido bruto | B7: {=B1+B2} -> 280744
A8: Deuda | B8: {=SUM('flujos - Totales'!B4:B5)} -> 50817
A9: Deuda mes anterior | B9: 0
A10: Líquido mes neto | B10: {=B$7-SUM(B$8)+B4+B5} -> 229927

Sheet flujos - Table 3-2
A1: apple music
A2: apple cloud storage
A3: apple tv
A4: youtube family

Sheet flujos - Gasto mensual
A1: Gasto mensual
B2: usd | C2: Ingreso | D2: Bruto | E2: Líquido | F2: Isapre | G2: AFP | H2: Adicional | I2: Saldo tc | J2: Crédito | K2: Ahorro | M2: Gasto real | N2: Gasto | P2: Supermercado | Q2: Carrete | R2: take out | S2: Ropa | T2: Otros | U2: Cuentas | V2: Drugs | W2: Salud | X2: Transporte | Y2: Cabify | Z2: Scooters | AA2: Delivery | AB2: Dólares | AC2: Crédito | AE2: Líder + falso | AF2: Líder Mastercard | AG2: Falso | AH2: Not monthly
A3: 42887 | B3: {=ROUND(C3/'variables - Table 1-1'!B2,0)} -> 1869 | C3: {=SUM(E3:J3)} -> 1242048 | D3: {=SUM(E3:G3)} -> 1122048 | E3: {=949283} -> 949283 | F3: 68402 | G3: {='net worth - retiro'!D5} -> 104363 | H3: {=120000} -> 120000 | J3: 0 | K3: {=529723} -> 529723 | L3: {=(K3/C3)} -> 0.42649157 | M3: {=N3-AF3} -> 493368 | N3: 529723 | P3: 125333.75 | Q3: 36781.25 | R3: 38820 | S3: 15516 | T3: 93575 | U3: 0 | V3: 106750 | W3: 115902 | X3: 129891 | AB3: 125717.91 | AC3: 0 | AE3: 36355 | AF3: 36355
A4: 42917 | B4: {=ROUND(C4/'variables - Table 1-1'!B3,0)} -> 2132 | C4: {=SUM(E4:J4)} -> 1392783 | D4: {=SUM(E4:G4)} -> 1192783 | E4: {=1009422} -> 1009422 | F4: 72765 | G4: {='net worth - retiro'!D6} -> 110596 | H4: {=150000+50000} -> 200000 | J4: 0 | K4: {=C4-N4} -> 594770 | L4: {=(K4/C4)} -> 0.42703709 | M4: {=N4-AF4} -> 658013 | N4: {=SUM(P4:AB4)} -> 798013 | P4: 172023 | Q4: 35325 | R4: 41390 | S4: 39980 | T4: 112520 | U4: 0 | V4: 120000 | W4: 122765 | X4: 125000 | AB4: {=ROUND(29009.587,0)} -> 29010 | AC4: {=J3} -> 0 | AE4: 140000 | AF4: 140000
A5: 42948 | B5: {=ROUND(C5/'variables - Table 1-1'!B4,0)} -> 2265 | C5: {=SUM(E5:J5)} -> 1430407 | D5: {=SUM(E5:G5)} -> 1310407 | E5: {=1105094} -> 1105094 | F5: 81804 | G5: {='net worth - retiro'!D7} -> 123509 | H5: {=120000} -> 120000 | J5: 0 | K5: {=C5-N5} -> 607902.89 | L5: {=(K5/C5)} -> 0.42498596 | M5: {=N5-AF5} -> 687504.11 | N5: {=SUM(P5:AB5)} -> 822504.11 | P5: 101864 | Q5: 40720 | R5: 39790 | S5: 0 | T5: 227430 | U5: 0 | V5: 90000 | W5: 131804 | X5: 159761 | AB5: 31135.112 | AC5: {=J4} -> 0 | AE5: 135000 | AF5: 135000
A6: 42979 | B6: {=ROUND(C6/'variables - Table 1-1'!B5,0)} -> 2323 | C6: {=SUM(E6:J6)} -> 1475760 | D6: {=SUM(E6:G6)} -> 1305760 | E6: {=1101255} -> 1101255 | F6: 81471 | G6: {='net worth - retiro'!D8} -> 123034 | H6: {=30000*4+50000} -> 170000 | J6: 0 | K6: {=C6-N6} -> 379127 | L6: {=(K6/C6)} -> 0.25690288 | M6: {=N6-AF6} -> 909333 | N6: {=SUM(P6:AB6)} -> 1096633 | P6: 93609 | Q6: 47440 | R6: 44690 | S6: 0 | T6: 107710 | U6: 0 | V6: 97000 | W6: 171471 | X6: 120817 | AB6: 413896 | AC6: {=J5} -> 0 | AE6: 187300 | AF6: 187300
A7: 43009 | B7: {=ROUND(C7/'variables - Table 1-1'!B6,0)} -> 2679 | C7: {=SUM(E7:J7)} -> 1663586 | D7: {=SUM(E7:G7)} -> 1316586 | E7: {=1101286} -> 1101286 | F7: 85916 | G7: {='net worth - retiro'!D9} -> 129384 | H7: {=80000+30000*3+45000+50000+2000+80000} -> 347000 | J7: 0 | K7: {=C7-N7} -> 948821.47 | L7: {=(K7/C7)} -> 0.57034711 | M7: {=N7-AF7} -> 592837.53 | N7: {=SUM(P7:AB7)} -> 714764.53 | P7: 133839 | Q7: 23640 | R7: 29410 | S7: 22084 | T7: 98252 | U7: 0 | V7: 120000 | W7: 85916 | X7: 172793 | AB7: 28830.533 | AC7: {=J6} -> 0 | AE7: 121927 | AF7: 121927
A8: 43040 | B8: {=ROUND(C8/'variables - Table 1-1'!B7,0)} -> 2215 | C8: {=SUM(E8:J8)} -> 1425860 | D8: {=SUM(E8:G8)} -> 1305860 | E8: {=1101355} -> 1101355 | F8: 81471 | G8: {='net worth - retiro'!D10} -> 123034 | H8: {=30000*4} -> 120000 | J8: 0 | K8: {=C8-N8} -> 656683.78 | L8: {=(K8/C8)} -> 0.46055278 | M8: {=N8-AF8} -> 546557.22 | N8: {=SUM(P8:AB8)} -> 769176.22 | P8: 163960 | Q8: 0 | R8: 29810 | S8: 24980 | T8: 86650 | U8: 0 | V8: 120000 | W8: 172471 | X8: 142498 | AB8: 28807.22 | AC8: {=J7} -> 0 | AE8: 222619 | AF8: 222619
A9: 43070 | B9: {=ROUND(C9/'variables - Table 1-1'!B8,0)} -> 2622 | C9: {=SUM(E9:J9)} -> 1610819 | D9: {=SUM(E9:G9)} -> 1305819 | E9: {=1101304} -> 1101304 | F9: 81471 | G9: {='net worth - retiro'!D11} -> 123044 | H9: {=80000*2+30000*3+50000+5000} -> 305000 | J9: 0 | K9: {=C9-N9} -> 803884.65 | L9: {=(K9/C9)} -> 0.49905337 | M9: {=N9-AF9} -> 683780.35 | N9: {=SUM(P9:AB9)} -> 806934.35 | P9: 193609 | Q9: 46215 | R9: 22470 | S9: 0 | T9: 124710 | U9: 0 | V9: 140000 | W9: 92461 | X9: 152373.35 | AB9: 35096 | AC9: {=J8} -> 0 | AE9: 123154 | AF9: 123154
A10: 43101 | B10: {=ROUND(C10/'variables - Table 1-1'!B9,0)} -> 2424 | C10: {=SUM(E10:J10)} -> 1470091 | D10: {=SUM(E10:G10)} -> 1310091 | E10: {=1101437} -> 1101437 | F10: 85916 | G10: {='net worth - retiro'!D12} -> 122738 | H10: {=40000+30000*4} -> 160000 | J10: 0 | K10: {=C10-N10} -> 707836 | L10: {=_xlfn.IFERROR(K10/C10,0)} -> 0.48149128 | M10: {=N10-AF10} -> 622726 | N10: {=SUM(P10:AB10)} -> 762255 | P10: 175665 | Q10: 0 | R10: 37460 | S10: 0 | T10: 151250 | U10: 0 | V10: 115000 | W10: 85916 | X10: 159203 | AB10: 37761 | AC10: {=J9} -> 0 | AE10: 139529 | AF10: 139529
A11: 43132 | B11: {=ROUND(C11/'variables - Table 1-1'!B10,0)} -> 2488 | C11: {=SUM(E11:J11)} -> 1471612 | D11: {=SUM(E11:G11)} -> 1301612 | E11: {=1103349} -> 1103349 | F11: 81638 | G11: {='net worth - retiro'!D13} -> 116625 | H11: {=80000+30000*3} -> 170000 | J11: 0 | K11: {=C11-N11} -> 471798 | L11: {=_xlfn.IFERROR(K11/C11,0)} -> 0.32059945 | M11: {=N11-AF11} -> 832114 | N11: {=SUM(P11:AB11)} -> 999814 | P11: 181799 | Q11: 69149 | R11: 42550 | S11: 208142 | T11: 122680 | U11: 0 | V11: 80000 | W11: 101638 | X11: 166188 | AB11: 27668 | AC11: {=J10} -> 0 | AE11: 167700 | AF11: 167700
A12: 43160 | B12: {=ROUND(C12/'variables - Table 1-1'!B11,0)} -> 3641 | C12: {=SUM(E12:J12)} -> 2196694 | D12: {=SUM(E12:G12)} -> 1301637 | E12: {=1103374} -> 1103374 | F12: 81638 | G12: {='net worth - retiro'!D14} -> 116625 | H12: {=650407+15000+80000+1520+2130+30000*3+AG12} -> 895057 | J12: 0 | K12: {=C12-N12} -> 1464675 | L12: {=_xlfn.IFERROR(K12/C12,0)} -> 0.66676333 | M12: {=N12-AE12} -> 432791 | N12: {=SUM(P12:AB12)} -> 732019 | P12: {=281859-4200} -> 277659 | Q12: 9955 | R12: 83320 | S12: 0 | T12: 88880 | U12: 0 | V12: 108000 | W12: 120828 | X12: 40328 | AB12: 3049 | AC12: {=J11} -> 0 | AE12: 299228 | AF12: 243228 | AG12: 56000
A13: 43191 | B13: {=ROUND(C13/'variables - Table 1-1'!B12,0)} -> 4606 | C13: {=SUM(E13:J13)} -> 2790130 | D13: {=SUM(E13:G13)} -> 1372630 | E13: 1200000 | F13: 81365 | G13: {='net worth - retiro'!D15} -> 91265 | H13: {=AG13+80000+30000*4+1200000} -> 1417500 | J13: 0 | K13: {=C13-N13} -> 2137545 | L13: {=_xlfn.IFERROR(K13/C13,0)} -> 0.76610946 | M13: {=N13-AE13} -> 525306 | N13: {=SUM(P13:AB13)} -> 652585 | P13: 181950 | Q13: 0 | R13: 29950 | S13: 0 | T13: 57180 | U13: 0 | V13: 153000 | W13: 131020 | X13: 66779 | AB13: 32706 | AC13: {=J12} -> 0 | AE13: 127279 | AF13: 109779 | AG13: 17500
A14: 43221 | B14: {=ROUND(C14/'variables - Table 1-1'!B13,0)} -> 1395 | C14: {=SUM(E14:J14)} -> 875062 | D14: {=SUM(E14:G14)-41314} -> 379592 | E14: {=304804} -> 304804 | F14: 81365 | G14: {='net worth - retiro'!D16} -> 34737 | H14: {=AG14+30000*4+25000-41314} -> 107186 | J14: {=346970} -> 346970 | K14: {=C14-N14} -> 234274 | L14: {=_xlfn.IFERROR(K14/C14,0)} -> 0.26772274 | M14: {=N14-AE14} -> 538265 | N14: {=SUM(P14:AB14)} -> 640788 | P14: 116288 | Q14: {=106245-13500-20274-10000} -> 62471 | R14: 16100 | S14: 0 | T14: 100800 | U14: 0 | V14: 150000 | W14: 85741 | X14: 54023 | AB14: {=55365} -> 55365 | AC14: {=J13} -> 0 | AE14: 102523 | AF14: 99023 | AG14: 3500
A15: 43252 | B15: {=ROUND(C15/'variables - Table 1-1'!B14,0)} -> 2553 | C15: {=SUM(E15:J15)} -> 1656689 | D15: {=SUM(E15:G15)} -> 1536689 | E15: {=1305231} -> 1305231 | F15: 81587 | G15: {='net worth - retiro'!D17} -> 149871 | H15: {=30000*4} -> 120000 | J15: 0 | K15: {=C15-N15} -> 595305 | L15: {=_xlfn.IFERROR(K15/C15,0)} -> 0.35933419 | M15: {=N15-AE15} -> 934243 | N15: {=SUM(P15:AC15)} -> 1061384 | P15: 172810 | Q15: 19077 | R15: 17780 | S15: 0 | T15: 59387 | U15: 0 | V15: 140000 | W15: 126587 | X15: 54141 | AB15: 124632 | AC15: 346970 | AE15: 127141 | AF15: 127141 | AG15: 15000
A16: 43282 | B16: {=ROUND(C16/'variables - Table 1-1'!B15,0)} -> 2643 | C16: {=SUM(E16:J16)} -> 1686766 | D16: {=SUM(E16:G16)} -> 1536766 | E16: {=1305308} -> 1305308 | F16: 81587 | G16: {='net worth - retiro'!D18} -> 149871 | H16: {=30000*5} -> 150000 | J16: 0 | K16: {=C16-N16} -> 898181 | L16: {=_xlfn.IFERROR(K16/C16,0)} -> 0.53248702 | M16: {=N16-AE16} -> 589898 | N16: {=SUM(P16:AC16)} -> 788585 | P16: 221983 | Q16: 30000 | R16: 3400 | S16: 0 | T16: 90928 | U16: 0 | V16: 200000 | W16: 161587 | X16: 48687 | AB16: 32000 | AC16: 0 | AE16: 198687 | AF16: 198687 | AG16: 15000
A17: 43313 | B17: {=ROUND(C17/'variables - Table 1-1'!B16,0)} -> 2453 | C17: {=SUM(E17:J17)} -> 1665468 | D17: {=SUM(E17:G17)} -> 1545468 | E17: 1313038 | F17: 81587 | G17: {='net worth - retiro'!D19} -> 150843 | H17: {=30000*4} -> 120000 | K17: {=C17-N17} -> 867592.48 | L17: {=_xlfn.IFERROR(K17/C17,0)} -> 0.52093014 | M17: {=N17-AE17} -> 582323.52 | N17: {=SUM(P17:AC17)} -> 797875.52 | P17: 155166 | Q17: 113683 | R17: 4830 | S17: 25492 | T17: 125980 | U17: 0 | V17: 200000 | W17: 83519.518 | X17: 57502 | AB17: 31703 | AC17: 0 | AE17: 215552 | AF17: 125502 | AG17: 90050
A18: 43344 | B18: {=ROUND(C18/'variables - Table 1-1'!B17,0)} -> 2570 | C18: {=SUM(E18:J18)} -> 1694404 | D18: {=SUM(E18:G18)} -> 1544404 | E18: 1307851 | F18: 85710 | G18: {='net worth - retiro'!D20} -> 150843 | H18: {=30000*(5-0)} -> 150000 | K18: {=C18-N18} -> 1108743.2 | L18: {=_xlfn.IFERROR(K18/C18,0)} -> 0.65435587 | M18: {=N18-AE18} -> 451097.8 | N18: {=SUM(P18:AC18)} -> 585660.8 | P18: {=199701} -> 199701 | Q18: 27153 | R18: 2550 | S18: 0 | T18: {=33230} -> 33230 | U18: 0 | V18: 190000 | W18: 85214.795 | X18: 43313 | AB18: 4499 | AC18: 0 | AE18: 134563 | AF18: 112563 | AG18: 22000
A19: 43374 | B19: {=ROUND(C19/'variables - Table 1-1'!B18,0)} -> 2921 | C19: {=SUM(E19:J19)} -> 2024160 | D19: {=SUM(E19:G19)} -> 1504160 | E19: 1271796 | F19: 85710 | G19: {='net worth - retiro'!D21} -> 146654 | H19: {=30000*4+400000} -> 520000 | K19: {=C19-N19} -> 1123636 | L19: {=_xlfn.IFERROR(K19/C19,0)} -> 0.55511224 | M19: {=N19-AE19} -> 733371 | N19: {=SUM(P19:X19,AC19)} -> 900524 | P19: 184544 | Q19: 84598 | R19: 17110 | S19: 0 | T19: 122405 | U19: 0 | V19: 150000 | W19: 102215 | X19: 239652 | AB19: 78349 | AC19: 0 | AE19: 167153 | AF19: 135488 | AG19: 31665
A20: 43405 | B20: {=ROUND(C20/'variables - Table 1-1'!B19,0)} -> 3617 | C20: {=SUM(E20:J20)} -> 2423722 | D20: {=SUM(E20:G20)} -> 2423722 | E20: 2123219 | F20: 85710 | G20: {='net worth - retiro'!D22} -> 214793 | H20: {=0} -> 0 | K20: {=C20-N20} -> 1326980 | L20: {=_xlfn.IFERROR(K20/C20,0)} -> 0.54749678 | M20: {=N20-AE20} -> 895905 | N20: {=SUM(P20:X20,AC20)} -> 1096742 | P20: 275472 | Q20: 19964 | R20: 6480 | S20: 94707 | T20: 302449 | U20: 0 | V20: 150000 | W20: 85812 | X20: 161858 | AB20: 155267 | AC20: 0 | AE20: 200837 | AF20: 153847 | AG20: 46990
A21: 43435 | B21: {=ROUND(C21/'variables - Table 1-1'!B20,0)} -> 3495 | C21: {=SUM(E21:J21)} -> 2423471 | D21: {=SUM(E21:G21)} -> 2423471 | E21: 2122179 | F21: 85710 | G21: {='net worth - retiro'!D23} -> 215582 | H21: {=0} -> 0 | K21: {=C21-N21} -> 1299768 | L21: {=_xlfn.IFERROR(K21/C21,0)} -> 0.53632497 | M21: {=N21-AE21} -> 803085 | N21: {=SUM(P21:X21,AC21)} -> 1123703 | P21: 214252 | Q21: 63190 | R21: 13330 | S21: 0 | T21: 395615 | U21: 0 | V21: 150000 | W21: 85710 | X21: 201606 | AB21: {=175209+1892} -> 177101 | AC21: 0 | AE21: {=SUM(AF21:AG21)} -> 320618 | AF21: 147582 | AG21: {=42341+130695} -> 173036
A22: 43466 | B22: {=ROUND(C22/'variables - Table 1-1'!B21,0)} -> 3654 | C22: {=SUM(E22:J22)} -> 2423745 | D22: {=SUM(E22:G22)} -> 2423745 | E22: 2122093 | F22: 85812 | G22: {='net worth - retiro'!D24} -> 215840 | H22: {=0} -> 0 | K22: {=C22-N22} -> 1724646 | L22: {=_xlfn.IFERROR(K22/C22,0)} -> 0.71156248 | M22: {=N22-AE22} -> 598716 | N22: {=SUM(P22:X22,AC22)} -> 699099 | P22: 209801 | Q22: 85298 | R22: 28530 | S22: 3766 | T22: 21400 | U22: 0 | V22: 155000 | W22: 85812 | X22: 109492 | AB22: 21855 | AC22: 0 | AE22: {=SUM(AF22:AG22)} -> 100383 | AF22: 100383 | AG22: {=0} -> 0
A23: 43497 | B23: {=ROUND(C23/'variables - Table 1-1'!B22,0)} -> 3739 | C23: {=SUM(E23:J23)} -> 2425605 | D23: {=SUM(E23:G23)} -> 2425605 | E23: 2122093 | F23: 85812 | G23: {='net worth - retiro'!D25} -> 217700 | H23: {=0} -> 0 | K23: {=C23-N23} -> 1609801 | L23: {=_xlfn.IFERROR(K23/C23,0)} -> 0.66366989 | M23: {=N23-AE23} -> 476001 | N23: {=SUM(P23:X23,AC23)} -> 815804 | P23: 269562 | Q23: 7000 | R23: 30378 | S23: 0 | T23: 114761 | U23: 0 | V23: 175000 | W23: 85751 | X23: 133352 | AB23: 31363 | AC23: 0 | AE23: {=SUM(AF23:AG23)} -> 339803 | AF23: 73647 | AG23: {=258656+7500} -> 266156
A24: 43525 | B24: {=ROUND(C24/'variables - Table 1-1'!B23,0)} -> 4285 | C24: {=SUM(E24:J24)} -> 2922564 | D24: {=SUM(E24:G24)} -> 2422564 | E24: 2119052 | F24: 85812 | G24: {='net worth - retiro'!D26} -> 217700 | H24: {=500000} -> 500000 | K24: {=C24-N24} -> 1831316 | L24: {=_xlfn.IFERROR(K24/C24,0)} -> 0.6266128 | M24: {=N24-AE24} -> 982015 | N24: {=SUM(P24:X24,AC24)} -> 1091248 | P24: 196890 | Q24: 42700 | R24: 35890 | S24: 0 | T24: 235969 | U24: 0 | V24: 185000 | W24: 104791 | X24: 290008 | AB24: 159759 | AC24: 0 | AE24: 109233 | AF24: 109233 | AG24: 0
A25: 43556 | B25: {=ROUND(C25/'variables - Table 1-1'!B24,0)} -> 3584 | C25: {=SUM(E25:J25)} -> 2430374 | D25: {=SUM(E25:G25)} -> 2430374 | E25: 2122917 | F25: 89242 | G25: {='net worth - retiro'!D27} -> 218215 | H25: {=0} -> 0 | K25: {=C25-N25} -> 1251325 | L25: {=_xlfn.IFERROR(K25/C25,0)} -> 0.51486932 | M25: {=N25-AE25} -> 872926.5 | N25: {=SUM(P25:X25,AC25)} -> 1179049 | P25: 131925 | Q25: 48881 | R25: 72787.5 | S25: 0 | T25: 412926.5 | U25: 0 | V25: 150000 | W25: 85812 | X25: 276717 | AB25: 309234 | AC25: 0 | AE25: 306122.5 | AF25: 75712 | AG25: 230410.5
A26: 43586 | B26: {=ROUND(C26/'variables - Table 1-1'!B25,0)} -> 3425 | C26: {=SUM(E26:J26)} -> 2430374 | D26: {=SUM(E26:G26)} -> 2430374 | E26: 2122917 | F26: 89242 | G26: {='net worth - retiro'!D28} -> 218215 | H26: {=0} -> 0 | K26: {=C26-N26} -> 1108602 | L26: {=_xlfn.IFERROR(K26/C26,0)} -> 0.45614461 | M26: {=N26-AE26} -> 1029852 | N26: {=SUM(P26:X26,AC26)} -> 1321772 | P26: 116929 | Q26: 135579 | R26: 80939 | S26: 89980 | T26: 494540 | U26: 0 | V26: 180000 | W26: 86425 | X26: 137380 | AB26: {='flujos - Gasto mes actual'!AN$37} -> 0 | AC26: 0 | AE26: {=SUM(AF26:AG26)} -> 291920 | AF26: 87000 | AG26: 204920
A27: 43617 | B27: {=ROUND(C27/'variables - Table 1-1'!B26,0)} -> 3574 | C27: {=SUM(E27:J27)} -> 2430795 | D27: {=SUM(E27:G27)} -> 2430795 | E27: 2123338 | F27: 89242 | G27: {='net worth - retiro'!D29} -> 218215 | H27: {=0} -> 0 | K27: {=C27-N27} -> 1214653 | L27: {=_xlfn.IFERROR(K27/C27,0)} -> 0.49969372 | M27: {=N27-AE27} -> 1050954 | N27: {=SUM(P27:X27,AC27)} -> 1216142 | P27: 254415 | Q27: {=10000+65000+50000} -> 125000 | R27: 64789 | S27: 0 | T27: 352474 | U27: 0 | V27: 180000 | W27: 97417 | X27: 142047 | AB27: 219952 | AC27: 0 | AE27: {=SUM(AF27:AG27)} -> 165188 | AF27: 126347 | AG27: 38841
A28: 43647 | B28: {=ROUND(C28/'variables - Table 1-1'!B27,0)} -> 3478 | C28: {=SUM(E28:J28)} -> 2430795 | D28: {=SUM(E28:G28)} -> 2430795 | E28: 2123338 | F28: 89242 | G28: {='net worth - retiro'!D30} -> 218215 | H28: {=0} -> 0 | K28: {=C28-N28} -> -1204880 | L28: {=_xlfn.IFERROR(K28/C28,0)} -> -0.49567323 | M28: {=N28-AE28} -> 3542249 | N28: {=SUM(P28:X28,AC28)} -> 3635675 | P28: 401423 | Q28: 11790 | R28: 81516 | S28: 0 | T28: 1788124 | U28: 1000000 | V28: 155000 | W28: 136198 | X28: 61624 | Y28: 30000 | Z28: 10000 | AA28: 80000 | AB28: 170771 | AC28: 0 | AE28: {=SUM(AF28:AG28)} -> 93426 | AF28: 33000 | AG28: 60426 | AH28: 2165000
A29: 43678 | B29: {=ROUND(C29/'variables - Table 1-1'!B28,0)} -> 4150 | C29: {=SUM(E29:J29)} -> 2991383 | D29: {=SUM(E29:G29)} -> 2431557 | E29: {=2124100} -> 2124100 | F29: 89242 | G29: {='net worth - retiro'!D31} -> 218215 | H29: {='net worth - cash and cash equiv'!D31} -> 559826 | K29: {=C29-N29} -> 902538 | L29: {=_xlfn.IFERROR(K29/C29,0)} -> 0.30171262 | M29: {=N29-AE29} -> 2020772 | N29: {=SUM(P29:X29,AC29)} -> 2088845 | P29: 360634 | Q29: 75004 | R29: 39540 | S29: 0 | T29: 305569 | U29: 746875 | V29: 300000 | W29: 166124 | X29: 95099 | Y29: 5083 | Z29: 41640 | AA29: 21089 | AB29: 56983 | AC29: 0 | AE29: 68073 | AF29: 30073 | AG29: 38000 | AH29: 370400
A30: 43709 | B30: {=ROUND(C30/'variables - Table 1-1'!B29,0)} -> 3432 | C30: {=SUM(E30:J30)} -> 2491557 | D30: {=SUM(E30:G30)} -> 2431557 | E30: {=2124100} -> 2124100 | F30: 89242 | G30: {='net worth - retiro'!D32} -> 218215 | H30: 60000 | K30: {=C30-N30} -> -226632 | L30: {=_xlfn.IFERROR(K30/C30,0)} -> -0.09095999 | M30: {=N30-AE30} -> 2654189 | N30: {=SUM(P30:X30,AC30)} -> 2718189 | P30: 190098 | Q30: 74310 | R30: 30570 | S30: 0 | T30: 1140223 | U30: {=821783+21283} -> 843066 | V30: 240000 | W30: 113935 | X30: 85987 | Y30: 18699 | Z30: 4841 | AA30: 35000 | AB30: 48272 | AC30: 0 | AE30: {=SUM(AF30:AG30)} -> 64000 | AF30: 30000 | AG30: 34000 | AH30: 1034868
A31: 43739 | B31: {=ROUND(C31/'variables - Table 1-1'!B30,0)} -> 3278 | C31: {=SUM(E31:J31)} -> 2431728 | D31: {=SUM(E31:G31)} -> 2431728 | E31: {=2124271} -> 2124271 | F31: 89242 | G31: {='net worth - retiro'!D33} -> 218215 | H31: {=0} -> 0 | K31: {=C31-N31} -> 529562 | L31: {=_xlfn.IFERROR(K31/C31,0)} -> 0.21777189 | M31: {=N31-AE31} -> 1855166 | N31: {=SUM(P31:X31,AC31)} -> 1902166 | P31: 392875 | Q31: 0 | R31: {=15800+4500} -> 20300 | S31: 29990 | T31: 265746 | U31: 863945 | V31: 228990 | W31: 87367 | X31: 12953 | Y31: 3408 | Z31: 2797 | AA31: 8166 | AB31: 54679 | AC31: 0 | AE31: {=SUM(AF31:AG31)} -> 47000 | AF31: 0 | AG31: 47000 | AH31: 258490
A32: 43770 | B32: {=ROUND(C32/'variables - Table 1-1'!B31,0)} -> 3419 | C32: {=SUM(E32:J32)} -> 2831898 | D32: {=SUM(E32:G32)} -> 2431898 | E32: {=2124441} -> 2124441 | F32: 89242 | G32: {='net worth - retiro'!D34} -> 218215 | H32: 400000 | K32: {=C32-N32} -> 564340 | L32: {=_xlfn.IFERROR(K32/C32,0)} -> 0.19927978 | M32: {=N32-AE32} -> 2047068 | N32: {=SUM(P32:X32,AC32)} -> 2267558 | P32: 223294 | Q32: 0 | R32: 64352 | S32: 33480 | T32: 518424 | U32: 851582 | V32: 456000 | W32: 103935 | X32: 16491 | Y32: 9290 | Z32: 0 | AA32: 0 | AB32: 360012 | AC32: 0 | AE32: 220490 | AF32: 0 | AG32: 220490 | AH32: 868794
A33: 43800 | B33: {=ROUND(C33/'variables - Table 1-1'!B32,0)} -> 3321 | C33: {=SUM(E33:J33)} -> 2431898 | D33: {=SUM(E33:G33)} -> 2431898 | E33: {=2124441} -> 2124441 | F33: 89242 | G33: {='net worth - retiro'!D35} -> 218215 | K33: {=C33-N33} -> 295039 | L33: {=_xlfn.IFERROR(K33/C33,0)} -> 0.12132047 | M33: {=N33-AE33} -> 2052909 | N33: {=SUM(P33:X33,AC33)} -> 2136859 | P33: 277362 | Q33: 54514 | R33: 52612 | S33: 0 | T33: 557394 | U33: 832012 | V33: 248465 | W33: 112500 | X33: 2000 | Y33: 0 | Z33: 2000 | AA33: 0 | AB33: 60239 | AC33: 0 | AE33: {=SUM(AF33:AG33)} -> 83950 | AF33: 0 | AG33: 83950 | AH33: 462114
A34: 43831 | B34: {=ROUND(C34/'variables - Table 1-1'!B33,0)} -> 3053 | C34: {=SUM(E34:J34)} -> 2432584 | D34: {=SUM(E34:G34)} -> 2432584 | E34: 2125127 | F34: 89242 | G34: {='net worth - retiro'!D36} -> 218215 | K34: {=C34-N34} -> 360975 | L34: {=_xlfn.IFERROR(K34/C34,0)} -> 0.14839159 | M34: {=N34-AE34} -> 2061142 | N34: {=SUM(P34:X34,AC34)} -> 2071609 | P34: 246302 | Q34: 112762 | R34: {=50480+9240} -> 59720 | S34: 0 | T34: 432600 | U34: 843276 | V34: 195760 | W34: 122787 | X34: 58402 | Y34: 6573 | Z34: 41379 | AA34: 8900 | AB34: 65033 | AC34: 0 | AE34: {=SUM(AF34:AG34)} -> 10467 | AF34: 0 | AG34: 10467 | AH34: 315000
A35: 43862 | B35: {=ROUND(C35/'variables - Table 1-1'!B34,0)} -> 3124 | C35: {=SUM(E35:J35)} -> 2542827 | D35: {=SUM(E35:G35)} -> 2542827 | E35: 2125214 | F35: {='presupuesto - Ingreso líquido'!$D$19} -> 199398 | G35: {='net worth - retiro'!D37} -> 218215 | K35: {=C35-N35} -> 1059817 | L35: {=_xlfn.IFERROR(K35/C35,0)} -> 0.41678691 | M35: {=N35-AE35} -> 1483010 | N35: {=SUM(P35:X35,AC35)} -> 1483010 | P35: 86111 | Q35: 0 | R35: 14490 | S35: 127062 | T35: 170416 | U35: 849309 | V35: 119990 | W35: 88129 | X35: 27503 | Y35: 4376 | Z35: 22427 | AA35: 0 | AB35: 81593 | AC35: 0 | AE35: {=SUM(AF35:AG35)} -> 0 | AF35: 0 | AG35: 0 | AH35: 193488
A36: 43891 | B36: {=ROUND(C36/'variables - Table 1-1'!B35,0)} -> 10381 | C36: {=SUM(E36:J36)} -> 8919021 | D36: {=SUM(E36:G36)} -> 2542914 | E36: {=2125301} -> 2125301 | F36: {='presupuesto - Ingreso líquido'!$D$19} -> 199398 | G36: {='net worth - retiro'!D38} -> 218215 | H36: 6376107 | K36: {=C36-N36} -> 5098231 | L36: {=_xlfn.IFERROR(K36/C36,0)} -> 0.5716133 | M36: {=N36-AE36} -> 3820790 | N36: {=SUM(P36:X36,AC36)} -> 3820790 | P36: 435108 | Q36: 0 | R36: 1500 | S36: 0 | T36: 2080691 | U36: 813191 | V36: 270010 | W36: 104170 | X36: 116120 | Y36: 2731 | Z36: 0 | AA36: 32036 | AB36: 421834 | AC36: 0 | AE36: {=SUM(AF36:AG36)} -> 0 | AF36: 0 | AG36: 0 | AH36: 1862131
A37: 43922 | B37: {=ROUND(C37/'variables - Table 1-1'!B36,0)} -> 465 | C37: {=SUM(E37:J37)-F37} -> 388237 | D37: {=SUM(E37:G37)} -> 383729 | E37: 167139 | F37: {='presupuesto - Ingreso líquido'!$D$19} -> 199398 | G37: {='net worth - retiro'!D39} -> 17192 | H37: {=203906} -> 203906 | K37: {=C37-N37} -> -1284575 | L37: {=_xlfn.IFERROR(K37/C37,0)} -> -3.3087392 | M37: {=N37-AE37} -> 1672812 | N37: {=SUM(P37:X37,AC37)} -> 1672812 | P37: 247329 | Q37: 0 | R37: 0 | S37: 0 | T37: 92565 | U37: 840735 | V37: 382000 | W37: 110183 | X37: 0 | Y37: 0 | Z37: 0 | AA37: 0 | AB37: 73426 | AC37: 0 | AE37: {=SUM(AF37:AG37)} -> 0 | AF37: 0 | AG37: 0 | AH37: 0
A38: 43952 | B38: {=ROUND(C38/'variables - Table 1-1'!B37,0)} -> 0 | C38: {=SUM(E38:J38)-F38} -> 0 | D38: {=SUM(E38:G38)-F38} -> 0 | E38: {=0} -> 0 | F38: {='presupuesto - Ingreso líquido'!$D$19} -> 199398 | G38: {='net worth - retiro'!D40} -> 0 | K38: {=C38-N38} -> -1286928 | L38: {=_xlfn.IFERROR(K38/C38,0)} -> 0 | M38: {=N38-AE38} -> 1206928 | N38: {=SUM(P38:X38,AC38)} -> 1286928 | P38: 144756 | Q38: 0 | R38: 0 | S38: 0 | T38: 28580 | U38: 839197 | V38: 185000 | W38: 89395 | X38: 0 | Y38: 0 | Z38: 0 | AA38: 0 | AB38: 36430 | AC38: 0 | AE38: {=SUM(AF38:AG38)} -> 80000 | AF38: 80000 | AG38: 0 | AH38: 0
A39: 43983 | B39: {=ROUND(C39/'variables - Table 1-1'!B38,0)} -> 0 | C39: {=SUM(E39:J39)-F39} -> 0 | D39: {=SUM(E39:G39)-F39} -> 0 | F39: {='presupuesto - Ingreso líquido'!$D$19} -> 199398 | G39: {='net worth - retiro'!D41} -> 0 | K39: {=C39-N39} -> -1614627 | L39: {=_xlfn.IFERROR(K39/C39,0)} -> 0 | M39: {=N39-AE39} -> 1557627 | N39: {=SUM(P39:X39,AC39)} -> 1614627 | P39: 206948 | Q39: 0 | R39: 0 | S39: 0 | T39: 371450 | U39: 860647 | V39: 46000 | W39: {=218582-89000} -> 129582 | X39: 0 | Y39: 0 | Z39: 0 | AA39: 0 | AB39: 44694 | AC39: 0 | AE39: {=SUM(AF39:AG39)} -> 57000 | AF39: 57000 | AG39: 0 | AH39: 0
A40: 44013 | B40: {=ROUND(C40/'variables - Table 1-1'!B39,0)} -> 0 | C40: {=SUM(E40:J40)-F40} -> 0 | D40: {=SUM(E40:G40)-F40} -> 0 | F40: {='presupuesto - Ingreso líquido'!$D$19} -> 199398 | G40: {='net worth - retiro'!D42} -> 0 | K40: {=C40-N40} -> -1233945 | L40: {=_xlfn.IFERROR(K40/C40,0)} -> 0 | M40: {=N40-AE40} -> 1233945 | N40: {=SUM(P40:X40,AC40)} -> 1233945 | P40: 143861 | Q40: 0 | R40: 0 | S40: 0 | T40: {=942228-832064} -> 110164 | U40: 846355 | V40: 31980 | W40: 101585 | X40: 0 | Y40: 0 | Z40: 0 | AA40: 0 | AB40: 97805 | AC40: 0 | AE40: {=SUM(AF40:AG40)} -> 0 | AF40: 0 | AG40: {=0} -> 0 | AH40: 77326
A41: 44044 | B41: {=ROUND(C41/'variables - Table 1-1'!B40,0)} -> 3244 | C41: {=SUM(E41:J41)} -> 2527269 | D41: {=SUM(E41:G41)} -> 2427269 | E41: 2000001 | F41: {='presupuesto - Ingreso líquido'!$D$19} -> 199398 | G41: {='net worth - retiro'!D43} -> 227870 | H41: 100000 | K41: {=C41-N41} -> 641153 | L41: {=_xlfn.IFERROR(K41/C41,0)} -> 0.25369401 | M41: {=N41-AE41} -> 1486116 | N41: {=SUM(P41:X41,AC41)} -> 1886116 | P41: 225066 | Q41: 0 | R41: 0 | S41: 0 | T41: 417365 | U41: 839762 | V41: 302440 | W41: 101483 | X41: 0 | Y41: 0 | Z41: 0 | AA41: 0 | AB41: 14695 | AC41: 0 | AE41: {=SUM(AF41:AG41)} -> 400000 | AF41: 0 | AG41: 400000 | AH41: 0
A42: 44075 | B42: {=ROUND(C42/'variables - Table 1-1'!B41,0)} -> 3096 | C42: {=SUM(E42:J42)} -> 2427182 | D42: {=SUM(E42:G42)} -> 2427182 | E42: {=1999914} -> 1999914 | F42: {='presupuesto - Ingreso líquido'!$D$19} -> 199398 | G42: {='net worth - retiro'!D44} -> 227870 | K42: {=C42-N42} -> 192178 | L42: {=_xlfn.IFERROR(K42/C42,0)} -> 0.079177416 | M42: {=N42-AE42} -> 2198004 | N42: {=SUM(P42:X42,AC42)} -> 2235004 | P42: 236159 | Q42: 23870 | R42: 0 | S42: 0 | T42: 582115 | U42: 917981 | V42: 265000 | W42: 119813 | X42: 90066 | Y42: 6266 | Z42: 0 | AA42: 0 | AB42: 67802 | AC42: 0 | AE42: {=SUM(AF42:AG42)} -> 37000 | AF42: 0 | AG42: 37000 | AH42: 667015
A43: 44105 | B43: {=ROUND(C43/'variables - Table 1-1'!B42,0)} -> 3144 | C43: {=SUM(E43:J43)} -> 2425801 | D43: {=SUM(E43:G43)} -> 2425801 | E43: 1998533 | F43: {='presupuesto - Ingreso líquido'!$D$19} -> 199398 | G43: {='net worth - retiro'!D45} -> 227870 | K43: {=C43-N43} -> 920964 | L43: {=_xlfn.IFERROR(K43/C43,0)} -> 0.37965357 | M43: {=N43-AE43} -> 1504837 | N43: {=SUM(P43:X43,AC43)} -> 1504837 | P43: 275767 | Q43: 0 | R43: 0 | S43: 0 | T43: 208314 | U43: 861986 | V43: 53388 | W43: 105382 | X43: 0 | Y43: 0 | Z43: 0 | AA43: 0 | AB43: 179169 | AC43: 0 | AE43: {=SUM(AF43:AG43)} -> 0 | AF43: 0 | AG43: 0 | AH43: 0
A44: 44136 | B44: {=ROUND(C44/'variables - Table 1-1'!B43,0)} -> 3158 | C44: {=SUM(E44:J44)} -> 2425888 | D44: {=SUM(E44:G44)} -> 2425888 | E44: 1998620 | F44: {='presupuesto - Ingreso líquido'!$D$19} -> 199398 | G44: {='net worth - retiro'!D46} -> 227870 | K44: {=C44-N44} -> 468904 | L44: {=_xlfn.IFERROR(K44/C44,0)} -> 0.19329169 | M44: {=N44-AE44} -> 1906984 | N44: {=SUM(P44:X44,AC44)} -> 1956984 | P44: 223549 | Q44: 15290 | R44: 0 | S44: 22000 | T44: 650987 | U44: 882375 | V44: 50000 | W44: 112783 | X44: 0 | Y44: 0 | Z44: 0 | AA44: 32305 | AB44: 169836 | AC44: 0 | AE44: {=SUM(AF44:AG44)} -> 50000 | AF44: 0 | AG44: 50000 | AH44: 200859
A45: 44166 | B45: {=ROUND(C45/'variables - Table 1-1'!B44,0)} -> 3425 | C45: {=SUM(E45:J45)} -> 2435340 | D45: {=SUM(E45:G45)} -> 2435340 | E45: 2008072 | F45: {='presupuesto - Ingreso líquido'!$D$19} -> 199398 | G45: {='net worth - retiro'!D47} -> 227870 | K45: {=C45-N45} -> 344702 | L45: {=_xlfn.IFERROR(K45/C45,0)} -> 0.14154163 | M45: {=N45-AE45} -> 1990638 | N45: {=SUM(P45:X45,AC45)} -> 2090638 | P45: 231031 | Q45: 0 | R45: 0 | S45: 22000 | T45: 582875 | U45: 849018 | V45: 123380 | W45: 247448 | X45: 34886 | Y45: 0 | Z45: 0 | AA45: 0 | AB45: 120721 | AC45: 0 | AE45: {=SUM(AF45:AG45)} -> 100000 | AF45: 0 | AG45: 100000 | AH45: 0
A46: 44197 | B46: {=ROUND(C46/'variables - Table 1-1'!B45,0)} -> 4293 | C46: {=SUM(E46:J46)} -> 3157488 | D46: {=SUM(E46:G46)} -> 2428817 | E46: 2001549 | F46: {='presupuesto - Ingreso líquido'!$D$19} -> 199398 | G46: {='net worth - retiro'!D48} -> 227870 | H46: {=2050041*0+20000+708671} -> 728671 | K46: {=C46-N46} -> 1578912 | L46: {=_xlfn.IFERROR(K46/C46,0)} -> 0.50005321 | M46: {=N46-AE46+2399990} -> 1578576 | N46: {=SUM(P46:X46,AC46)} -> 1578576 | P46: 200188 | Q46: 0 | R46: 11090 | S46: 5000 | T46: 234130 | U46: 871405 | V46: 124000 | W46: 132373 | X46: 390 | Y46: 0 | Z46: 0 | AA46: 16426 | AB46: 128506 | AC46: 0 | AE46: {=SUM(AF46:AG46)} -> 2399990 | AF46: 0 | AG46: 2399990 | AH46: 0
A47: 44228 | B47: {=ROUND(C47/'variables - Table 1-1'!B46,0)} -> 5924 | C47: {=SUM(E47:J47)} -> 4238300 | D47: {=SUM(E47:G47)*0} -> 0 | E47: {=748030+3406414} -> 4154444 | F47: {='presupuesto - Ingreso líquido'!$D$19*0} -> 0 | G47: {='net worth - retiro'!D49} -> 83856 | K47: {=C47-N47} -> 2712367 | L47: {=_xlfn.IFERROR(K47/C47,0)} -> 0.63996579 | M47: {=N47-AE47} -> 1525933 | N47: {=SUM(P47:X47,AC47)} -> 1525933 | P47: 201137 | Q47: 0 | R47: 9300 | S47: 10000 | T47: {=310962-266925} -> 44037 | U47: 855087 | V47: 242000 | W47: 120472 | X47: 43900 | Y47: 0 | Z47: 0 | AA47: 15795 | AB47: 56259 | AC47: 0 | AE47: {=SUM(AF47:AG47)} -> 0 | AF47: 0 | AG47: 0 | AH47: 0
A48: 44256 | B48: {=ROUND(C48/'variables - Table 1-1'!B47,0)} -> 4262 | C48: {=SUM(E48:J48)} -> 3106414 | D48: {=SUM(E48:G48)*0} -> 0 | E48: 3106414 | F48: {='presupuesto - Ingreso líquido'!$D$19*0} -> 0 | G48: {='net worth - retiro'!D50*0} -> 0 | K48: {=C48-N48} -> 1546879 | L48: {=_xlfn.IFERROR(K48/C48,0)} -> 0.49796292 | M48: {=N48-AE48} -> 1549535 | N48: {=SUM(P48:X48,AC48)} -> 1559535 | P48: 257218 | Q48: 22990 | R48: 0 | S48: 12000 | T48: 87496 | U48: 869632 | V48: 93000 | W48: 108367 | X48: 108832 | Y48: 0 | Z48: 0 | AA48: 34251 | AB48: 109324 | AC48: 0 | AE48: {=SUM(AF48:AG48)} -> 10000 | AF48: 0 | AG48: 10000 | AH48: 0
A49: 44287 | B49: {=ROUND(C49/'variables - Table 1-1'!B48,0)} -> 4382 | C49: {=SUM(E49:J49)} -> 3106414 | D49: {=SUM(E49:G49)*0} -> 0 | E49: 3106414 | F49: {='presupuesto - Ingreso líquido'!$D$19*0} -> 0 | G49: {='net worth - retiro'!D51*0} -> 0 | K49: {=C49-N49} -> 1531652 | L49: {=_xlfn.IFERROR(K49/C49,0)} -> 0.49306113 | M49: {=N49-AE49} -> 1574762 | N49: {=SUM(P49:X49,AC49)} -> 1574762 | P49: 215959 | Q49: 0 | R49: 12000 | S49: 0 | T49: 313511 | U49: 875467 | V49: 0 | W49: 101790 | X49: 56035 | Y49: 0 | Z49: 0 | AA49: 17550 | AB49: 59003 | AC49: 0 | AE49: {=SUM(AF49:AG49)} -> 0 | AF49: 0 | AG49: 0 | AH49: 0
A50: 44317 | B50: {=ROUND(C50/'variables - Table 1-1'!B49,0)} -> 4733 | C50: {=SUM(E50:J50)} -> 3426779 | D50: {=SUM(E50:G50)*0} -> 0 | E50: 3106414 | F50: {='presupuesto - Ingreso líquido'!$D$19*0} -> 0 | G50: {='net worth - retiro'!D52*0} -> 0 | H50: 320365 | K50: {=C50-N50} -> 1775026 | L50: {=_xlfn.IFERROR(K50/C50,0)} -> 0.51798672 | M50: {=N50-AE50} -> 1636753 | N50: {=SUM(P50:X50,AC50)} -> 1651753 | P50: 241188 | Q50: 12265 | R50: 0 | S50: 0 | T50: 107823 | U50: 821764 | V50: 319000 | W50: 149713 | X50: 0 | Y50: 0 | Z50: 0 | AA50: 41972 | AB50: 51721 | AC50: 0 | AE50: {=SUM(AF50:AG50)} -> 15000 | AF50: 0 | AG50: 15000 | AH50: 0
A51: 44348 | B51: {=ROUND(C51/'variables - Table 1-1'!B50,0)} -> 4424 | C51: {=SUM(E51:J51)} -> 3217065 | D51: {=SUM(E51:G51)*0} -> 0 | E51: 3150539 | F51: {='presupuesto - Ingreso líquido'!$D$19*0} -> 0 | G51: {='net worth - retiro'!D53*0} -> 0 | H51: 66526 | K51: {=C51-N51} -> 788967 | L51: {=_xlfn.IFERROR(K51/C51,0)} -> 0.24524435 | M51: {=N51-AE51} -> 2428098 | N51: {=SUM(P51:X51,AC51)} -> 2428098 | P51: 401073 | Q51: 0 | R51: 0 | S51: 0 | T51: 762495 | U51: 815209 | V51: {=238000+90000} -> 328000 | W51: 121321 | X51: 0 | Y51: 0 | Z51: 0 | AA51: 13413 | AB51: 34595 | AC51: 0 | AE51: {=SUM(AF51:AG51)} -> 0 | AF51: 0 | AG51: 0 | AH51: 0
A52: 44378 | B52: {=ROUND(C52/'variables - Table 1-1'!B51,0)} -> 4302 | C52: {=SUM(E52:J52)} -> 3268652 | D52: {=SUM(E52:G52)*0} -> 0 | E52: {=2898652+500*740} -> 3268652 | F52: {='presupuesto - Ingreso líquido'!$D$19*0} -> 0 | G52: {='net worth - retiro'!D54*0} -> 0 | K52: {=C52-N52} -> 1238218 | L52: {=_xlfn.IFERROR(K52/C52,0)} -> 0.3788161 | M52: {=N52-AE52} -> 2030434 | N52: {=SUM(P52:X52,AC52)} -> 2030434 | P52: 259862 | Q52: 33000 | R52: 0 | S52: 12000 | T52: 321276 | U52: 861303 | V52: 388000 | W52: 127761 | X52: 27232 | Y52: 0 | Z52: 0 | AA52: 18966 | AB52: 60137 | AC52: 0 | AE52: {=SUM(AF52:AG52)} -> 0 | AF52: 0 | AG52: 0 | AH52: 0
A53: 44409 | B53: {=ROUND(C53/'variables - Table 1-1'!B52,0)} -> 3568 | C53: {=SUM(E53:J53)} -> 2791155 | D53: {=SUM(E53:G53)*0} -> 0 | E53: {=2935041-143886} -> 2791155 | F53: {='presupuesto - Ingreso líquido'!$D$19*0} -> 0 | G53: {='net worth - retiro'!D55*0} -> 0 | K53: {=C53-N53} -> -1726685 | L53: {=_xlfn.IFERROR(K53/C53,0)} -> -0.61862741 | M53: {=N53-AE53} -> 4373954 | N53: {=SUM(P53:X53,AC53)} -> 4517840 | P53: 202884 | Q53: 36630 | R53: 56140 | S53: 80900 | T53: 1907264 | U53: 1596301 | V53: {=383000+120000} -> 503000 | W53: 134721 | X53: 0 | Y53: 0 | Z53: 0 | AA53: 10213 | AB53: 792738 | AC53: 0 | AE53: {=SUM(AF53:AG53)} -> 143886 | AF53: 0 | AG53: 143886 | AH53: 0
A54: 44440 | B54: {=ROUND(C54/'variables - Table 1-1'!B53,0)} -> 0 | C54: {=SUM(E54:J54)} -> 0 | D54: {=SUM(E54:G54)*0} -> 0 | F54: {='presupuesto - Ingreso líquido'!$D$19*0} -> 0 | G54: {='net worth - retiro'!D56*0} -> 0 | K54: {=C54-N54} -> -2620675 | L54: {=_xlfn.IFERROR(K54/C54,0)} -> 0 | M54: {=N54-AE54} -> 2620675 | N54: {=SUM(P54:X54,AC54)} -> 2620675 | P54: 0 | Q54: 0 | R54: 0 | S54: 0 | T54: 1800422 | U54: 820253 | V54: 0 | W54: 0 | X54: 0 | Y54: 0 | Z54: 0 | AA54: 0 | AB54: 2608685 | AC54: 0 | AE54: {=SUM(AF54:AG54)} -> 0 | AF54: 0 | AG54: 0 | AH54: 0
A55: 44470 | B55: {=ROUND(C55/'variables - Table 1-1'!B54,0)} -> 0 | C55: {=SUM(E55:J55)} -> 0 | D55: {=SUM(E55:G55)*0} -> 0 | K55: {=C55-N55} -> -930817 | L55: {=_xlfn.IFERROR(K55/C55,0)} -> 0 | M55: {=N55-AE55} -> 930817 | N55: {=SUM(P55:X55,AC55)} -> 930817 | P55: {='flujos - Gasto mes actual'!D$37} -> 0 | Q55: {='flujos - Gasto mes actual'!H$37} -> 0 | R55: {='flujos - Gasto mes actual'!L$37} -> 0 | S55: {='flujos - Gasto mes actual'!P$37} -> 0 | T55: {='flujos - Gasto mes actual'!T$37} -> 0 | U55: {='flujos - Gasto mes actual'!$AA$37} -> 930817 | V55: {='flujos - Gasto mes actual'!X$37} -> 0 | W55: {='flujos - Gasto mes actual'!AE$37} -> 0 | X55: {='flujos - Gasto mes actual'!AI$37} -> 0 | Y55: {='flujos - Gasto mes actual'!$AI$4} -> 0 | Z55: {='flujos - Gasto mes actual'!$AI$5} -> 0 | AA55: {='flujos - Gasto mes actual'!$AN$6} -> 0 | AB55: {='flujos - Gasto mes actual'!AN$37} -> 0 | AC55: 0 | AE55: {=SUM(AF55:AG55)} -> 0 | AF55: {='flujos - Totales'!$B$9} -> 0 | AG55: {='flujos - Totales'!$B$3} -> 0 | AH55: {='flujos - Totales'!$B$14} -> 0
A56: 44501 | B56: {=ROUND(C56/'variables - Table 1-1'!B55,0)} -> 0 | C56: {=SUM(E56:J56)} -> 0 | D56: {=SUM(E56:G56)*0} -> 0 | K56: {=C56-N56} -> 0 | L56: {=_xlfn.IFERROR(K56/C56,0)} -> 0 | M56: {=N56-AE56} -> 0 | N56: {=SUM(P56:X56,AC56)} -> 0 | AE56: {=SUM(AF56:AG56)} -> 0
A57: 44531 | B57: {=ROUND(C57/'variables - Table 1-1'!B56,0)} -> 0 | C57: {=SUM(E57:J57)} -> 0 | D57: {=SUM(E57:G57)*0} -> 0 | K57: {=C57-N57} -> 0 | L57: {=_xlfn.IFERROR(K57/C57,0)} -> 0 | M57: {=N57-AE57} -> 0 | N57: {=SUM(P57:X57,AC57)} -> 0 | AE57: {=SUM(AF57:AG57)} -> 0
A58: 44562 | B58: {=ROUND(C58/'variables - Table 1-1'!B57,0)} -> 0 | C58: {=SUM(E58:J58)} -> 0 | D58: {=SUM(E58:G58)*0} -> 0 | K58: {=C58-N58} -> 0 | L58: {=_xlfn.IFERROR(K58/C58,0)} -> 0 | M58: {=N58-AE58} -> 0 | N58: {=SUM(P58:X58,AC58)} -> 0 | AE58: {=SUM(AF58:AG58)} -> 0
A59: 44593 | B59: {=ROUND(C59/'variables - Table 1-1'!B58,0)} -> 0 | C59: {=SUM(E59:J59)} -> 0 | D59: {=SUM(E59:G59)*0} -> 0 | K59: {=C59-N59} -> 0 | L59: {=_xlfn.IFERROR(K59/C59,0)} -> 0 | M59: {=N59-AE59} -> 0 | N59: {=SUM(P59:X59,AC59)} -> 0 | AE59: {=SUM(AF59:AG59)} -> 0
A60: 44621 | B60: {=ROUND(C60/'variables - Table 1-1'!B59,0)} -> 0 | C60: {=SUM(E60:J60)} -> 0 | D60: {=SUM(E60:G60)*0} -> 0 | K60: {=C60-N60} -> 0 | L60: {=_xlfn.IFERROR(K60/C60,0)} -> 0 | M60: {=N60-AE60} -> 0 | N60: {=SUM(P60:X60,AC60)} -> 0 | AE60: {=SUM(AF60:AG60)} -> 0
A61: 44652 | B61: {=ROUND(C61/'variables - Table 1-1'!B60,0)} -> 0 | C61: {=SUM(E61:J61)} -> 0 | D61: {=SUM(E61:G61)*0} -> 0 | K61: {=C61-N61} -> 0 | L61: {=_xlfn.IFERROR(K61/C61,0)} -> 0 | M61: {=N61-AE61} -> 0 | N61: {=SUM(P61:X61,AC61)} -> 0 | AE61: {=SUM(AF61:AG61)} -> 0
A62: 44682 | B62: {=ROUND(C62/'variables - Table 1-1'!B61,0)} -> 0 | C62: {=SUM(E62:J62)} -> 0 | D62: {=SUM(E62:G62)*0} -> 0 | K62: {=C62-N62} -> 0 | L62: {=_xlfn.IFERROR(K62/C62,0)} -> 0 | M62: {=N62-AE62} -> 0 | N62: {=SUM(P62:X62,AC62)} -> 0 | AE62: {=SUM(AF62:AG62)} -> 0
A63: 44713 | B63: {=ROUND(C63/'variables - Table 1-1'!B62,0)} -> 0 | C63: {=SUM(E63:J63)} -> 0 | D63: {=SUM(E63:G63)*0} -> 0 | K63: {=C63-N63} -> 0 | L63: {=_xlfn.IFERROR(K63/C63,0)} -> 0 | M63: {=N63-AE63} -> 0 | N63: {=SUM(P63:X63,AC63)} -> 0 | AE63: {=SUM(AF63:AG63)} -> 0
A64: 44743 | B64: {=ROUND(C64/'variables - Table 1-1'!B63,0)} -> 0 | C64: {=SUM(E64:J64)} -> 0 | D64: {=SUM(E64:G64)*0} -> 0 | K64: {=C64-N64} -> 0 | L64: {=_xlfn.IFERROR(K64/C64,0)} -> 0 | M64: {=N64-AE64} -> 0 | N64: {=SUM(P64:X64,AC64)} -> 0 | AE64: {=SUM(AF64:AG64)} -> 0
A65: 44774 | B65: {=ROUND(C65/'variables - Table 1-1'!B64,0)} -> 0 | C65: {=SUM(E65:J65)} -> 0 | D65: {=SUM(E65:G65)*0} -> 0 | K65: {=C65-N65} -> 0 | L65: {=_xlfn.IFERROR(K65/C65,0)} -> 0 | M65: {=N65-AE65} -> 0 | N65: {=SUM(P65:X65,AC65)} -> 0 | AE65: {=SUM(AF65:AG65)} -> 0
A66: 44805 | B66: {=ROUND(C66/'variables - Table 1-1'!B65,0)} -> 3637 | C66: {=SUM(D66)} -> 3503481.9 | D66: 3503481.9 | E66: 3000565 | K66: {=C66-N66} -> 3503481.9 | L66: {=_xlfn.IFERROR(K66/C66,0)} -> 1 | M66: {=N66-AE66} -> 0 | N66: {=SUM(P66:X66,AC66)} -> 0 | AE66: {=SUM(AF66:AG66)} -> 0
A67: 44835 | B67: {=ROUND(C67/'variables - Table 1-1'!B66,0)} -> 3716 | C67: {=SUM(D67)} -> 3503982.5 | D67: 3503982.5 | E67: 2999530 | K67: {=C67-N67} -> 3503982.5 | L67: {=_xlfn.IFERROR(K67/C67,0)} -> 1 | M67: {=N67-AE67} -> 0 | N67: {=SUM(P67:X67,AC67)} -> 0 | AE67: {=SUM(AF67:AG67)} -> 0
A68: 44866 | B68: {=ROUND(C68/'variables - Table 1-1'!B67,0)} -> 4198 | C68: {=SUM(D68)} -> 3778796 | D68: 3778796 | E68: 3075345 | K68: {=C68-N68} -> 3778796 | L68: {=_xlfn.IFERROR(K68/C68,0)} -> 1 | M68: {=N68-AE68} -> 0 | N68: {=SUM(P68:X68,AC68)} -> 0 | AE68: {=SUM(AF68:AG68)} -> 0
A69: 44896 | B69: {=ROUND(C69/'variables - Table 1-1'!B68,0)} -> 4416 | C69: {=SUM(D69)} -> 3780012 | D69: 3780012 | E69: 3072997 | K69: {=C69-N69} -> 3780012 | L69: {=_xlfn.IFERROR(K69/C69,0)} -> 1 | M69: {=N69-AE69} -> 0 | N69: {=SUM(P69:X69,AC69)} -> 0 | AE69: {=SUM(AF69:AG69)} -> 0
A70: 44927 | B70: {=ROUND(C70/'variables - Table 1-1'!B69,0)} -> 4688 | C70: {=SUM(D70)} -> 3783202 | D70: 3783202 | E70: 3076959 | K70: {=C70-N70} -> 3783202 | L70: {=_xlfn.IFERROR(K70/C70,0)} -> 1 | M70: {=N70-AE70} -> 0 | N70: {=SUM(P70:X70,AC70)} -> 0 | AE70: {=SUM(AF70:AG70)} -> 0
A71: 44958 | B71: {=ROUND(C71/'variables - Table 1-1'!B70,0)} -> 4541 | C71: {=SUM(D71)} -> 3783294 | D71: 3783294 | E71: 3075033 | K71: {=C71-N71} -> 3783294 | L71: {=_xlfn.IFERROR(K71/C71,0)} -> 1 | M71: {=N71-AE71} -> 0 | N71: {=SUM(P71:X71,AC71)} -> 0 | AE71: {=SUM(AF71:AG71)} -> 0
A72: 44986 | B72: {=ROUND(C72/'variables - Table 1-1'!B71,0)} -> 4796 | C72: {=SUM(D72)} -> 3783536 | D72: 3783536 | E72: 3076443 | K72: {=C72-N72} -> 3783536 | L72: {=_xlfn.IFERROR(K72/C72,0)} -> 1 | M72: {=N72-AE72} -> 0 | N72: {=SUM(P72:X72,AC72)} -> 0 | AE72: {=SUM(AF72:AG72)} -> 0
A73: 45017 | B73: {=ROUND(C73/'variables - Table 1-1'!B72,0)} -> 4713 | C73: {=SUM(D73)} -> 3783504 | D73: 3783504 | E73: 3072900 | K73: {=C73-N73} -> 3783504 | L73: {=_xlfn.IFERROR(K73/C73,0)} -> 1 | M73: {=N73-AE73} -> 0 | N73: {=SUM(P73:X73,AC73)} -> 0 | AE73: {=SUM(AF73:AG73)} -> 0
A74: 45047 | B74: {=ROUND(C74/'variables - Table 1-1'!B73,0)} -> 4703 | C74: {=SUM(D74)} -> 3782836 | D74: 3782836 | E74: 3072705 | K74: {=C74-N74} -> 3782836 | L74: {=_xlfn.IFERROR(K74/C74,0)} -> 1 | M74: {=N74-AE74} -> 0 | N74: {=SUM(P74:X74,AC74)} -> 0 | AE74: {=SUM(AF74:AG74)} -> 0
A75: 45078 | B75: {=ROUND(C75/'variables - Table 1-1'!B74,0)} -> 4743 | C75: {=SUM(D75)} -> 3807533 | D75: 3807533 | E75: 3094006 | K75: {=C75-N75} -> 3807533 | L75: {=_xlfn.IFERROR(K75/C75,0)} -> 1 | M75: {=N75-AE75} -> 0 | N75: {=SUM(P75:X75,AC75)} -> 0 | AE75: {=SUM(AF75:AG75)} -> 0
A76: 45108 | B76: {=ROUND(C76/'variables - Table 1-1'!B75,0)} -> 4584 | C76: {=SUM(D76)} -> 3794771 | D76: 3794771 | E76: 3083791 | K76: {=C76-N76} -> 3794771 | L76: {=_xlfn.IFERROR(K76/C76,0)} -> 1 | M76: {=N76-AE76} -> 0 | N76: {=SUM(P76:X76,AC76)} -> 0 | AE76: {=SUM(AF76:AG76)} -> 0
A77: 45139 | B77: {=ROUND(C77/'variables - Table 1-1'!B76,0)} -> 4455 | C77: {=SUM(D77)} -> 3795039 | D77: 3795039 | E77: 3082497 | K77: {=C77-N77} -> 3795039 | L77: {=_xlfn.IFERROR(K77/C77,0)} -> 1 | M77: {=N77-AE77} -> 0 | N77: {=SUM(P77:X77,AC77)} -> 0 | AE77: {=SUM(AF77:AG77)} -> 0
... A85: 45383 | B85: {=ROUND(C85/'variables - Table 1-1'!B84,0)} -> 4039 | C85: {=SUM(D85)} -> 3802758 | D85: 3802758 | E85: 3064580 | K85: {=C85-N85} -> 3802758 | L85: {=_xlfn.IFERROR(K85/C85,0)} -> 1 | M85: {=N85-AE85} -> 0 | N85: {=SUM(P85:X85,AC85)} -> 0 | AE85: {=SUM(AF85:AG85)} -> 0
A86: 45413 | B86: {=ROUND(C86/'variables - Table 1-1'!B85,0)} -> 4148 | C86: {=SUM(D86)} -> 3802877 | D86: 3802877 | E86: 3062633 | K86: {=C86-N86} -> 3802877 | L86: {=_xlfn.IFERROR(K86/C86,0)} -> 1 | M86: {=N86-AE86} -> 0 | N86: {=SUM(P86:X86,AC86)} -> 0 | U86: {='net worth - resumen | depósitos'!B86} -> 0 | AE86: {=SUM(AF86:AG86)} -> 0
A87: 45444 | B87: {=ROUND(C87/'variables - Table 1-1'!B86,0)} -> 3986 | C87: {=SUM(D87)} -> 3803028 | D87: 3803028 | E87: 3061398 | K87: {=C87-N87} -> 2603028 | L87: {=_xlfn.IFERROR(K87/C87,0)} -> 0.68446196 | M87: {=N87-AE87} -> 1200000 | N87: {=SUM(P87:X87,AC87)} -> 1200000 | U87: {='net worth - resumen | depósitos'!B87} -> 1200000 | AE87: {=SUM(AF87:AG87)} -> 0
A88: 45474 | B88: {=ROUND(C88/'variables - Table 1-1'!B87,0)} -> 4096 | C88: {=SUM(D88)} -> 3913957 | D88: 3913957 | E88: 3163005 | K88: {=C88-N88} -> 902816 | L88: {=_xlfn.IFERROR(K88/C88,0)} -> 0.23066579 | M88: {=N88-AE88} -> 3011141 | N88: {=SUM(P88:X88,AC88)} -> 3011141 | U88: {='net worth - resumen | depósitos'!B88} -> 3011141 | AE88: {=SUM(AF88:AG88)} -> 0
A89: 45505 | B89: {=ROUND(C89/'variables - Table 1-1'!B88,0)} -> 4176 | C89: {=SUM(D89)} -> 3818923 | D89: 3818923 | E89: 3073630 | K89: {=C89-N89} -> 809347 | L89: {=_xlfn.IFERROR(K89/C89,0)} -> 0.21193069 | M89: {=N89-AE89} -> 3009576 | N89: {=SUM(P89:X89,AC89)} -> 3009576 | U89: {='net worth - resumen | depósitos'!B89} -> 3009576 | AE89: {=SUM(AF89:AG89)} -> 0
A90: 45536 | B90: {=ROUND(C90/'variables - Table 1-1'!B89,0)} -> 4245 | C90: {=SUM(D90)} -> 3819135 | D90: 3819135 | E90: 3072317 | K90: {=C90-N90} -> 789050 | L90: {=_xlfn.IFERROR(K90/C90,0)} -> 0.20660438 | M90: {=N90-AE90} -> 3030085 | N90: {=SUM(P90:X90,AC90)} -> 3030085 | P90: {='flujos - Gasto mes actual'!D$37} -> 0 | Q90: {='flujos - Gasto mes actual'!H$37} -> 0 | R90: {='flujos - Gasto mes actual'!L$37} -> 0 | S90: {='flujos - Gasto mes actual'!P$37} -> 0 | T90: {='flujos - Gasto mes actual'!T$37} -> 0 | U90: {='net worth - resumen | depósitos'!B90} -> 3030085 | V90: {='flujos - Gasto mes actual'!X$37} -> 0 | W90: {='flujos - Gasto mes actual'!AE$37} -> 0 | X90: {='flujos - Gasto mes actual'!AI$37} -> 0 | Y90: {='flujos - Gasto mes actual'!$AI$4} -> 0 | Z90: {='flujos - Gasto mes actual'!$AI$5} -> 0 | AA90: {='flujos - Gasto mes actual'!$AN$6} -> 0 | AB90: {='flujos - Gasto mes actual'!AN$37} -> 0 | AE90: {=SUM(AF90:AG90)} -> 0
A91: 45566 | B91: {=ROUND(C91/'variables - Table 1-1'!B90,0)} -> 3973 | C91: {=SUM(D91)} -> 3819227 | D91: 3819227 | E91: 3062609 | K91: {=C91-N91} -> 780868 | L91: {=_xlfn.IFERROR(K91/C91,0)} -> 0.20445708 | M91: {=N91-AE91} -> 3038359 | N91: {=SUM(P91:X91,AC91)} -> 3038359 | U91: {='net worth - resumen | depósitos'!B91} -> 3038359 | AE91: {=SUM(AF91:AG91)} -> 0
A92: 45597 | B92: {=ROUND(C92/'variables - Table 1-1'!B91,0)} -> 3907 | C92: {=SUM(D92)} -> 3818846 | D92: 3818846 | E92: 3058907 | K92: {=C92-N92} -> -19206863 | L92: {=_xlfn.IFERROR(K92/C92,0)} -> -5.029494 | M92: {=N92-AE92} -> 23025709 | N92: {=SUM(P92:X92,AC92)} -> 23025709 | U92: {='net worth - resumen | depósitos'!B92} -> 22825709 | V92: 200000 | AE92: {=SUM(AF92:AG92)} -> 0
A93: 45627 | B93: {=ROUND(C93/'variables - Table 1-1'!B92,0)} -> 3845 | C93: {=SUM(D93)} -> 3819149 | D93: 3819149 | E93: 3057736 | K93: {=C93-N93} -> 548107 | L93: {=_xlfn.IFERROR(K93/C93,0)} -> 0.14351548 | M93: {=N93-AE93} -> 3271042 | N93: {=SUM(P93:X93,AC93)} -> 3271042 | U93: {='net worth - resumen | depósitos'!B93} -> 3071042 | V93: 200000 | AE93: {=SUM(AF93:AG93)} -> 0
A94: 45658 | B94: {=ROUND(C94/'variables - Table 1-1'!B93,0)} -> 3888 | C94: {=SUM(D94)} -> 3824817 | D94: 3824817 | E94: 3046126 | K94: {=C94-N94} -> 803134 | L94: {=_xlfn.IFERROR(K94/C94,0)} -> 0.20997972 | M94: {=N94-AE94} -> 2273347 | N94: {=SUM(P94:X94,AC94)} -> 3021683 | P94: {=SUM('flujos - Table 1-2'!D7:D23,'flujos - Table 1-2'!D31,'flujos - Table 1-2'!D39:D41,'flujos - Table 1-2'!D50:D53,'flujos - Table 1-2'!D73:D75,'flujos - Table 1-2'!D79:D80,'flujos - Table 1-2'!D86)} -> 487730 | Q94: {='flujos - Table 1-2'!D91+'flujos - Table 1-2'!D117} -> 53900 | R94: {=SUM('flujos - Table 1-2'!D104:D105,'flujos - Table 1-2'!D97:D101,'flujos - Table 1-2'!D78)} -> 61575 | T94: {='flujos - Table 1-2'!E$1-(V94+P94+R94+AA94+Q94+S94+W94+X94+U94)} -> -922911 | U94: {='net worth - resumen | depósitos'!B94} -> 3071622 | V94: 200000 | W94: {='flujos - Table 1-2'!D44+'flujos - Table 1-2'!D30} -> 16187 | X94: {='flujos - Table 1-2'!D33} -> 53580 | AE94: {=SUM(AF94:AG94)} -> 748336 | AG94: {=SUM('flujos - Table 1-2'!D56:D72,'flujos - Table 1-2'!D54,'flujos - Table 1-2'!D106:D107,'flujos - Table 1-2'!D84,'flujos - Table 1-2'!D111:D113)} -> 748336
A95: 45689 | B95: {=ROUND(C95/'variables - Table 1-1'!B94,0)} -> 4025 | C95: {=SUM(D95)} -> 3833081 | D95: 3833081 | E95: 3049869 | K95: {=C95-N95} -> -4805253 | L95: {=_xlfn.IFERROR(K95/C95,0)} -> -1.2536268 | M95: {=N95-AE95} -> 8254404 | N95: {=SUM(P95:X95,AC95)} -> 8638334 | P95: {=SUM('flujos - Table 1-3'!D9:D12,'flujos - Table 1-3'!D20:D21,'flujos - Table 1-3'!D22,'flujos - Table 1-3'!D28,'flujos - Table 1-3'!D33:D34,'flujos - Table 1-3'!D48:D52,'flujos - Table 1-3'!D59:D60,'flujos - Table 1-3'!D71,'flujos - Table 1-3'!D95:D96,'flujos - Table 1-3'!D98)} -> 214252 | Q95: {='flujos - Table 1-3'!D90+'flujos - Table 1-3'!D77+'flujos - Table 1-3'!D66} -> 98590 | R95: {=SUM('flujos - Table 1-3'!D78:D89)+'flujos - Table 1-3'!D99+'flujos - Table 1-3'!D64+'flujos - Table 1-3'!D63+'flujos - Table 1-3'!D61+'flujos - Table 1-3'!D29} -> 130607 | S95: {='flujos - Table 1-3'!D32+'flujos - Table 1-3'!D76} -> 16230 | T95: {='flujos - Table 1-3'!E$1-(V95+P95+R95+AA95+Q95+S95+W95+X95+U95)} -> -10974160 | U95: {='net worth - resumen | depósitos'!B95} -> 18672815 | V95: {=205000+245000} -> 450000 | X95: {='flujos - Table 1-3'!D23} -> 30000 | AE95: {=SUM(AF95:AG95)} -> 383930 | AG95: {=SUM('flujos - Table 1-3'!D37:D47,'flujos - Table 1-3'!D35,'flujos - Table 1-3'!D68,'flujos - Table 1-3'!D92)} -> 383930
A96: 45717 | B96: {=ROUND(C96/'variables - Table 1-1'!B95,0)} -> 4332 | C96: {=SUM(D96)} -> 3969354 | D96: 3969354 | E96: 3171856 | I96: 5570207 | K96: {=C96-N96} -> -1476307 | L96: {=_xlfn.IFERROR(K96/C96,0)} -> -0.37192626 | M96: {=N96-AE96} -> 4960556 | N96: {=SUM(P96:X96,AC96)} -> 5445661 | P96: {=SUM('flujos - Table 1-4'!D10:D11,'flujos - Table 1-4'!D21:D22,'flujos - Table 1-4'!D27:D30,'flujos - Table 1-4'!D31:D32,'flujos - Table 1-4'!D56:D57,'flujos - Table 1-4'!D78,'flujos - Table 1-4'!E96:E97,'flujos - Table 1-4'!E94:E95)} -> 362084 | Q96: {='flujos - Table 1-4'!D90} -> 29900 | R96: {=SUM('flujos - Table 1-4'!D91:D97,'flujos - Table 1-4'!D70:D71,'flujos - Table 1-4'!D67:D68,'flujos - Table 1-4'!D65,'flujos - Table 1-4'!D64,'flujos - Table 1-4'!D13)} -> 141033 | S96: {='flujos - Table 1-4'!D12} -> 49980 | T96: {='flujos - Table 1-4'!E$1-(V96+P96+R96+AA96+Q96+S96+W96+X96+U96)} -> -23141489 | U96: {='net worth - resumen | depósitos'!B96} -> 27658932 | V96: 200000 | X96: {='flujos - Table 1-4'!D109+'flujos - Table 1-4'!D103+'flujos - Table 1-4'!D17+'flujos - Table 1-4'!D15+'flujos - Table 1-4'!D14} -> 145221 | AE96: {=SUM(AF96:AG96)} -> 485105 | AG96: {=SUM('flujos - Table 1-4'!D35:D55,'flujos - Table 1-4'!D106,'flujos - Table 1-4'!D98,'flujos - Table 1-4'!D33)} -> 485105
A97: 45748 | B97: {=ROUND(C97/'variables - Table 1-1'!B96,0)} -> 4200 | C97: {=SUM(D97)} -> 3969501 | D97: 3969501 | E97: 3169768 | I97: 4870207 | K97: {=C97-N97} -> 209645 | L97: {=_xlfn.IFERROR(K97/C97,0)} -> 0.052813943 | M97: {=N97-AE97} -> 3557580 | N97: {=SUM(P97:X97,AC97)} -> 3759856 | P97: {=SUM('flujos - Table 3-1'!D4:D5,'flujos - Table 3-1'!D17:D21,'flujos - Table 3-1'!D27:D33,'flujos - Table 3-1'!D67:D68,'flujos - Table 3-1'!D75,'flujos - Table 3-1'!D80,'flujos - Table 3-1'!D89)} -> 363950 | R97: {=SUM('flujos - Table 3-1'!D84:D88,'flujos - Table 3-1'!D70,'flujos - Table 3-1'!D66,'flujos - Table 3-1'!D57:D59)+'flujos - Table 3-1'!D90} -> 73887 | T97: {='flujos - Table 3-1'!E$1-(V97+P97+R97+AA97+Q97+S97+W97+X97+U97)} -> 1350021 | U97: {='net worth - resumen | depósitos'!B97} -> 1519135 | V97: 400000 | X97: {='flujos - Table 3-1'!D9+'flujos - Table 3-1'!D97} -> 52863 | AE97: {=SUM(AF97:AG97)} -> 202276 | AG97: {=SUM('flujos - Table 3-1'!D34:D51,'flujos - Table 3-1'!D79,'flujos - Table 3-1'!D26)} -> 202276
A98: 45778 | B98: {=ROUND(C98/'variables - Table 1-1'!B97,0)} -> 4230 | C98: {=SUM(D98)} -> 3969683 | D98: 3969683 | E98: 3168752 | I98: 4170207 | K98: {=C98-N98} -> -426048 | L98: {=_xlfn.IFERROR(K98/C98,0)} -> -0.10732545 | M98: {=N98-AE98} -> 3946001 | N98: {=SUM(P98:X98,AC98)} -> 4395731 | P98: {=SUM('flujos - Table 3-1-1'!D66,'flujos - Table 3-1-1'!D57:D58,'flujos - Table 3-1-1'!D48:D50,'flujos - Table 3-1-1'!D28:D36,'flujos - Table 3-1-1'!D19:D21,'flujos - Table 3-1-1'!D3:D4)} -> 452879 | Q98: {='flujos - Table 3-1-1'!D69+'flujos - Table 3-1-1'!D73} -> 98850 | R98: {=SUM('flujos - Table 3-1-1'!D83,'flujos - Table 3-1-1'!D70:D72,'flujos - Table 3-1-1'!D59,'flujos - Table 3-1-1'!D51)} -> 65724 | S98: {=SUM('flujos - Table 3-1-1'!D9:D10)} -> 119970 | T98: {='flujos - Table 3-1-1'!E$1-(V98+P98+R98+AA98+Q98+S98+W98+X98+U98+AC98)} -> 842120 | U98: 1696375 | V98: 200000 | W98: {='flujos - Table 3-1-1'!D8+'flujos - Table 3-1-1'!D67+'flujos - Table 3-1-1'!D78+'flujos - Table 3-1-1'!D77} -> 189607 | X98: {='flujos - Table 3-1-1'!D11} -> 53571 | AC98: 676635 | AE98: {=SUM(AF98:AG98)} -> 449730 | AG98: {=SUM('flujos - Table 3-1-1'!D74:D75,'flujos - Table 3-1-1'!D85,'flujos - Table 3-1-1'!D37:D47,'flujos - Table 3-1-1'!D27)} -> 449730
A99: 45809 | B99: {=ROUND(C99/'variables - Table 1-1'!B98,0)} -> 4319 | C99: {=SUM(D99)} -> 3969758 | D99: 3969758 | E99: 3167894 | I99: 3970423 | K99: {=C99-N99} -> -520603 | L99: {=_xlfn.IFERROR(K99/C99,0)} -> -0.13114225 | M99: {=N99-AE99} -> 4927630 | N99: {=SUM(P99:X99,AC99)} -> 4490361 | P99: {=SUM('flujos - Table 3-1-1-1'!D2:D4,'flujos - Table 3-1-1-1'!D12,'flujos - Table 3-1-1-1'!D20:D32,'flujos - Table 3-1-1-1'!D59:D60,'flujos - Table 3-1-1-1'!D62)} -> 515069 | T99: {='flujos - Table 3-1-1-1'!D$1-(V99+P99+R99+AA99+Q99+S99+W99+X99+U99+AC99)} -> 1178539 | U99: 1696375 | V99: {=SUM('flujos - Table 3-1-1-1'!D13:D14)} -> 400000 | AC99: 700378 | AE99: {=SUM(AF99:AG99)} -> -437269 | AG99: {=SUM('flujos - Table 3-1-1-1'!D16:D29,'flujos - Table 3-1-1-1'!D31:D32)*-1} -> -437269
A100: 45839 | B100: {=ROUND(C100/'variables - Table 1-1'!B99,0)} -> 4097 | C100: {=SUM(D100)} -> 4020714 | D100: 4020714 | E100: 3215910 | I100: 3470207 | K100: {=C100-N100} -> 2589681 | L100: {=_xlfn.IFERROR(K100/C100,0)} -> 0.64408486 | M100: {=N100-AE100} -> 1023631 | N100: {=SUM(P100:X100,AC100)} -> 1431033 | U100: {='flujos - Gasto mes actual'!$AA$37} -> 930817 | AC100: 500216 | AE100: {=SUM(AF100:AG100)} -> 407402 | AG100: {=SUM('flujos - Table 3-1-1-1'!D33:D34,'flujos - Table 3-1-1-1'!D36:D51)} -> 407402
A101: 45870 | B101: {=ROUND(C101/'variables - Table 1-1'!B100,0)} -> 4109 | C101: {=SUM(D101)} -> 3976953 | D101: 3976953 | E101: 3172662 | I101: 2998443 | K101: {=C101-N101} -> 2543549 | L101: {=_xlfn.IFERROR(K101/C101,0)} -> 0.63957231 | M101: {=N101-AE101} -> 1433404 | N101: {=SUM(P101:X101,AC101)} -> 1433404 | U101: {='flujos - Gasto mes actual'!$AA$37} -> 930817 | AC101: 502587 | AE101: {=SUM(AF101:AG101)} -> 0
A102: 45901 | B102: {=ROUND(C102/'variables - Table 1-1'!B101,0)} -> 4122 | C102: {=SUM(D102)} -> 3977286 | D102: 3977286 | E102: 3166444 | I102: 2765960 | K102: {=C103-N102} -> 2656160 | L102: {=_xlfn.IFERROR(K102/C103,0)} -> 0.66784706 | M102: {=N102-AE102} -> 1321038 | N102: {=SUM(P102:X102,AC102)} -> 1321038 | U102: {='flujos - Gasto mes actual'!$AA$37} -> 930817 | AC102: 390221 | AE102: {=SUM(AF102:AG102)} -> 0
A103: 45931 | B103: {=ROUND(C103/'variables - Table 1-1'!B102,0)} -> 4229 | C103: {=SUM(D103)} -> 3977198 | D103: 3977198 | E103: 3165805 | I103: {=5974709-150000} -> 5824709 | K103: {=C104-N103} -> 2656607 | L103: {=_xlfn.IFERROR(K103/C104,0)} -> 0.66788439 | M103: {=N103-AE103} -> 1321038 | N103: {=SUM(P103:X103,AC103)} -> 1321038 | U103: {='flujos - Gasto mes actual'!$AA$37} -> 930817 | AC103: 390221 | AE103: {=SUM(AF103:AG103)} -> 0
A104: 45962 | B104: {=ROUND(C104/'variables - Table 1-1'!B103,0)} -> 4291 | C104: {=SUM(D104)} -> 3977645 | D104: 3977645 | E104: 3165632 | I104: 5096529 | K104: {=C105-N104} -> 2610749 | L104: {=_xlfn.IFERROR(K104/C105,0)} -> 0.65633318 | M104: {=N104-AE104} -> 1367031 | N104: {=SUM(P104:X104,AC104)} -> 1367031 | U104: {='flujos - Gasto mes actual'!$AA$37} -> 930817 | AC104: 436214 | AE104: {=SUM(AF104:AG104)} -> 0
A105: 45992 | B105: {=ROUND(C105/'variables - Table 1-1'!B104,0)} -> 4420 | C105: {=SUM(D105)} -> 3977780 | D105: 3977780 | E105: 3164430 | I105: 6776991 | K105: {=C106-N105} -> 2602501 | L105: {=_xlfn.IFERROR(K105/C106,0)} -> 0.65425966 | M105: {=N105-AE105} -> 1375279 | N105: {=SUM(P105:X105,AC105)} -> 1375279 | U105: {='flujos - Gasto mes actual'!$AA$37} -> 930817 | AC105: 444462 | AE105: {=SUM(AF105:AG105)} -> 0
A106: 46023 | B106: {=ROUND(C106/'variables - Table 1-1'!B104,0)} -> 4420 | C106: {=SUM(D106)} -> 3977780 | D106: 3977780 | E106: 3164430 | I106: 6121064 | K106: {=C106-N106} -> 2391037 | L106: {=_xlfn.IFERROR(K106/C106,0)} -> 0.60109835 | M106: {=N106-AE106} -> 1586743 | N106: {=SUM(P106:X106,AC106)} -> 1586743 | U106: {='flujos - Gasto mes actual'!$AA$37} -> 930817 | AC106: 655926 | AE106: {=SUM(AF106:AG106)} -> 0
A107: 46054 | B107: {=ROUND(C107/'variables - Table 1-1'!B106,0)} -> 4598 | C107: {=SUM(D107)} -> 3977780 | D107: 3977780 | E107: 3164430 | I107: 5741896 | K107: {=C107-N107} -> 2378845 | L107: {=_xlfn.IFERROR(K107/C107,0)} -> 0.59803333 | M107: {=N107-AE107} -> 1598935 | N107: {=SUM(P107:X107,AC107)} -> 1598935 | U107: {='flujos - Gasto mes actual'!$AA$37} -> 930817 | AC107: 668118 | AE107: {=SUM(AF107:AG107)} -> 0
...

Sheet flujos - Table 1
B1: Cris | C1: Pana | D1: Chamo | E1: Seba
B2: 4000 | C2: 8000 | D2: 7100 | E2: 8000 | H2: 7100
B3: {=3200/4} -> 800 | C3: {=3200/4} -> 800 | D3: 4600 | E3: {=3200/4} -> 800 | H3: 4600
D4: 5400 | H4: 5400
D5: 4600 | H5: 4600
B6: {=SUM(B2:B4)} -> 4800 | C6: {=SUM(C2:C4)} -> 8800 | D6: {=SUM(D2:D5)} -> 21700 | E6: {=SUM(E2:E4)} -> 8800
A7: + propina | B7: {=B6*1.1} -> 5280 | C7: {=C6*1.1} -> 9680 | D7: {=D6*1.1} -> 23870 | E7: {=E6*1.1} -> 9680
A8: + berni | B8: {=B7+$E$7/6} -> 6893.3333 | C8: {=C7+$E$7/6} -> 11293.333 | D8: {=D7+$E$7/6} -> 25483.333

Sheet flujos - Table 1-1
B1: Cris | C1: Wale | D1: Cleme | E1: Seba | F1: Chamo | G1: Pana | I1: acero | J1: hielo
B2: 6400 | C2: 6900 | D2: 6400 | E2: 8500 | F2: 7200 | G2: 7200 | I2: hielo | J2: roca
B3: 2000 | C3: 2700 | D3: 1500 | E3: 2000 | F3: 2700 | G3: 2000 | I3: roca | J3: acero
I4: hi | J4: roca
I5: ac | J5: hielo
I6: r
B7: {=SUM(B2:B6)} -> 8400 | C7: {=SUM(C2:C6)} -> 9600 | D7: {=SUM(D2:D6)} -> 7900 | E7: {=SUM(E2:E6)} -> 10500 | F7: {=SUM(F2:F6)} -> 9900 | G7: {=SUM(G2:G6)} -> 9200 | H7: {=SUM(H2:H6)} -> 0 | I7: {=SUM(I2:I6)} -> 0 | J7: {=SUM(J2:J6)} -> 0
A8: + propina | B8: {=B7*1.1} -> 9240 | C8: {=C7*1.1} -> 10560 | D8: {=D7*1.1} -> 8690 | E8: {=E7*1.1} -> 11550 | F8: {=F7*1.1} -> 10890 | G8: {=G7*1.1} -> 10120 | H8: {=H7*1.1} -> 0 | I8: {=I7*1.1} -> 0 | J8: {=J7*1.1} -> 0
C10: ok | D10: ok | E10: ok | F10: ok | G10: ok

Sheet flujos - Table 1-1-1
B1: Cris | C1: Chamo | D1: Pana | E1: Flavia | F1: Berni | G1: Cleme | I1: 600 | J1: 550
B2: {=15990/6} -> 2665 | C2: {=15990/6} -> 2665 | D2: {=15990/6} -> 2665 | E2: {=15990/6} -> 2665 | F2: {=15990/6} -> 2665 | G2: {=15990/6} -> 2665 | I2: 190 | J2: 80
B3: {=25000/6} -> 4166.6667 | C3: {=25000/6} -> 4166.6667 | D3: {=25000/6} -> 4166.6667 | E3: {=25000/6} -> 4166.6667 | F3: {=25000/6} -> 4166.6667 | G3: {=25000/6} -> 4166.6667 | J3: 80
G4: 1600
I5: {=SUM(I1:I3)} -> 790 | J5: {=SUM(J1:J3)} -> 710
B7: {=SUM(B2:B6)} -> 6831.6667 | C7: {=SUM(C2:C6)} -> 6831.6667 | D7: {=SUM(D2:D6)} -> 6831.6667 | E7: {=SUM(E2:E6)} -> 6831.6667 | F7: {=SUM(F2:F6)} -> 6831.6667 | G7: {=SUM(G2:G6)} -> 8431.6667 | H7: {=SUM(H2:H6)} -> 0 | I7: {=SUM(I2:I6)} -> 980 | J7: {=SUM(J2:J6)} -> 870
A8: + propina | B8: {=B7*1.1} -> 7514.8333 | C8: {=C7*1.1} -> 7514.8333 | D8: {=D7*1.1} -> 7514.8333 | E8: {=E7*1.1} -> 7514.8333 | F8: {=F7*1.1} -> 7514.8333 | G8: {=G7*1.1} -> 9274.8333 | H8: {=H7*1.1} -> 0 | I8: {=I7*1.1} -> 1078 | J8: {=J7*1.1} -> 957
C10: ok | D10: ok | F10: ok | G10: ok

Sheet flujos - Table 3
D1: cuota | F1: offset | G1: llevo | J1: falta | N1: total | S1: 0 | T1: {=S$1+1} -> 1 | U1: {=T$1+1} -> 2 | V1: {=U$1+1} -> 3 | W1: {=V$1+1} -> 4 | X1: {=W$1+1} -> 5 | Y1: {=X$1+1} -> 6 | Z1: {=Y$1+1} -> 7 | AA1: {=Z$1+1} -> 8 | ... AQ1: {=AP$1+1} -> 24
D2: a pagar 10-mar | F2: 11 | P2: {='net worth - Table 1-3'!AE109} -> 0.041282181 | S2: {=EDATE(DATE(2025,6,1),$F$2+S$1)} -> 46143 | T2: {=EDATE(DATE(2025,6,1),$F$2+T$1)} -> 46174 | U2: {=EDATE(DATE(2025,6,1),$F$2+U$1)} -> 46204 | V2: {=EDATE(DATE(2025,6,1),$F$2+V$1)} -> 46235 | W2: {=EDATE(DATE(2025,6,1),$F$2+W$1)} -> 46266 | X2: {=EDATE(DATE(2025,6,1),$F$2+X$1)} -> 46296 | Y2: {=EDATE(DATE(2025,6,1),$F$2+Y$1)} -> 46327 | Z2: {=EDATE(DATE(2025,6,1),$F$2+Z$1)} -> 46357 | ... AQ2: {=EDATE(DATE(2025,6,1),$F$2+AQ$1)} -> 46874
A3: . | B3: funk tribu | D3: {=ROUND(O3/N3,0)} -> 27983 | E3: {=D3/D$17} -> 0.062757068 | F3: -9 | G3: {=F3+F$2} -> 2 | H3: {=IF(G3<0,0,G3/N3)} -> 0.66666667 | I3: {=IF(G3<0,0,D3*G3)} -> 55966 | J3: {=N3-G3} -> 1 | K3: {=1-H3} -> 0.33333333 | L3: {=IF($G3<0,O3,O3-I3)} -> 27984 | M3: {=L3/L$17} -> 0.0063609802 | N3: 3 | O3: 83950 | P3: {=O3*(1+P$2/12)^(N3)} -> 84819.394 | Q3: {=P3-O3} -> 869.3938 | S3: {=IF(AND(1>S$1-$J3,$J3-S$1<$N3),$D3,0)} -> 27983 | T3: {=IF(AND(1>T$1-$J3,$J3-T$1<$N3),$D3,0)} -> 27983 | U3: {=IF(AND(1>U$1-$J3,$J3-U$1<$N3),$D3,0)} -> 0 | V3: {=IF(AND(1>V$1-$J3,$J3-V$1<$N3),$D3,0)} -> 0 | W3: {=IF(AND(1>W$1-$J3,$J3-W$1<$N3),$D3,0)} -> 0 | X3: {=IF(AND(1>X$1-$J3,$J3-X$1<$N3),$D3,0)} -> 0 | Y3: {=IF(AND(1>Y$1-$J3,$J3-Y$1<$N3),$D3,0)} -> 0 | Z3: {=IF(AND(1>Z$1-$J3,$J3-Z$1<$N3),$D3,0)} -> 0 | ... AQ3: {=IF(AND(1>AQ$1-$J3,$J3-AQ$1<$N3),$D3,0)} -> 0
A4: . | B4: respaldo cama | C4: rosen | D4: {=ROUND(O4/N4,0)} -> 13665 | E4: {=D4/D$17} -> 0.030646297 | F4: 0 | G4: {=F4+F$2} -> 11 | H4: {=IF(G4<0,0,G4/N4)} -> 0.91666667 | I4: {=IF(G4<0,0,D4*G4)} -> 150315 | J4: {=N4-G4} -> 1 | K4: {=1-H4} -> 0.083333333 | L4: {=IF($G4<0,O4,O4-I4)} -> 13665 | M4: {=L4/L$17} -> 0.0031061604 | N4: 12 | O4: 163980 | P4: {=O4*(1+P$2/12)^(N4)} -> 170879.02 | Q4: {=P4-O4} -> 6899.0171 | S4: {=IF(AND(1>S$1-$J4,$J4-S$1<$N4),$D4,0)} -> 13665 | T4: {=IF(AND(1>T$1-$J4,$J4-T$1<$N4),$D4,0)} -> 13665 | U4: {=IF(AND(1>U$1-$J4,$J4-U$1<$N4),$D4,0)} -> 0 | V4: {=IF(AND(1>V$1-$J4,$J4-V$1<$N4),$D4,0)} -> 0 | W4: {=IF(AND(1>W$1-$J4,$J4-W$1<$N4),$D4,0)} -> 0 | X4: {=IF(AND(1>X$1-$J4,$J4-X$1<$N4),$D4,0)} -> 0 | Y4: {=IF(AND(1>Y$1-$J4,$J4-Y$1<$N4),$D4,0)} -> 0 | Z4: {=IF(AND(1>Z$1-$J4,$J4-Z$1<$N4),$D4,0)} -> 0 | ... AQ4: {=IF(AND(1>AQ$1-$J4,$J4-AQ$1<$N4),$D4,0)} -> 0
A5: . | B5: la roche | C5: mercadolibre | D5: {=ROUND(O5/N5,0)} -> 9245 | E5: {=D5/D$17} -> 0.020733627 | F5: -7 | G5: {=F5+F$2} -> 4 | H5: {=IF(G5<0,0,G5/N5)} -> 0.66666667 | I5: {=IF(G5<0,0,D5*G5)} -> 36980 | J5: {=N5-G5} -> 2 | K5: {=1-H5} -> 0.33333333 | L5: {=IF($G5<0,O5,O5-I5)} -> 18490 | M5: {=L5/L$17} -> 0.0042029204 | N5: 6 | O5: 55470 | P5: {=O5*(1+P$2/12)^(N5)} -> 56624.854 | Q5: {=P5-O5} -> 1154.8538 | S5: {=IF(AND(1>S$1-$J5,$J5-S$1<$N5),$D5,0)} -> 9245 | T5: {=IF(AND(1>T$1-$J5,$J5-T$1<$N5),$D5,0)} -> 9245 | U5: {=IF(AND(1>U$1-$J5,$J5-U$1<$N5),$D5,0)} -> 9245 | V5: {=IF(AND(1>V$1-$J5,$J5-V$1<$N5),$D5,0)} -> 0 | W5: {=IF(AND(1>W$1-$J5,$J5-W$1<$N5),$D5,0)} -> 0 | X5: {=IF(AND(1>X$1-$J5,$J5-X$1<$N5),$D5,0)} -> 0 | Y5: {=IF(AND(1>Y$1-$J5,$J5-Y$1<$N5),$D5,0)} -> 0 | Z5: {=IF(AND(1>Z$1-$J5,$J5-Z$1<$N5),$D5,0)} -> 0 | ... AQ5: {=IF(AND(1>AQ$1-$J5,$J5-AQ$1<$N5),$D5,0)} -> 0
A6: . | B6: funda ipad | D6: {=ROUND(O6/N6,0)} -> 7416 | E6: {=D6/D$17} -> 0.016631756 | F6: -1 | G6: {=F6+F$2} -> 10 | H6: {=IF(G6<0,0,G6/N6)} -> 0.83333333 | I6: {=IF(G6<0,0,D6*G6)} -> 74160 | J6: {=N6-G6} -> 2 | K6: {=1-H6} -> 0.16666667 | L6: {=IF($G6<0,O6,O6-I6)} -> 14830 | M6: {=L6/L$17} -> 0.003370974 | N6: 12 | O6: 88990 | P6: {=O6*(1+P$2/12)^(N6)} -> 92734.015 | Q6: {=P6-O6} -> 3744.0147 | S6: {=IF(AND(1>S$1-$J6,$J6-S$1<$N6),$D6,0)} -> 7416 | T6: {=IF(AND(1>T$1-$J6,$J6-T$1<$N6),$D6,0)} -> 7416 | U6: {=IF(AND(1>U$1-$J6,$J6-U$1<$N6),$D6,0)} -> 7416 | V6: {=IF(AND(1>V$1-$J6,$J6-V$1<$N6),$D6,0)} -> 0 | W6: {=IF(AND(1>W$1-$J6,$J6-W$1<$N6),$D6,0)} -> 0 | X6: {=IF(AND(1>X$1-$J6,$J6-X$1<$N6),$D6,0)} -> 0 | Y6: {=IF(AND(1>Y$1-$J6,$J6-Y$1<$N6),$D6,0)} -> 0 | Z6: {=IF(AND(1>Z$1-$J6,$J6-Z$1<$N6),$D6,0)} -> 0 | ... AQ6: {=IF(AND(1>AQ$1-$J6,$J6-AQ$1<$N6),$D6,0)} -> 0
A7: . | B7: motits | D7: {=ROUND(O7/N7,0)} -> 68333 | E7: {=D7/D$17} -> 0.15324943 | F7: -10 | G7: {=F7+F$2} -> 1 | H7: {=IF(G7<0,0,G7/N7)} -> 0.33333333 | I7: {=IF(G7<0,0,D7*G7)} -> 68333 | J7: {=N7-G7} -> 2 | K7: {=1-H7} -> 0.66666667 | L7: {=IF($G7<0,O7,O7-I7)} -> 136667 | M7: {=L7/L$17} -> 0.031065469 | N7: 3 | O7: 205000 | P7: {=O7*(1+P$2/12)^(N7)} -> 207123 | Q7: {=P7-O7} -> 2122.9986 | S7: {=IF(AND(1>S$1-$J7,$J7-S$1<$N7),$D7,0)} -> 68333 | T7: {=IF(AND(1>T$1-$J7,$J7-T$1<$N7),$D7,0)} -> 68333 | U7: {=IF(AND(1>U$1-$J7,$J7-U$1<$N7),$D7,0)} -> 68333 | V7: {=IF(AND(1>V$1-$J7,$J7-V$1<$N7),$D7,0)} -> 0 | W7: {=IF(AND(1>W$1-$J7,$J7-W$1<$N7),$D7,0)} -> 0 | X7: {=IF(AND(1>X$1-$J7,$J7-X$1<$N7),$D7,0)} -> 0 | Y7: {=IF(AND(1>Y$1-$J7,$J7-Y$1<$N7),$D7,0)} -> 0 | Z7: {=IF(AND(1>Z$1-$J7,$J7-Z$1<$N7),$D7,0)} -> 0 | ... AQ7: {=IF(AND(1>AQ$1-$J7,$J7-AQ$1<$N7),$D7,0)} -> 0
B8: permiso 1/2 | D8: {=ROUND(O8/N8,0)} -> 9763 | E8: {=D8/D$17} -> 0.021895338 | F8: -10 | G8: {=F8+F$2} -> 1 | H8: {=IF(G8<0,0,G8/N8)} -> 0.33333333 | I8: {=IF(G8<0,0,D8*G8)} -> 9763 | J8: {=N8-G8} -> 2 | K8: {=1-H8} -> 0.66666667 | L8: {=IF($G8<0,O8,O8-I8)} -> 19525 | M8: {=L8/L$17} -> 0.0044381839 | N8: 3 | O8: 29288 | P8: {=O8*(1+P$2/12)^(N8)} -> 29591.309 | Q8: {=P8-O8} -> 303.30918 | S8: {=IF(AND(1>S$1-$J8,$J8-S$1<$N8),$D8,0)} -> 9763 | T8: {=IF(AND(1>T$1-$J8,$J8-T$1<$N8),$D8,0)} -> 9763 | U8: {=IF(AND(1>U$1-$J8,$J8-U$1<$N8),$D8,0)} -> 9763 | V8: {=IF(AND(1>V$1-$J8,$J8-V$1<$N8),$D8,0)} -> 0 | W8: {=IF(AND(1>W$1-$J8,$J8-W$1<$N8),$D8,0)} -> 0 | X8: {=IF(AND(1>X$1-$J8,$J8-X$1<$N8),$D8,0)} -> 0 | Y8: {=IF(AND(1>Y$1-$J8,$J8-Y$1<$N8),$D8,0)} -> 0 | Z8: {=IF(AND(1>Z$1-$J8,$J8-Z$1<$N8),$D8,0)} -> 0 | ... AQ8: {=IF(AND(1>AQ$1-$J8,$J8-AQ$1<$N8),$D8,0)} -> 0
A9: . | B9: bandeja brownies | D9: {=ROUND(O9/N9,0)} -> 2371 | E9: {=D9/D$17} -> 0.0053174073 | F9: -2 | G9: {=F9+F$2} -> 9 | H9: {=IF(G9<0,0,G9/N9)} -> 0.75 | I9: {=IF(G9<0,0,D9*G9)} -> 21339 | J9: {=N9-G9} -> 3 | K9: {=1-H9} -> 0.25 | L9: {=IF($G9<0,O9,O9-I9)} -> 7111 | M9: {=L9/L$17} -> 0.0016163854 | N9: 12 | O9: 28450 | P9: {=O9*(1+P$2/12)^(N9)} -> 29646.957 | Q9: {=P9-O9} -> 1196.9572 | S9: {=IF(AND(1>S$1-$J9,$J9-S$1<$N9),$D9,0)} -> 2371 | T9: {=IF(AND(1>T$1-$J9,$J9-T$1<$N9),$D9,0)} -> 2371 | U9: {=IF(AND(1>U$1-$J9,$J9-U$1<$N9),$D9,0)} -> 2371 | V9: {=IF(AND(1>V$1-$J9,$J9-V$1<$N9),$D9,0)} -> 2371 | W9: {=IF(AND(1>W$1-$J9,$J9-W$1<$N9),$D9,0)} -> 0 | X9: {=IF(AND(1>X$1-$J9,$J9-X$1<$N9),$D9,0)} -> 0 | Y9: {=IF(AND(1>Y$1-$J9,$J9-Y$1<$N9),$D9,0)} -> 0 | Z9: {=IF(AND(1>Z$1-$J9,$J9-Z$1<$N9),$D9,0)} -> 0 | ... AQ9: {=IF(AND(1>AQ$1-$J9,$J9-AQ$1<$N9),$D9,0)} -> 0
B10: contribuciones 1/4 marzo | D10: {=ROUND(O10/N10,0)} -> 30973 | E10: {=D10/D$17} -> 0.069462697 | F10: -11 | G10: {=F10+F$2} -> 0 | H10: {=IF(G10<0,0,G10/N10)} -> 0 | I10: {=IF(G10<0,0,D10*G10)} -> 0 | J10: {=N10-G10} -> 3 | K10: {=1-H10} -> 1 | L10: {=IF($G10<0,O10,O10-I10)} -> 92918 | M10: {=L10/L$17} -> 0.021120982 | N10: 3 | O10: 92918 | P10: {=O10*(1+P$2/12)^(N10)} -> 93880.267 | Q10: {=P10-O10} -> 962.26723 | S10: {=IF(AND(1>S$1-$J10,$J10-S$1<$N10),$D10,0)} -> 0 | T10: {=IF(AND(1>T$1-$J10,$J10-T$1<$N10),$D10,0)} -> 30973 | U10: {=IF(AND(1>U$1-$J10,$J10-U$1<$N10),$D10,0)} -> 30973 | V10: {=IF(AND(1>V$1-$J10,$J10-V$1<$N10),$D10,0)} -> 30973 | W10: {=IF(AND(1>W$1-$J10,$J10-W$1<$N10),$D10,0)} -> 0 | X10: {=IF(AND(1>X$1-$J10,$J10-X$1<$N10),$D10,0)} -> 0 | Y10: {=IF(AND(1>Y$1-$J10,$J10-Y$1<$N10),$D10,0)} -> 0 | Z10: {=IF(AND(1>Z$1-$J10,$J10-Z$1<$N10),$D10,0)} -> 0 | ... AQ10: {=IF(AND(1>AQ$1-$J10,$J10-AQ$1<$N10),$D10,0)} -> 0
A11: . | B11: le creuset | C11: mercadopago 4 | D11: {=ROUND(O11/N11,0)} -> 8248 | E11: {=D11/D$17} -> 0.01849767 | F11: -4 | G11: {=F11+F$2} -> 7 | H11: {=IF(G11<0,0,G11/N11)} -> 0.58333333 | I11: {=IF(G11<0,0,D11*G11)} -> 57736 | J11: {=N11-G11} -> 5 | K11: {=1-H11} -> 0.41666667 | L11: {=IF($G11<0,O11,O11-I11)} -> 41234 | M11: {=L11/L$17} -> 0.0093728079 | N11: 12 | O11: 98970 | P11: {=O11*(1+P$2/12)^(N11)} -> 103133.9 | Q11: {=P11-O11} -> 4163.8963 | S11: {=IF(AND(1>S$1-$J11,$J11-S$1<$N11),$D11,0)} -> 8248 | T11: {=IF(AND(1>T$1-$J11,$J11-T$1<$N11),$D11,0)} -> 8248 | U11: {=IF(AND(1>U$1-$J11,$J11-U$1<$N11),$D11,0)} -> 8248 | V11: {=IF(AND(1>V$1-$J11,$J11-V$1<$N11),$D11,0)} -> 8248 | W11: {=IF(AND(1>W$1-$J11,$J11-W$1<$N11),$D11,0)} -> 8248 | X11: {=IF(AND(1>X$1-$J11,$J11-X$1<$N11),$D11,0)} -> 8248 | Y11: {=IF(AND(1>Y$1-$J11,$J11-Y$1<$N11),$D11,0)} -> 0 | Z11: {=IF(AND(1>Z$1-$J11,$J11-Z$1<$N11),$D11,0)} -> 0 | ... AQ11: {=IF(AND(1>AQ$1-$J11,$J11-AQ$1<$N11),$D11,0)} -> 0
B12: mercadolibe shit | D12: {=ROUND(O12/N12,0)} -> 12398 | E12: {=D12/D$17} -> 0.027804815 | F12: -11 | G12: {=F12+F$2} -> 0 | H12: {=IF(G12<0,0,G12/N12)} -> 0 | I12: {=IF(G12<0,0,D12*G12)} -> 0 | J12: {=N12-G12} -> 6 | K12: {=1-H12} -> 1 | L12: {=IF($G12<0,O12,O12-I12)} -> 74387 | M12: {=L12/L$17} -> 0.016908742 | N12: 6 | O12: 74387 | P12: {=O12*(1+P$2/12)^(N12)} -> 75935.695 | Q12: {=P12-O12} -> 1548.6949 | S12: {=IF(AND(1>S$1-$J12,$J12-S$1<$N12),$D12,0)} -> 0 | T12: {=IF(AND(1>T$1-$J12,$J12-T$1<$N12),$D12,0)} -> 12398 | U12: {=IF(AND(1>U$1-$J12,$J12-U$1<$N12),$D12,0)} -> 12398 | V12: {=IF(AND(1>V$1-$J12,$J12-V$1<$N12),$D12,0)} -> 12398 | W12: {=IF(AND(1>W$1-$J12,$J12-W$1<$N12),$D12,0)} -> 12398 | X12: {=IF(AND(1>X$1-$J12,$J12-X$1<$N12),$D12,0)} -> 12398 | Y12: {=IF(AND(1>Y$1-$J12,$J12-Y$1<$N12),$D12,0)} -> 12398 | Z12: {=IF(AND(1>Z$1-$J12,$J12-Z$1<$N12),$D12,0)} -> 0 | ... AQ12: {=IF(AND(1>AQ$1-$J12,$J12-AQ$1<$N12),$D12,0)} -> 0
A13: . | B13: macbook air | D13: 135416 | E13: {=D13/D$17} -> 0.3036955 | F13: -6 | G13: {=F13+F$2} -> 5 | H13: {=IF(G13<0,0,G13/N13)} -> 0.41666667 | I13: {=IF(G13<0,0,D13*G13)} -> 677080 | J13: {=N13-G13} -> 7 | K13: {=1-H13} -> 0.58333333 | L13: {=IF($G13<0,O13,O13-I13)} -> 947912 | M13: {=L13/L$17} -> 0.21546775 | N13: 12 | O13: {=N13*D13} -> 1624992 | P13: {=O13*(1+P$2/12)^(N13)} -> 1693359.2 | Q13: {=P13-O13} -> 68367.164 | S13: {=IF(AND(1>S$1-$J13,$J13-S$1<$N13),$D13,0)} -> 135416 | T13: {=IF(AND(1>T$1-$J13,$J13-T$1<$N13),$D13,0)} -> 135416 | U13: {=IF(AND(1>U$1-$J13,$J13-U$1<$N13),$D13,0)} -> 135416 | V13: {=IF(AND(1>V$1-$J13,$J13-V$1<$N13),$D13,0)} -> 135416 | W13: {=IF(AND(1>W$1-$J13,$J13-W$1<$N13),$D13,0)} -> 135416 | X13: {=IF(AND(1>X$1-$J13,$J13-X$1<$N13),$D13,0)} -> 135416 | Y13: {=IF(AND(1>Y$1-$J13,$J13-Y$1<$N13),$D13,0)} -> 135416 | Z13: {=IF(AND(1>Z$1-$J13,$J13-Z$1<$N13),$D13,0)} -> 135416 | ... AQ13: {=IF(AND(1>AQ$1-$J13,$J13-AQ$1<$N13),$D13,0)} -> 0
A14: . | B14: impresora | C14: sp digital | D14: {=ROUND(O14/N14,0)} -> 5538 | E14: {=D14/D$17} -> 0.012419992 | F14: -1 | G14: {=F14+F$2} -> 10 | H14: {=IF(G14<0,0,G14/N14)} -> 0.41666667 | I14: {=IF(G14<0,0,D14*G14)} -> 55380 | J14: {=N14-G14} -> 14 | K14: {=1-H14} -> 0.58333333 | L14: {=IF($G14<0,O14,O14-I14)} -> 77521 | M14: {=L14/L$17} -> 0.017621124 | N14: 24 | O14: 132901 | P14: {=O14*(1+P$2/12)^(N14)} -> 144319.15 | Q14: {=P14-O14} -> 11418.149 | S14: {=IF(AND(1>S$1-$J14,$J14-S$1<$N14),$D14,0)} -> 5538 | T14: {=IF(AND(1>T$1-$J14,$J14-T$1<$N14),$D14,0)} -> 5538 | U14: {=IF(AND(1>U$1-$J14,$J14-U$1<$N14),$D14,0)} -> 5538 | V14: {=IF(AND(1>V$1-$J14,$J14-V$1<$N14),$D14,0)} -> 5538 | W14: {=IF(AND(1>W$1-$J14,$J14-W$1<$N14),$D14,0)} -> 5538 | X14: {=IF(AND(1>X$1-$J14,$J14-X$1<$N14),$D14,0)} -> 5538 | Y14: {=IF(AND(1>Y$1-$J14,$J14-Y$1<$N14),$D14,0)} -> 5538 | Z14: {=IF(AND(1>Z$1-$J14,$J14-Z$1<$N14),$D14,0)} -> 5538 | ... AQ14: {=IF(AND(1>AQ$1-$J14,$J14-AQ$1<$N14),$D14,0)} -> 0
A15: . | B15: ipad | D15: {=ROUND(O15/N15,0)} -> 18333 | E15: {=D15/D$17} -> 0.041115153 | F15: -2 | G15: {=F15+F$2} -> 9 | H15: {=IF(G15<0,0,G15/N15)} -> 0.375 | I15: {=IF(G15<0,0,D15*G15)} -> 164997 | J15: {=N15-G15} -> 15 | K15: {=1-H15} -> 0.625 | L15: {=IF($G15<0,O15,O15-I15)} -> 274993 | M15: {=L15/L$17} -> 0.062508041 | N15: 24 | O15: 439990 | P15: {=O15*(1+P$2/12)^(N15)} -> 477791.61 | Q15: {=P15-O15} -> 37801.607 | S15: {=IF(AND(1>S$1-$J15,$J15-S$1<$N15),$D15,0)} -> 18333 | T15: {=IF(AND(1>T$1-$J15,$J15-T$1<$N15),$D15,0)} -> 18333 | U15: {=IF(AND(1>U$1-$J15,$J15-U$1<$N15),$D15,0)} -> 18333 | V15: {=IF(AND(1>V$1-$J15,$J15-V$1<$N15),$D15,0)} -> 18333 | W15: {=IF(AND(1>W$1-$J15,$J15-W$1<$N15),$D15,0)} -> 18333 | X15: {=IF(AND(1>X$1-$J15,$J15-X$1<$N15),$D15,0)} -> 18333 | Y15: {=IF(AND(1>Y$1-$J15,$J15-Y$1<$N15),$D15,0)} -> 18333 | Z15: {=IF(AND(1>Z$1-$J15,$J15-Z$1<$N15),$D15,0)} -> 18333 | ... AQ15: {=IF(AND(1>AQ$1-$J15,$J15-AQ$1<$N15),$D15,0)} -> 0
A16: . | B16: lo arcaya | D16: {=ROUND(O16/N16,0)} -> 139583 | E16: {=D16/D$17} -> 0.31304077 | F16: -6 | G16: {=F16+F$2} -> 5 | H16: {=IF(G16<0,0,G16/N16)} -> 0.20833333 | I16: {=IF(G16<0,0,D16*G16)} -> 697915 | J16: {=N16-G16} -> 19 | K16: {=1-H16} -> 0.79166667 | L16: {=IF($G16<0,O16,O16-I16)} -> 2652085 | M16: {=L16/L$17} -> 0.60283948 | N16: 24 | O16: 3350000 | P16: {=O16*(1+P$2/12)^(N16)} -> 3637814.2 | Q16: {=P16-O16} -> 287814.23 | S16: {=IF(AND(1>S$1-$J16,$J16-S$1<$N16),$D16,0)} -> 139583 | T16: {=IF(AND(1>T$1-$J16,$J16-T$1<$N16),$D16,0)} -> 139583 | U16: {=IF(AND(1>U$1-$J16,$J16-U$1<$N16),$D16,0)} -> 139583 | V16: {=IF(AND(1>V$1-$J16,$J16-V$1<$N16),$D16,0)} -> 139583 | W16: {=IF(AND(1>W$1-$J16,$J16-W$1<$N16),$D16,0)} -> 139583 | X16: {=IF(AND(1>X$1-$J16,$J16-X$1<$N16),$D16,0)} -> 139583 | Y16: {=IF(AND(1>Y$1-$J16,$J16-Y$1<$N16),$D16,0)} -> 139583 | Z16: {=IF(AND(1>Z$1-$J16,$J16-Z$1<$N16),$D16,0)} -> 139583 | ... AQ16: {=IF(AND(1>AQ$1-$J16,$J16-AQ$1<$N16),$D16,0)} -> 0
D17: {=S$17} -> 445894 | E17: {=D$17/(L$17+D$17)} -> 0.092027683 | I17: {=SUM(I3:I16)} -> 2069964 | L17: {=SUM(L3:L16)} -> 4399322 | M17: {=L$17/O$17} -> 0.68003208 | O17: {=SUM(O3:O16)} -> 6469286 | Q17: {=SUM(Q3:Q16)} -> 428366.55 | S17: {=SUM(S3:S16)} -> 445894 | T17: {=SUM(T3:T16)} -> 489265 | U17: {=SUM(U3:U16)} -> 447617 | V17: {=SUM(V3:V16)} -> 352860 | W17: {=SUM(W3:W16)} -> 319516 | X17: {=SUM(X3:X16)} -> 319516 | Y17: {=SUM(Y3:Y16)} -> 311268 | Z17: {=SUM(Z3:Z16)} -> 298870 | ... AQ17: {=SUM(AQ3:AQ16)} -> 0
T18: {=T17-S17} -> 43371 | U18: {=U17-T17} -> -41648 | V18: {=V17-U17} -> -94757 | W18: {=W17-V17} -> -33344 | X18: {=X17-W17} -> 0 | Y18: {=Y17-X17} -> -8248 | Z18: {=Z17-Y17} -> -12398 | AA18: {=AA17-Z17} -> -135416 | ... AQ18: {=AQ17-AP17} -> 0
S19: {=L$17} -> 4399322 | T19: {=L$17-T$17} -> 3910057 | U19: {=T$19-U$17} -> 3462440 | V19: {=U$19-V$17} -> 3109580 | W19: {=V$19-W$17} -> 2790064 | X19: {=W$19-X$17} -> 2470548 | Y19: {=X$19-Y$17} -> 2159280 | Z19: {=Y$19-Z$17} -> 1860410 | AA19: {=Z$19-AA$17} -> 1696956 | AB19: {=AA$19-AB$17} -> 1533502 | ... AQ19: {=AP$19-AQ$17} -> -16

Sheet flujos - Table 2
B2: cupo utilizado | C2: {=H6+H7} -> 9857935 | D2: 100
G3: worldmember | H3: 5857935
A4: gastado este mes | B4: cuota mes | C4: {='flujos - Table 3'!S$17} -> 445894 | G4: lider | H4: {=0} -> 0
B5: gasto del mes | C5: {=C2-'flujos - Table 3'!L$17} -> 5458613 | E5: {=C5-C9} -> 4636348
B6: total mes pesos | D6: {=SUM(C4:C5)} -> 5904507 | G6: {=C2-H6} -> 4000000 | H6: {=SUM(H3)} -> 5857935
B7: dolares | C7: {=D2*'variables - Table 1'!B13} -> 88694 | G7: offset | H7: 4000000
B8: total mes | D8: {=SUM(C7,C5)} -> 5547307
B9: dividendo | C9: {='depto - dividendos'!J31} -> 822265
B10: - dividendo | D10: {=D8-C9} -> 4725042
B12: a pagar | C12: {=C4+D8} -> 5993201 | H12: 2336694
B13: - dividendo | C13: {=C12-C9} -> 5170936 | H13: {=265473*1} -> 265473
H14: {=SUM(H12:H13)} -> 2602167
A15: retirar de fintual | B15: c. corriente | C15: {=$C$12-'net worth - cash'!$B$2} -> 5712457
B16: + sueldo | C16: {=$C$12-'presupuesto - Ingreso líquido'!$B$32} -> 2832547
A18: 45971 | B18: a pagar | C18: {=SUM(E18,F19)+C12*0} -> 5721066 | E18: {=C12*0+5570527} -> 5570527
B19: retirar pa pagar | C19: {=C18-'net worth - cash'!B2} -> 5440322 | E19: 166.4 | F19: {=ROUND(('variables - Table 1'!B13*1.02)*E19,0)} -> 150539

Sheet flujos - Table 3-3
C1: 2023 | E1: 2024
A2: 45292 | B2: metrogas | E2: 40683 | F2: 24.9
B3: enel
A4: 44958 | B4: metrogas | C4: 20945 | D4: 12.2
B5: enel
A6: 44986 | B6: metrogas | E6: 42088 | F6: 26
B7: enel
A8: 45017 | B8: metrogas | C8: 16525 | D8: 9.4 | E8: 29340 | F8: 17.6
B9: enel
A10: 45047 | B10: metrogas | E10: 50304 | F10: 32.7
B11: enel
A12: 45078 | B12: metrogas | F12: 6
B13: enel
A14: 45108 | B14: metrogas | C14: 18854 | D14: 10.9
B15: enel
A16: 45139 | B16: metrogas | F16: 30
B17: enel
A18: 45170 | B18: metrogas | C18: 34363 | D18: 20.9
B19: enel
A20: 45200 | B20: metrogas | C20: 44793 | D20: 28.2 | F20: 24
B21: enel
A22: 45231 | B22: metrogas
B23: enel
A24: 45261 | B24: metrogas
B25: enel
C32: LONDON COFFEE A | D32: -5460
A33: 17/12/2025 | C33: LONDON COFFEE ALCANTARA | D33: -8260
C34: LONDON COFFEE ALCANTARA | D34: -5460
A35: 16/12/2025 | C35: LONDON COFFEE ALCANTARA | D35: -5460
C36: LONDON COFFEE ALCANTARA | D36: -5663
C37: LONDON COFFEE ALCANTARA | D37: -5460
A38: 15/12/2025 | C38: GOOGLE PLAY YOUTUBE CL | D38: -11000
C39: CARMINE CC | D39: -83020
C40: LONDON COFFEE ALCANTARA | D40: -4680

Sheet flujos - Table 3-3-1
A3: 0-5 | B3: 1933 | D3: {=B3*5} -> 9665 | E3: {=D2-$D$12} -> -50304 | F3: {=ROUND(E3/B3,1)} -> -26 | G3: {=-F3} -> 26
A4: 5-10 | B4: 1557 | D4: {=D3+5*B4} -> 17450 | E4: {=D3-$D$12} -> -40639 | F4: {=ROUND(E4/B4,1)} -> -26.1 | G4: {=5-F4} -> 31.1
A5: 10-25 | B5: 1556 | D5: {=B5*15+D4} -> 40790 | E5: {=D4-$D$12} -> -32854 | F5: {=ROUND(E5/B5,1)} -> -21.1 | G5: {=10-F5} -> 31.1
A6: 25-40 | B6: 1242 | D6: {=B6*15+D5} -> 59420 | E6: {=D5-$D$12} -> -9514 | F6: {=ROUND(E6/B6,1)} -> -7.7 | G6: {=25-F6} -> 32.7
A7: 40-60 | B7: 805 | D7: {=B7*20+D6} -> 75520 | E7: {=D6-$D$12} -> 9116 | F7: {=ROUND(E7/B7,1)} -> 11.3 | G7: {=40-F7} -> 28.7
E8: {=D7-$D$12} -> 25216 | F8: {=ROUND(E8/B8,1)} | G8: {=10-F8}
D12: 50304
C19: lider | D19: 3000 | E19: 486 | F19: {=D19/E19} -> 6.1728395
D20: 5000 | E20: 810 | F20: {=D20/E20} -> 6.1728395
D21: 90000 | E21: 14575 | F21: {=D21/E21} -> 6.1749571
D22: 200000 | E22: 32388 | F22: {=D22/E22} -> 6.1751266
D23: 20000 | E23: 3239 | F23: {=D23/E23} -> 6.1747453
D24: 50000 | E24: 8097 | F24: {=D24/E24} -> 6.1751266
D25: 40000 | E25: 6478 | F25: {=D25/E25} -> 6.1747453
D26: 100000 | E26: 16194 | F26: {=D26/E26} -> 6.1751266
D27: 60000 | E27: 9717 | F27: {=D27/E27} -> 6.1747453
D28: 150000 | E28: 24291 | F28: {=D28/E28} -> 6.1751266
D29: 30000 | E29: 4859 | F29: {=D29/E29} -> 6.1741099
D30: 70000 | E30: 11336 | F30: {=D30/E30} -> 6.1750176
C33: paris | D33: 50000 | E33: 7786 | F33: {=D33/E33} -> 6.4217827
D34: 100000 | E34: 15571 | F34: {=D34/E34} -> 6.4221951
C35: cenco | D35: 200000 | E35: 31142 | F35: {=D35/E35} -> 6.4221951
D36: 150000 | E36: 23357 | F36: {=D36/E36} -> 6.4220576
A37: 86740 | D37: 100000 | E37: 15571 | F37: {=D37/E37} -> 6.4221951
A38: 14990
A39: 64310 | C39: unimarc | D39: 10000 | E39: 1213 | F39: {=D39/E39} -> 8.2440231
A40: 91904 | D40: 100000 | E40: 12127 | F40: {=D40/E40} -> 8.2460625
A41: 106930 | D41: 200000 | E41: 24253 | F41: {=D41/E41} -> 8.2464025
A42: 50326
C43: cineplis | D43: 5000 | E43: 611 | F43: {=D43/E43} -> 8.1833061
D44: 400000 | E44: 58624 | F44: {=D44/E44} -> 6.8231441
D45: 734253 | E45: 83932 | F45: {=D45/E45} -> 8.748189
C48: latam | D48: {='variables - Table 1'!$B$13*E48} -> 886.94 | E48: 1
C49: 1 milla x dolar | D49: {='variables - Table 1'!$B$13*E49} -> 886940 | E49: 1000
D50: {='variables - Table 1'!$B$13*E50} -> 718421.4 | E50: 810 | F50: {=D20} -> 5000 | G50: {=F50/D50} -> 0.0069597036
D51: {='variables - Table 1'!$B$13*E51} -> 1075858.2 | E51: 1213 | F51: {=D39} -> 10000 | G51: {=F51/D51} -> 0.009294905
D52: {='variables - Table 1'!$B$13*E52} -> 13810543 | E52: {=E37} -> 15571 | F52: {=D37} -> 100000 | G52: {=F52/D52} -> 0.007240845

Sheet flujos - Drawings

Sheet anual - Table 1-1
B3: Ingreso | D3: Depositado | E3: USD depositado | H3: Gasto | J3: % crec | K3: ∆ net worth | L3: ∆ inversiones | M3: ∆ retiro | N3: ∆ cripto | O3: ∆ pasivo | P3: acum | Q3: USD net worth | R3: Net worth | S3: Assets | U3: Inversiones | W3: Cripto | Y3: Retiro | AA3: Líquido | AC3: liabilities
A4: 2017 | B4: {=SUM('flujos - Gasto mensual'!C3:C9)} -> 10241263 | C4: {=SUM('flujos - Gasto mensual'!B3:B9)} -> 16105 | D4: {=SUM('net worth - resumen | depósitos'!R3:R9)} -> 8704479 | E4: {=D4/'variables - Table 1-1'!$B8} -> 14167.446 | F4: {=D4/B4*100%} -> 0.84994195 | G4: {=F4} -> 0.84994195 | H4: {=B4-D4} -> 1536784 | I4: {=H4/'variables - Table 1-1'!$B8} -> 2501.276 | J4: {=R4/'net worth - Table 1-1'!F2-1} -> 1.5465687 | K4: {=R4-'net worth - Table 1-1'!F2} -> 6576929.8 | L4: {=SUM('net worth - Table 1-3'!$I3:$I9)} -> 0 | M4: {=SUM('net worth - Table 1-3'!$AO3:$AO9)} -> 18245 | N4: {=SUM('net worth - Table 1-2'!E2:E8)} -> 1055049.6 | O4: {=SUM(L4:N4)} -> 1073294.6 | P4: {=SUM(O$4:O4)} -> 1073294.6 | Q4: {='net worth - Table 1-1'!E8} -> 17626.179 | R4: {=SUM(S4,U4,W4,Y4,AA4)} -> 10829524 | U4: {='net worth - Table 1-1'!H8} -> 1894508 | V4: {=U4} -> 1894508 | W4: {='net worth - Table 1-1'!I8} -> 3085682.4 | X4: {=W4} -> 3085682.4 | Y4: {='net worth - Table 1-1'!J8} -> 995738 | Z4: {=Y4} -> 995738 | AA4: {='net worth - Table 1-1'!K8} -> 4853596 | AB4: {=AA4-'net worth - Table 1-1'!K2} -> 1727089
A5: 2018 | B5: {=SUM('flujos - Gasto mensual'!C$10:C21)} -> 22378269 | C5: {=SUM('flujos - Gasto mensual'!B10:B21)} -> 34806 | D5: {=SUM('net worth - resumen | depósitos'!R10:R21)} -> 12524119 | E5: {=D5/'variables - Table 1-1'!$B20} -> 18059.292 | F5: {=D5/B5*100%} -> 0.55965539 | G5: {=_xlfn.IFERROR(SUM(D$4:D5)/SUM(B$4:B5),0)} -> 0.65079407 | H5: {=B5-D5} -> 9854150.2 | I5: {=H5/'variables - Table 1-1'!$B20} -> 14209.301 | J5: {=R5/R4-1} -> 0.83246583 | K5: {=R5-R4} -> 9015209.1 | L5: {=SUM('net worth - Table 1-3'!$I10:$I21)} -> -151096 | M5: {=SUM('net worth - Table 1-3'!$AO10:$AO21)} -> -138147 | N5: {=SUM('net worth - Table 1-2'!E9:E20)} -> -2886593.5 | O5: {=SUM(L5:N5)} -> -3175836.5 | P5: {=SUM(O$4:O5)} -> -2102542 | Q5: {='net worth - Table 1-1'!E20} -> 28615.333 | R5: {=SUM(S5,U5,W5,Y5,AA5)} -> 19844733 | U5: {='net worth - Table 1-1'!H20} -> 4148904 | V5: {=U5-U4} -> 2254396 | W5: {='net worth - Table 1-1'!I20} -> 799676.48 | X5: {=W5-W4} -> -2286005.9 | Y5: {='net worth - Table 1-1'!J20} -> 4885955 | Z5: {=Y5-Y4} -> 3890217 | AA5: {='net worth - Table 1-1'!K20} -> 10010198 | AB5: {=AA5-AA4} -> 5156602
A6: 2019 | B6: {=SUM('flujos - Gasto mensual'!C$22:C33)} -> 30672716 | C6: {=SUM('flujos - Gasto mensual'!B22:B33)} -> 43339 | D6: {=SUM('net worth - resumen | depósitos'!R22:R33)} -> 16744375 | E6: {=D6/'variables - Table 1-1'!$B32} -> 22868.581 | F6: {=D6/B6*100%} -> 0.54590454 | G6: {=_xlfn.IFERROR(SUM(D$4:D6)/SUM(B$4:B6),0)} -> 0.59996246 | H6: {=B6-D6} -> 13928341 | I6: {=H6/'variables - Table 1-1'!$B32} -> 19022.591 | J6: {=R6/R5-1} -> 1.1572246 | K6: {=R6-R5} -> 22964813 | L6: {=SUM('net worth - Table 1-3'!$I$22:$I33)} -> 2962156 | M6: {=SUM('net worth - Table 1-3'!$AO$22:$AO33)} -> 1854755 | N6: {=SUM('net worth - Table 1-2'!E21:E32)} -> -25196.798 | O6: {=SUM(L6:N6)} -> 4791714.2 | P6: {=SUM(O$4:O6)} -> 2689172.2 | Q6: {='net worth - Table 1-1'!E32} -> 58467.012 | R6: {=SUM(S6,U6,W6,Y6,AA6)} -> 42809546 | U6: {='net worth - Table 1-1'!H32} -> 13411060 | V6: {=U6-U5} -> 9262156 | W6: {='net worth - Table 1-1'!I32} -> 1135089.4 | X6: {=W6-W5} -> 335412.93 | Y6: {='net worth - Table 1-1'!J32} -> 15116086 | Z6: {=Y6-Y5} -> 10230131 | AA6: {='net worth - Table 1-1'!K32} -> 13147311 | AB6: {=AA6-AA5} -> 3137113
A7: 2020 | B7: {=SUM('flujos - Gasto mensual'!C$34:C45)} -> 26524149 | C7: {=SUM('flujos - Gasto mensual'!B34:B45)} -> 33090 | D7: {=SUM('net worth - resumen | depósitos'!R34:R45)} -> 4551200 | E7: {=D7/'variables - Table 1-1'!$B44} -> 6401.1252 | F7: {=D7/B7*100%} -> 0.17158703 | G7: {=_xlfn.IFERROR(SUM(D$4:D7)/SUM(B$4:B7),0)} -> 0.47345668 | H7: {=B7-D7} -> 21972949 | I7: {=H7/'variables - Table 1-1'!$B44} -> 30904.288 | J7: {=R7/R6-1} -> 0.35446147 | K7: {=R7-R6} -> 15174335 | L7: {=SUM('net worth - Table 1-3'!$I$34:$I45)} -> 3079726 | M7: {=SUM('net worth - Table 1-3'!$AO$34:$AO45)} -> 2778376 | N7: {=SUM('net worth - Table 1-2'!E33:E44)} -> 4075278.6 | O7: {=SUM(L7:N7)} -> 9933380.6 | P7: {=SUM(O$4:O7)} -> 12622553 | Q7: {='net worth - Table 1-1'!E44} -> 81552.575 | R7: {=SUM(S7,U7,W7,Y7,AA7)} -> 57983881 | U7: {='net worth - Table 1-1'!H44} -> 13490786 | V7: {=U7-U6} -> 79726 | W7: {='net worth - Table 1-1'!I44} -> 5210368 | X7: {=W7-W6} -> 4075278.6 | Y7: {='net worth - Table 1-1'!J44} -> 24996909 | Z7: {=Y7-Y6} -> 9880823 | AA7: {='net worth - Table 1-1'!K44} -> 14285818 | AB7: {=AA7-AA6} -> 1138507
A8: 2021 | B8: {=SUM('flujos - Gasto mensual'!C$46:C57)} -> 26312267 | C8: {=SUM('flujos - Gasto mensual'!B46:B57)} -> 35888 | D8: {=SUM('net worth - resumen | depósitos'!R46:R57)} -> 1698600 | E8: {=D8/'variables - Table 1-1'!$B56} -> 1994.8326 | F8: {=D8/B8*100%} -> 0.064555441 | G8: {=_xlfn.IFERROR(SUM(D$4:D8)/SUM(B$4:B8),0)} -> 0.38080842 | H8: {=B8-D8} -> 24613667 | I8: {=H8/'variables - Table 1-1'!$B56} -> 28906.244 | J8: {=R8/R7-1} -> 0.39980653 | K8: {=R8-R7} -> 23182334 | L8: {=SUM('net worth - Table 1-3'!$I$46:$I57)} -> 4801646 | M8: {=SUM('net worth - Table 1-3'!$AO$46:$AO57)} -> 7270365 | N8: {=SUM('net worth - Table 1-2'!E45:E56)} -> 8219768 | O8: {=SUM(L8:N8)} -> 20291779 | P8: {=SUM(O$4:O8)} -> 32914332 | Q8: {='net worth - Table 1-1'!E56} -> 95321.45 | R8: {=SUM(S8,U8,W8,Y8,AA8)} -> 81166215 | U8: {='net worth - Table 1-1'!H56} -> 20792432 | V8: {=U8-U7} -> 7301646 | W8: {='net worth - Table 1-1'!I56} -> 8730136 | X8: {=W8-W7} -> 3519768 | Y8: {='net worth - Table 1-1'!J56} -> 32643647 | Z8: {=Y8-Y7} -> 7646738 | AA8: {='net worth - Table 1-1'!K56} -> 19000000 | AB8: {=AA8-AA7} -> 4714182
A9: 2022 | B9: {=SUM('flujos - Gasto mensual'!C$58:C69)} -> 14566272 | C9: {=SUM('flujos - Gasto mensual'!B58:B69)} -> 15967 | D9: {=SUM('net worth - resumen | depósitos'!R58:R69)} -> -5217506 | E9: {=D9/'variables - Table 1-1'!$B68} -> -6095.2173 | F9: {=D9/B9*100%} -> -0.35819089 | G9: {=_xlfn.IFERROR(SUM(D$4:D9)/SUM(B$4:B9),0)} -> 0.29844513 | H9: {=B9-D9} -> 19783778 | I9: {=H9/'variables - Table 1-1'!$B68} -> 23111.891 | J9: {=R9/R8-1} -> -0.28892875 | K9: {=R9-R8} -> -23451253 | L9: {=SUM('net worth - Table 1-3'!$I$58:$I69)} -> -5987315 | M9: {=SUM('net worth - Table 1-3'!$AO$58:$AO69)} -> -6449282 | N9: {=SUM('net worth - Table 1-2'!E57:E68)} -> -5828659 | O9: {=SUM(L9:N9)} -> -18265256 | P9: {=SUM(O$4:O9)} -> 14649076 | Q9: {='net worth - Table 1-1'!E68} -> 67424.021 | R9: {=SUM(S9,U9,W9,Y9,AA9)} -> 57714962 | U9: {='net worth - Table 1-1'!H68} -> 18905117 | V9: {=U9-U8} -> -1887315 | W9: {='net worth - Table 1-1'!I68} -> 2901477 | X9: {=W9-W8} -> -5828659 | Y9: {='net worth - Table 1-1'!J68} -> 28908368 | Z9: {=Y9-Y8} -> -3735279 | AA9: {='net worth - Table 1-1'!K68} -> 7000000 | AB9: {=AA9-AA8} -> -12000000
A10: 2023 | B10: {=SUM('flujos - Gasto mensual'!C$70:C81)} -> 45635233 | C10: {=SUM('flujos - Gasto mensual'!B70:B81)} -> 54415 | D10: {=SUM('net worth - resumen | depósitos'!R70:R81)} -> 10354988 | E10: {=D10/'variables - Table 1-1'!$B80} -> 11705.313 | F10: {=D10/B10*100%} -> 0.22690775 | G10: {=_xlfn.IFERROR(SUM(D$4:D10)/SUM(B$4:B10),0)} -> 0.27993085 | H10: {=B10-D10} -> 35280245 | I10: {=H10/'variables - Table 1-1'!$B80} -> 39880.906 | J10: {=R10/R9-1} -> 0.53404918 | K10: {=R10-R9} -> 30822628 | L10: {=SUM('net worth - Table 1-3'!I$70:I81)} -> 6518061.2 | M10: {=SUM('net worth - Table 1-3'!$AO$70:$AO81)} -> 10330004 | N10: {=SUM('net worth - Table 1-2'!E69:E80)} -> 3034137 | O10: {=SUM(L10:N10)} -> 19882202 | P10: {=SUM(O$4:O10)} -> 34531278 | Q10: {='net worth - Table 1-1'!E80} -> 100083.19 | R10: {=SUM(S10,U10,W10,Y10,AA10)} -> 88537590 | S10: 0 | T10: {=S10-S9} -> 0 | U10: {='net worth - Table 1-1'!H80} -> 25673178 | V10: {=U10-U9} -> 6768061.2 | W10: {='net worth - Table 1-1'!I80} -> 5935614 | X10: {=W10-W9} -> 3034137 | Y10: {='net worth - Table 1-1'!J80} -> 46828798 | Z10: {=Y10-Y9} -> 17920430 | AA10: {='net worth - Table 1-1'!K80} -> 10100000 | AB10: {=AA10-AA9} -> 3100000
A11: 2024 | B11: {=SUM('flujos - Gasto mensual'!C$82:C93)} -> 45817617 | C11: {=SUM('flujos - Gasto mensual'!B82:B93)} -> 48240 | D11: {=SUM('net worth - resumen | depósitos'!R82:R93)} -> 102353083 | E11: {=D11/'variables - Table 1'!$B$5} -> 106065.37 | F11: {=D11/B11*100%} -> 2.2339242 | G11: {=_xlfn.IFERROR(SUM(D$4:D11)/SUM(B$4:B11),0)} -> 0.68293878 | H11: {=B11-D11} -> -56535466 | I11: {=H11/'variables - Table 1'!$B$5} -> -58585.975 | J11: {=R11/R10-1} -> 1.4342221 | K11: {=R11-R10} -> 1.2698257e+08 | L11: {=SUM('net worth - Table 1-3'!I$82:I93)} -> 8397843.8 | M11: {=SUM('net worth - Table 1-3'!$AO$82:$AO93)} -> 14027908 | N11: {=SUM('net worth - Table 1-2'!E81:E92)} -> 5519852 | O11: {=SUM(L11:N11)} -> 27945604 | P11: {=SUM(O$4:O11)} -> 62476882 | Q11: {='net worth - Table 1-1'!E92} -> 216962.96 | R11: {=SUM(S11,U11,W11,Y11,AA11)} -> 215520158 | S11: {='net worth - Table 1-1'!G92} -> 89886057 | T11: {=S11-S10} -> 89886057 | U11: {='net worth - Table 1-1'!H92} -> 31621022 | V11: {=U11-U10} -> 5947843.8 | W11: {='net worth - Table 1-1'!I92} -> 10855466 | X11: {=W11-W10} -> 4919852 | Y11: {='net worth - Table 1-1'!J92} -> 68882160 | Z11: {=Y11-Y10} -> 22053362 | AA11: {='net worth - Table 1-1'!K92} -> 14275453 | AB11: {=AA11-AA10} -> 4175453 | AC11: {='depto - dividendos'!M14} -> 117412648 | AD11: {=-(AC11-AC10)} -> -117412648
A12: 2025 | B12: {=SUM('flujos - Gasto mensual'!C$94:C105)} -> 47443770 | C12: {=SUM('flujos - Gasto mensual'!B94:B105)} -> 50262 | D12: {=SUM('net worth - resumen | depósitos'!R94:R105)} -> 26020478 | E12: {=D12/'variables - Table 1'!$B$5} -> 26964.226 | F12: {=D12/B12*100%} -> 0.54844879 | G12: {=_xlfn.IFERROR(SUM(D$4:D12)/SUM(B$4:B12),0)} -> 0.65927071 | H12: {=B12-D12} -> 21423292 | I12: {=H12/'variables - Table 1'!$B$5} -> 22200.302 | J12: {=R12/R11-1} -> 0.0035974732 | K12: {=R12-R11} -> 775328 | L12: {=SUM('net worth - Table 1-3'!I$94:I105)} -> -327691 | M12: {=SUM('net worth - Table 1-3'!$AO$94:$AO105)} -> 9553411 | N12: {=SUM('net worth - Table 1-2'!E93:E104)} -> -2343219 | O12: {=SUM(L12:N12)} -> 6882501 | P12: {=SUM(O$4:O12)} -> 69359383 | Q12: {='net worth - Table 1-1'!E104} -> 240344.34 | R12: {=SUM(S12,U12,W12,Y12,AA12)} -> 216295486 | S12: {='net worth - Table 1-1'!G104} -> 122600540 | T12: {=S12-S11} -> 32714483 | U12: {='net worth - Table 1-1'!H104} -> 9693331 | V12: {=U12-U11} -> -21927691 | W12: {='net worth - Table 1-1'!I104} -> 1922666 | X12: {=W12-W11} -> -8932800 | Y12: {='net worth - Table 1-1'!J104} -> 83724577 | Z12: {=Y12-Y11} -> 14842417 | AA12: {='net worth - Table 1-1'!K104} -> -1645628 | AB12: {=AA12-AA11} -> -15921081 | AC12: {='net worth - Table 1-1'!L104} -> 98707435 | AD12: {=-(AC12-AC11)} -> 18705213
A13: 2026 | B13: {=SUM('flujos - Gasto mensual'!C$106:C117)} -> 7955560 | C13: {=SUM('flujos - Gasto mensual'!B106:B117)} -> 9018 | D13: {=SUM('net worth - resumen | depósitos'!R106:R114)} -> 42168470 | E13: {=D13/'variables - Table 1'!$B$5} -> 43697.896 | F13: {=D13/B13*100%} -> 5.300503 | G13: {=_xlfn.IFERROR(SUM(D$4:D13)/SUM(B$4:B13),0)} -> 0.79230615 | H13: {=B13-D13} -> -34212910 | I13: {=H13/'variables - Table 1'!$B$5} -> -35453.793 | J13: {=R13/R12-1} -> 0.24212023 | K13: {=R13-R12} -> 52369512 | L13: {=SUM('net worth - Table 1-3'!I$106:I114)} -> 1354140 | M13: {=SUM('net worth - Table 1-3'!$AO$106:$AO114)} -> 10442965 | N13: {=SUM('net worth - Table 1-2'!E105:E113)} -> -229209 | O13: {=SUM(L13:N13)} -> 11567896 | P13: {=SUM(O$4:O13)} -> 80927279 | Q13: {='net worth - net worth'!E$18} -> 302912.26 | R13: {=SUM(S13,U13,W13,Y13,AA13)} -> 268664998 | S13: {='net worth - net worth'!$B$13} -> 144757881 | T13: {=S13-S12} -> 22157341 | U13: {='net worth - net worth'!$B$3} -> 11447471 | V13: {=U13-U12} -> 1754140 | W13: {='net worth - net worth'!$B$2} -> 1693457 | X13: {=W13-W12} -> -229209 | Y13: {='net worth - net worth'!$B$6} -> 93254171 | Z13: {=Y13-Y12} -> 9529594 | AA13: {='net worth - net worth'!$B$12} -> 17512018 | AB13: {=AA13-AA12} -> 19157646 | AC13: {='net worth - net worth'!$B$15} -> 78939167 | AD13: {=-(AC13-AC12)} -> 19768268
B14: {=SUM(B4:B13)} -> 2.7754712e+08 | C14: {=SUM(C4:C13)} -> 341130 | D14: {=SUM(D4:D13)} -> 2.1990229e+08 | H14: {=SUM(H4:H13)} -> 57644830 | L14: {=SUM(L4:L13)} -> 20647471 | M14: {=SUM(M4:M13)} -> 49688600 | N14: {=SUM(N4:N13)} -> 10591208 | O14: {=SUM(O4:O13)} -> 80927279

Sheet net worth - Table 2
E1: invested | F1: net worth
A2: 10000 | B2: {=A2*'variables - Table 1'!$B$13} -> 8869400 | C2: {=COUNT('net worth - Table 1-1'!P2:P9)} -> 8 | D2: {=SUM(C$2:C2)} -> 8
A3: 25000 | B3: {=A3*'variables - Table 1'!$B$13} -> 22173500 | C3: {=COUNT('net worth - Table 1-1'!P$10:P26)} -> 17 | D3: {=SUM(C$2:C3)} -> 25
A4: 50000 | B4: {=A4*'variables - Table 1'!$B$13} -> 44347000 | C4: {=COUNT('net worth - Table 1-1'!$P$27:P43)} -> 17 | D4: {=SUM(C$2:C4)} -> 42
A5: 100000 | B5: {=A5*'variables - Table 1'!$B$13} -> 88694000 | C5: {=COUNT('net worth - Table 1-1'!$Q$44:Q85)} -> 42 | D5: {=SUM(C$2:C5)} -> 84
A6: 150000 | B6: {=A6*'variables - Table 1'!$B$13} -> 133041000 | C6: {=COUNT('net worth - Table 1-1'!$Q$86:Q113)} -> 28 | D6: {=SUM(C$2:C6)} -> 112 | E6: {=B6-'net worth - net worth'!B$17} -> 26645901
A7: 200000 | B7: {=A7*'variables - Table 1'!$B$13} -> 177388000 | E7: {=B7-'net worth - net worth'!B$17} -> 70992901
A8: 250000 | B8: {=A8*'variables - Table 1'!$B$13} -> 221735000 | E8: {=B8-'net worth - net worth'!B$17} -> 115339901
A9: 300000 | B9: {=A9*'variables - Table 1'!$B$13} -> 266082000 | E9: {=B9-'net worth - net worth'!B$17} -> 159686901 | F9: {=B9-'net worth - net worth'!B$18} -> -2582998
A10: 500000 | B10: {=A10*'variables - Table 1'!$B$13} -> 443470000 | E10: {=B10-'net worth - net worth'!B$17} -> 337074901 | F10: {=B10-'net worth - net worth'!B$18} -> 174805002
A11: 1000000 | B11: {=A11*'variables - Table 1'!$B$13} -> 886940000 | E11: {=B11-'net worth - net worth'!B$17} -> 780544901 | F11: {=B11-'net worth - net worth'!B$18} -> 618275002

Sheet net worth - dap-1
A1: dap-1
B2: fintual reserva | C2: dap
A3: 45526 | B3: 4140553
A4: 45527 | B4: 4140826 | C4: {=B3} -> 4140553
A5: 45528 | B5: 4140826
A6: 45529 | B6: 4140826
A7: 45530 | B7: 4142732
A8: 45531 | B8: 4143367
A9: 45532 | B9: 4144004
A10: 45533
A11: 45534 | C11: {=C4+3381} -> 4143934 | D11: {=A11-TODAY()} -> -622
A12: 45535
A13: 45536
A14: 45537 | B14: 4442563
A15: 45538 | B15: {=4443161+1300000} -> 5743161
A16: 45539 | B16: 5743772
A17: 45540
A18: 45541
A19: 45542
A20: 45543
A21: 45544 | B21: 7747397
A22: 45545 | B22: 7748574
A23: 45546 | B23: 7749627
A24: 45547 | B24: 7750596
A25: 45548
A26: 45549
A27: 45550
A28: 45551
A29: 45552 | B29: 7754222
A30: 45553
A31: 45554
A32: 45555
A33: 45556
A34: 45557
A35: 45558 | B35: 7761907 | C35: 4452432 | D35: {=A35-TODAY()} -> -598
A36: 45559 | B36: 7762848
A37: 45560
A38: 45561 | B38: 12765558
A39: 45562 | B39: 12767567
A40: 45563
A41: 45564
A42: 45565 | B42: 12772416
A43: 45566
A44: 45567 | B44: 12776432
A45: 45568 | B45: 12778026
A46: 45569 | B46: 12780727 | C46: 4459164 | D46: {=A46-TODAY()} -> -587 | E46: {=B46-B42} -> 8311
A47: 45570 | B47: {=12780727+2852410} -> 15633137
A48: 45571
A49: 45572 | B49: 15637893
A50: 45573 | B50: 15640411
A51: 45574 | B51: 15642841
A52: 45575 | B52: 15645126
A53: 45576 | B53: 15647031
A54: 45577
A55: 45578 | B55: 15646039
A56: 45579 | B56: 15652999
A57: 45580 | B57: 15655483
A58: 45581 | B58: 15657563
A59: 45582 | B59: 15659670
A60: 45583 | B60: 15661701
A61: 45584
A62: 45585
A63: 45586 | B63: 15667701
A64: 45587 | B64: 15669806
A65: 45588 | B65: 15671870
A66: 45589 | B66: 15673872 | E66: {=B66-B47} -> 40735
A67: 45590 | B67: 19674551
A68: 45591
A69: 45592
A70: 45593 | B70: 19683509
A71: 45594 | B71: 19686356
A72: 45595 | B72: 19688735 | E72: {=B72-B67} -> 14184
A73: 45596
A74: 45597
A75: 45598
A76: 45599 | B76: 19686225
A77: 45600 | B77: 19700214
A78: 45601 | B78: 19702409
A79: 45602 | B79: 19705388
A80: 45603 | B80: 19707807
A81: 45604 | B81: 19709066
A82: 45605
A83: 45606
A84: 45607 | B84: 19717719
A85: 45608 | B85: 19719934
A86: 45609
A87: 45610
A88: 45611
A89: 45612
A90: 45613 | B90: 225424
A91: 45614 | B91: 3225424
A92: 45615 | B92: 3225557
A93: 45616 | B93: 3226075
A94: 45617
A95: 45618 | B95: 6226075
A96: 45619
A97: 45620
A98: 45621 | B98: 6229776
A99: 45622 | B99: 6230707
A100: 45623 | B100: 6231612
...

Sheet net worth - net worth
A1: net worth
A2: cripto | B2: {='net worth - resumen | depósitos'!N$116} -> 1693457 | E2: {=ROUND(B2/'variables - Table 1'!$B$13,2)} -> 1909.33 | F2: {=B2/B$18} -> 0.006303229 | G2: {=SUM(F2:F6)} -> 0.39601399
A3: brokerage | B3: {='net worth - resumen | depósitos'!H$116} -> 11447471 | E3: {=ROUND(B3/'variables - Table 1'!$B$13,2)} -> 12906.7 | F3: {=B3/B$18} -> 0.042608717 | G3: {=SUM(F3:F6)} -> 0.38971077
C4: {='net worth - brokerage'!F$117} -> 10361465 | D4: {=C4/B$18} -> 0.038566486 | E4: {=C4/'variables - Table 1'!$B$13} -> 11682.261 | F4: {=B4/B$18} -> 0
C5: {='net worth - brokerage'!J$117} -> 1086006 | D5: {=C5/B$18} -> 0.0040422311 | E5: {=C5/'variables - Table 1'!$B$13} -> 1224.4413 | F5: {=B5/B$18} -> 0
A6: retiro | B6: {='net worth - resumen | depósitos'!E$116} -> 93254171 | E6: {=ROUND(B6/'variables - Table 1'!$B$13,2)} -> 105141.47 | F6: {=B6/B$18} -> 0.34710205
C7: {='net worth - retiro'!O$118} -> 1294075 | D7: {=C7/B$18} -> 0.0048166862 | E7: {=B6/'variables - Table 1'!$B$13} -> 105141.47
C8: {='net worth - retiro'!K$118} -> 19827694 | D8: {=C8/B$18} -> 0.073800808 | E8: {=C8/'variables - Table 1'!$B$13} -> 22355.169
C9: {='net worth - retiro'!D$118} -> 28084955 | D9: {=C9/B$18} -> 0.10453522 | E9: {=C9/'variables - Table 1'!$B$13} -> 31665
C10: {='net worth - retiro'!F$118} -> 44047447 | D10: {=C10/B$18} -> 0.16394933 | E10: {=C10/'variables - Table 1'!$B$13} -> 49662.262
A12: cash and eqs | B12: {='net worth - resumen | depósitos'!K$116} -> 17512018 | E12: {=ROUND(B12/'variables - Table 1'!$B$13,2)} -> 19744.31 | F12: {=B12/B$18} -> 0.065181613 | G12: {=F12} -> 0.065181613
A13: real estate | B13: {='depto - dividendos'!C$164} -> 144757881 | E13: {=ROUND(B13/'variables - Table 1'!$B$13,2)} -> 163210.46 | F13: {=B13/B$18} -> 0.53880439 | G13: {=SUM(F13)} -> 0.53880439
A15: liabilities | B15: {='flujos - Table 3'!L$17+'depto - dividendos'!C$163} -> 78939167 | E15: {=ROUND(B$15/'variables - Table 1'!B13,2)} -> 89001.7 | F15: {=B15/'presupuesto - Ingreso líquido'!$B$40} -> 1.6520863
A16: availabl | B16: {=SUM(B12,B2,B3,'net worth - balances'!B9:B10*0.85)} -> 84946816 | E16: {=ROUND(B16/'variables - Table 1'!$B$13,2)} -> 95775.15 | F16: {=B16/'presupuesto - Ingreso líquido'!$B$40} -> 1.777818
A17: invested | B17: {=SUM(B2,B3,B6)} -> 106395099 | E17: {=ROUND(B17/'variables - Table 1'!$B$13,2)} -> 119957.49 | F17: {=B17/'presupuesto - Ingreso líquido'!$B$40} -> 2.2267005
A18: net worth | B18: {=SUM(B2,B3,B6,B12,B13)} -> 268664998 | E18: {=ROUND(B$18/'variables - Table 1'!$B$13,2)} -> 302912.26 | F18: {=B18/'presupuesto - Ingreso líquido'!$B$40} -> 5.6227824

Sheet net worth - cash
A1: cash
A2: cuenta corriente | B2: {=238528+2772870+9346+60000-2800000} -> 280744
A3: reserva | B3: {='net worth - dap'!C$12} -> 27351662
A6: usd | B6: 0
A7: eur | B7: 0
A8: foreign money | B8: {=B6*'variables - Table 1'!B13+B7*'variables - Table 1'!B14} -> 0
A9: emergencia | B9: {=3000000*0} -> 0
A10: no cuenta | B10: {=('flujos - Gasto mensual'!A119-IF('flujos - Table 2-1'!B$10<0,'flujos - Table 2-1'!B$10,0))*0} -> 0
A11: no cuenta2 | B11: {='flujos - Table 3'!L$17+'flujos - Table 2'!C18-'presupuesto - Ingreso líquido'!B35*0} -> 10120388
A12: líquido | B12: {=SUM($B$2:$B$3)-$B$10-B$11} -> 17512018

Sheet net worth - balances
A1: balances
A4: reserva - fintual | B4: 27351662 | C4: {=ROUND(B4/'variables - Table 1'!B$2,2)} -> 673.51 | D4: {=B4/'variables - Table 1'!$B$13} -> 30838.233
A5: rn - fintual | B5: 10361465 | C5: {=ROUND(B5/'variables - Table 1'!B$2,2)} -> 255.14 | D5: {=B5/'variables - Table 1'!$B$13} -> 11682.261
A6: stocks | B6: {='net worth - brokerage'!J$117} -> 1086006 | C6: {=ROUND(B6/'variables - Table 1'!B$2,2)} -> 26.74 | D6: {=B6/'variables - Table 1'!$B$13} -> 1224.4413
A7: dap | C7: {=ROUND(B7/'variables - Table 1'!B$2,2)} -> 0 | D7: {=B7/'variables - Table 1'!$B$13} -> 0
A8: ahorro vivienda | B8: {='net worth - cash and cash equiv'!D$118} -> 0 | C8: {=ROUND(B8/'variables - Table 1'!B$2,2)} -> 0 | D8: {=B8/'variables - Table 1'!$B$13} -> 0
A9: rn apv-a - fintual | B9: 44047447 | C9: {=ROUND(B9/'variables - Table 1'!B$2,2)} -> 1084.63 | D9: {=B9/'variables - Table 1'!$B$13} -> 49662.262
A10: rn apv-b - fintual | B10: 19827694 | C10: {=ROUND(B10/'variables - Table 1'!B$2,2)} -> 488.24 | D10: {=B10/'variables - Table 1'!$B$13} -> 22355.169
A11: afp | B11: 28084955 | C11: {=ROUND(B11/'variables - Table 1'!B$2,2)} -> 691.57 | D11: {=B11/'variables - Table 1'!$B$13} -> 31665
A12: afc | B12: 1294075 | C12: {=ROUND(B12/'variables - Table 1'!B$2,2)} -> 31.87 | D12: {=B12/'variables - Table 1'!$B$13} -> 1459.0333

Sheet net worth - Table 1
C1: Precio de comrpa
A2: Kindle | B2: 42838 | C2: 60000
A3: Wayfarers | B3: 43267 | C3: 100000
A4: Bose QC35 | B4: 42705 | C4: 320000
A9: Batería portátil | B9: 42811 | C9: 49900
A10: Kronaby | B10: 42933 | E10: 315
A11: Correa Kronaby | B11: 42933 | E11: 59
A13: iPhone SE | B13: 42995 | D13: 449
A16: Wüsthof | B16: 43118 | C16: 63000
A18: Clubmasters | B18: 43149 | C18: 169900
A19: Switch | B19: 43238 | C19: 249990
A20: Mario Kart | B20: 43238 | D20: 66
A21: Zelda: BotW | B21: 43238 | C21: 36990
A22: Dynavap x2 | B22: 43299 | D22: 100
A23: AirPods | B23: 43361 | D23: 149
A24: Super Mario Party | B24: 43391 | D24: 59
A29: Magic Keyboard | B29: 43515 | C29: 89990
A30: Magic Trackpad | B30: 43515 | C30: 129990
A31: Cama | B31: 43665 | C31: {=371490} -> 371490
A32: Refrigerador | B32: 43665 | C32: 328980
A33: Bravia X72F | B33: 43665 | C33: 370000
A34: Cortinas | B34: 43665 | C34: 400000
A35: Mesa comedor | B35: 43757 | C35: 156980
A37: MacBook Pro | B37: 43891 | C37: 1549990
A38: AC Infinity T4 | B38: 43891 | D38: 119
A39: Lavadora | B39: 43983 | C39: 349990
A40: iPhone SE 2020 | B40: 44075 | C40: 492980
A41: Procesadora | B41: 44105 | C41: 49990
A42: Silla de escritorio | B42: 44136 | C42: 124899
A43: Bici P3 | B43: 44166 | C43: 179990
A44: Aire | B44: 44166 | C44: 323980
A46: LGR black matte/blue mirror | B46: 44774 | E46: {=300+100} -> 400
A60: PC escritorio
A62: Plays
A63: Nintendo
A64: Sus juegos
C66: {=SUM(C2:C65)} -> 5969029 | D66: {=SUM(D2:D65)} -> 942 | E66: {=SUM(E2:E65)} -> 774

Sheet net worth - resumen | depósitos
A1: resumen | depósitos - actual
B2: real estate | E2: retiro | F2: {=E$116/'presupuesto - Ingreso líquido'!B40} -> 1.9516793 | H2: brokerage | K2: cash and eqs | N2: cripto | Q2: total | R2: + real estate | U2: - cripto
A3: 42887 | E3: {='net worth - retiro'!B5} -> 131724 | F3: {=E3/'flujos - Gasto mensual'!C3} -> 0.10605387 | H3: {='net worth - brokerage'!B4} -> 1000000 | K3: {='net worth - cash and cash equiv'!D5+'net worth - cash and cash equiv'!D4} -> 2811698 | L3: {=K3/'flujos - Gasto mensual'!$C3} -> 2.2637595 | Q3: {=R3-B3} -> 3943422 | R3: {=K3+H3+N3+E3} -> 3943422 | S3: {=R3/'variables - Table 1-1'!B2} -> 5932.6343 | T3: {=_xlfn.IFERROR(R3/'flujos - Gasto mensual'!$C3,0)} -> 3.1749353 | U3: {=E3+H3+K3} -> 3943422 | V3: {=F3+O3+I3+L3} -> 2.3698134
A4: 42917 | E4: {='net worth - retiro'!B6} -> 139702 | F4: {=E4/'flujos - Gasto mensual'!C4} -> 0.10030421 | H4: {='net worth - brokerage'!B5} -> 0 | K4: {='net worth - cash and cash equiv'!D6} -> 53188 | L4: {=K4/'flujos - Gasto mensual'!$C4} -> 0.038188289 | Q4: {=R4-B4} -> 192890 | R4: {=K4+H4+N4+E4} -> 192890 | S4: {=R4/'variables - Table 1-1'!B3} -> 295.30006 | T4: {=_xlfn.IFERROR(R4/'flujos - Gasto mensual'!$C4,0)} -> 0.1384925 | U4: {=E4+H4+K4} -> 192890 | V4: {=F4+O4+I4+L4} -> 0.1384925
A5: 42948 | E5: {='net worth - retiro'!B7} -> 149219 | F5: {=E5/'flujos - Gasto mensual'!C5} -> 0.10431926 | H5: {='net worth - brokerage'!B6} -> 0 | K5: {='net worth - cash and cash equiv'!D7} -> 53212 | L5: {=K5/'flujos - Gasto mensual'!$C5} -> 0.037200601 | Q5: {=R5-B5} -> 202431 | R5: {=K5+H5+N5+E5} -> 202431 | S5: {=R5/'variables - Table 1-1'!B4} -> 320.60659 | T5: {=_xlfn.IFERROR(R5/'flujos - Gasto mensual'!$C5,0)} -> 0.14151986 | U5: {=E5+H5+K5} -> 202431 | V5: {=F5+O5+I5+L5} -> 0.14151986
A6: 42979 | E6: {='net worth - retiro'!B8} -> 148639 | F6: {=E6/'flujos - Gasto mensual'!C6} -> 0.10072031 | H6: {='net worth - brokerage'!B7} -> 0 | K6: {='net worth - cash and cash equiv'!D8} -> 353306 | L6: {=K6/'flujos - Gasto mensual'!$C6} -> 0.23940614 | Q6: {=R6-B6} -> 501945 | R6: {=K6+H6+N6+E6} -> 501945 | S6: {=R6/'variables - Table 1-1'!B5} -> 789.96695 | T6: {=_xlfn.IFERROR(R6/'flujos - Gasto mensual'!$C6,0)} -> 0.34012644 | U6: {=E6+H6+K6} -> 501945 | V6: {=F6+O6+I6+L6} -> 0.34012644
A7: 43009 | E7: {='net worth - retiro'!B9} -> 156386 | F7: {=E7/'flujos - Gasto mensual'!C7} -> 0.09400536 | H7: {='net worth - brokerage'!B8} -> 200000 | I7: {=H7/'flujos - Gasto mensual'!$C7} -> 0.12022222 | K7: {='net worth - cash and cash equiv'!D9} -> 653266 | L7: {=K7/'flujos - Gasto mensual'!$C7} -> 0.39268544 | Q7: {=R7-B7} -> 1009652 | R7: {=K7+H7+N7+E7} -> 1009652 | S7: {=R7/'variables - Table 1-1'!B6} -> 1625.7963 | T7: {=_xlfn.IFERROR(R7/'flujos - Gasto mensual'!$C7,0)} -> 0.60691302 | U7: {=E7+H7+K7} -> 1009652 | V7: {=F7+O7+I7+L7} -> 0.60691302
A8: 43040 | E8: {='net worth - retiro'!B10} -> 148639 | F8: {=E8/'flujos - Gasto mensual'!C8} -> 0.10424516 | H8: {='net worth - brokerage'!B9} -> 350000 | I8: {=H8/'flujos - Gasto mensual'!$C8} -> 0.24546589 | K8: {='net worth - cash and cash equiv'!D10} -> 553462 | L8: {=K8/'flujos - Gasto mensual'!$C8} -> 0.38816013 | N8: {='net worth - criptomonedas'!B10} -> 940418 | O8: {=N8/'flujos - Gasto mensual'!$C8} -> 0.65954442 | Q8: {=R8-B8} -> 1992519 | R8: {=K8+H8+N8+E8} -> 1992519 | S8: {=R8/'variables - Table 1-1'!B7} -> 3094.9348 | T8: {=_xlfn.IFERROR(R8/'flujos - Gasto mensual'!$C8,0)} -> 1.3974156 | U8: {=E8+H8+K8} -> 1052101 | V8: {=F8+O8+I8+L8} -> 1.3974156
A9: 43070 | E9: {='net worth - retiro'!B11} -> 148649 | F9: {=E9/'flujos - Gasto mensual'!C9} -> 0.092281628 | H9: {='net worth - brokerage'!B10} -> 200000 | I9: {=H9/'flujos - Gasto mensual'!$C9} -> 0.12416044 | K9: {='net worth - cash and cash equiv'!D11} -> 60655 | L9: {=K9/'flujos - Gasto mensual'!$C9} -> 0.037654758 | N9: {='net worth - criptomonedas'!B11} -> 452316 | O9: {=N9/'flujos - Gasto mensual'!$C9} -> 0.28079877 | Q9: {=R9-B9} -> 861620 | R9: {=K9+H9+N9+E9} -> 861620 | S9: {=R9/'variables - Table 1-1'!B8} -> 1402.3763 | T9: {=_xlfn.IFERROR(R9/'flujos - Gasto mensual'!$C9,0)} -> 0.5348956 | U9: {=E9+H9+K9} -> 409304 | V9: {=F9+O9+I9+L9} -> 0.5348956
A10: 43101 | E10: {='net worth - retiro'!B12} -> 149740 | F10: {=E10/'flujos - Gasto mensual'!C10} -> 0.10185764 | H10: {='net worth - brokerage'!B11} -> 0 | I10: {=H10/'flujos - Gasto mensual'!$C10} -> 0 | K10: {='net worth - cash and cash equiv'!D12} -> 146404 | L10: {=K10/'flujos - Gasto mensual'!$C10} -> 0.099588393 | N10: {='net worth - criptomonedas'!B12} -> 254436.85 | O10: {=N10/'flujos - Gasto mensual'!$C10} -> 0.17307558 | Q10: {=R10-B10} -> 550580.85 | R10: {=K10+H10+N10+E10} -> 550580.85 | S10: {=R10/'variables - Table 1-1'!B9} -> 907.94995 | T10: {=_xlfn.IFERROR(R10/'flujos - Gasto mensual'!$C10,0)} -> 0.37452161 | U10: {=E10+H10+K10} -> 296144 | V10: {=F10+O10+I10+L10} -> 0.37452161
A11: 43132 | E11: {='net worth - retiro'!B13} -> 142283 | F11: {=E11/'flujos - Gasto mensual'!C11} -> 0.096685132 | H11: {='net worth - brokerage'!B12} -> 200000 | I11: {=H11/'flujos - Gasto mensual'!$C11} -> 0.13590539 | K11: {='net worth - cash and cash equiv'!D13} -> 200000 | L11: {=K11/'flujos - Gasto mensual'!$C11} -> 0.13590539 | N11: {='net worth - criptomonedas'!B13} -> 271169 | O11: {=N11/'flujos - Gasto mensual'!$C11} -> 0.18426664 | Q11: {=R11-B11} -> 813452 | R11: {=K11+H11+N11+E11} -> 813452 | S11: {=R11/'variables - Table 1-1'!B10} -> 1375.2358 | T11: {=_xlfn.IFERROR(R11/'flujos - Gasto mensual'!$C11,0)} -> 0.55276255 | U11: {=E11+H11+K11} -> 542283 | V11: {=F11+O11+I11+L11} -> 0.55276255
A12: 43160 | E12: {='net worth - retiro'!B14} -> 192283 | F12: {=E12/'flujos - Gasto mensual'!C12} -> 0.087532902 | H12: {='net worth - brokerage'!B13} -> 150000 | I12: {=H12/'flujos - Gasto mensual'!$C12} -> 0.068284431 | K12: {='net worth - cash and cash equiv'!D14} -> 403934 | L12: {=K12/'flujos - Gasto mensual'!$C12} -> 0.18388269 | N12: {='net worth - criptomonedas'!B14} -> 200000 | O12: {=N12/'flujos - Gasto mensual'!$C12} -> 0.091045908 | Q12: {=R12-B12} -> 946217 | R12: {=K12+H12+N12+E12} -> 946217 | S12: {=R12/'variables - Table 1-1'!B11} -> 1568.1422 | T12: {=_xlfn.IFERROR(R12/'flujos - Gasto mensual'!$C12,0)} -> 0.43074593 | U12: {=E12+H12+K12} -> 746217 | V12: {=F12+O12+I12+L12} -> 0.43074593
A13: 43191 | E13: {='net worth - retiro'!B15} -> 561344 | F13: {=E13/'flujos - Gasto mensual'!C13} -> 0.20118919 | H13: {='net worth - brokerage'!B14} -> 250000 | I13: {=H13/'flujos - Gasto mensual'!$C13} -> 0.08960156 | K13: {='net worth - cash and cash equiv'!D15} -> 254042 | L13: {=K13/'flujos - Gasto mensual'!$C13} -> 0.091050238 | N13: {='net worth - criptomonedas'!B15} -> 450000 | O13: {=N13/'flujos - Gasto mensual'!$C13} -> 0.16128281 | Q13: {=R13-B13} -> 1515386 | R13: {=K13+H13+N13+E13} -> 1515386 | S13: {=R13/'variables - Table 1-1'!B12} -> 2501.8755 | T13: {=_xlfn.IFERROR(R13/'flujos - Gasto mensual'!$C13,0)} -> 0.5431238 | U13: {=E13+H13+K13} -> 1065386 | V13: {=F13+O13+I13+L13} -> 0.5431238
A14: 43221 | E14: {='net worth - retiro'!B16} -> 42379 | F14: {=E14/'flujos - Gasto mensual'!C14} -> 0.048429711 | H14: {='net worth - brokerage'!B15} -> 0 | I14: {=H14/'flujos - Gasto mensual'!$C14} -> 0 | K14: {='net worth - cash and cash equiv'!D16} -> 54157 | L14: {=K14/'flujos - Gasto mensual'!$C14} -> 0.061889329 | N14: {='net worth - criptomonedas'!B16} -> 0 | O14: {=N14/'flujos - Gasto mensual'!$C14} -> 0 | Q14: {=R14-B14} -> 96536 | R14: {=K14+H14+N14+E14} -> 96536 | S14: {=R14/'variables - Table 1-1'!B13} -> 153.91582 | T14: {=_xlfn.IFERROR(R14/'flujos - Gasto mensual'!$C14,0)} -> 0.11031904 | U14: {=E14+H14+K14} -> 96536 | V14: {=F14+O14+I14+L14} -> 0.11031904
A15: 43252 | E15: {='net worth - retiro'!B17} -> 532842 | F15: {=E15/'flujos - Gasto mensual'!C15} -> 0.32163067 | H15: {='net worth - brokerage'!B16} -> 150000 | I15: {=H15/'flujos - Gasto mensual'!$C15} -> 0.090542039 | K15: {='net worth - cash and cash equiv'!D17} -> 688185 | L15: {=K15/'flujos - Gasto mensual'!$C15} -> 0.41539782 | N15: {='net worth - criptomonedas'!B17} -> 0 | O15: {=N15/'flujos - Gasto mensual'!$C15} -> 0 | Q15: {=R15-B15} -> 1371027 | R15: {=K15+H15+N15+E15} -> 1371027 | S15: {=R15/'variables - Table 1-1'!B14} -> 2112.5223 | T15: {=_xlfn.IFERROR(R15/'flujos - Gasto mensual'!$C15,0)} -> 0.82757053 | U15: {=E15+H15+K15} -> 1371027 | V15: {=F15+O15+I15+L15} -> 0.82757053
A16: 43282 | E16: {='net worth - retiro'!B18} -> 432842 | F16: {=E16/'flujos - Gasto mensual'!C16} -> 0.25661058 | H16: {='net worth - brokerage'!B17} -> 150000 | I16: {=H16/'flujos - Gasto mensual'!$C16} -> 0.088927569 | K16: {='net worth - cash and cash equiv'!D18} -> 354405 | L16: {=K16/'flujos - Gasto mensual'!$C16} -> 0.21010917 | N16: {='net worth - criptomonedas'!B18} -> 0 | O16: {=N16/'flujos - Gasto mensual'!$C16} -> 0 | Q16: {=R16-B16} -> 937247 | R16: {=K16+H16+N16+E16} -> 937247 | S16: {=R16/'variables - Table 1-1'!B15} -> 1468.809 | T16: {=_xlfn.IFERROR(R16/'flujos - Gasto mensual'!$C16,0)} -> 0.55564732 | U16: {=E16+H16+K16} -> 937247 | V16: {=F16+O16+I16+L16} -> 0.55564732
A17: 43313 | E17: {='net worth - retiro'!B19} -> 434029 | F17: {=E17/'flujos - Gasto mensual'!C17} -> 0.26060483 | H17: {='net worth - brokerage'!B18} -> 0 | I17: {=H17/'flujos - Gasto mensual'!$C17} -> 0 | K17: {='net worth - cash and cash equiv'!D19} -> 354575 | L17: {=K17/'flujos - Gasto mensual'!$C17} -> 0.21289812 | N17: {='net worth - criptomonedas'!B19} -> 0 | O17: {=N17/'flujos - Gasto mensual'!$C17} -> 0 | Q17: {=R17-B17} -> 788604 | R17: {=K17+H17+N17+E17} -> 788604 | S17: {=R17/'variables - Table 1-1'!B16} -> 1161.4197 | T17: {=_xlfn.IFERROR(R17/'flujos - Gasto mensual'!$C17,0)} -> 0.47350294 | U17: {=E17+H17+K17} -> 788604 | V17: {=F17+O17+I17+L17} -> 0.47350294
A18: 43344 | E18: {='net worth - retiro'!B20} -> 434029 | F18: {=E18/'flujos - Gasto mensual'!C18} -> 0.25615438 | H18: {='net worth - brokerage'!B19} -> 150000 | I18: {=H18/'flujos - Gasto mensual'!$C18} -> 0.088526703 | K18: {='net worth - cash and cash equiv'!D20} -> 354715 | L18: {=K18/'flujos - Gasto mensual'!$C18} -> 0.209345 | N18: {='net worth - criptomonedas'!B20} -> 0 | O18: {=N18/'flujos - Gasto mensual'!$C18} -> 0 | Q18: {=R18-B18} -> 938744 | R18: {=K18+H18+N18+E18} -> 938744 | S18: {=R18/'variables - Table 1-1'!B17} -> 1423.6336 | T18: {=_xlfn.IFERROR(R18/'flujos - Gasto mensual'!$C18,0)} -> 0.55402608 | U18: {=E18+H18+K18} -> 938744 | V18: {=F18+O18+I18+L18} -> 0.55402608
A19: 43374 | E19: {='net worth - retiro'!B21} -> 428918 | F19: {=E19/'flujos - Gasto mensual'!C19} -> 0.21189926 | H19: {='net worth - brokerage'!B20} -> 250000 | I19: {=H19/'flujos - Gasto mensual'!$C19} -> 0.12350802 | K19: {='net worth - cash and cash equiv'!D21} -> 704864 | L19: {=K19/'flujos - Gasto mensual'!$C19} -> 0.34822544 | N19: {='net worth - criptomonedas'!B21} -> 0 | O19: {=N19/'flujos - Gasto mensual'!$C19} -> 0 | Q19: {=R19-B19} -> 1383782 | R19: {=K19+H19+N19+E19} -> 1383782 | S19: {=R19/'variables - Table 1-1'!B18} -> 1996.7994 | T19: {=_xlfn.IFERROR(R19/'flujos - Gasto mensual'!$C19,0)} -> 0.68363272 | U19: {=E19+H19+K19} -> 1383782 | V19: {=F19+O19+I19+L19} -> 0.68363272
... A37: 43922 | E37: {='net worth - retiro'!B39} -> 620974 | F37: {=E37/'flujos - Gasto mensual'!C37} -> 1.5994715 | H37: {='net worth - brokerage'!B38} -> 0 | I37: {=H37/'flujos - Gasto mensual'!$C37} -> 0 | K37: {='net worth - cash and cash equiv'!D39} -> 0 | L37: {=K37/'flujos - Gasto mensual'!$C37} -> 0 | N37: {='net worth - criptomonedas'!B39} -> 0 | O37: {=N37/'flujos - Gasto mensual'!$C37} -> 0 | Q37: {=R37-B37} -> 620974 | R37: {=K37+H37+N37+E37} -> 620974 | S37: {=R37/'variables - Table 1-1'!B36} -> 744.48387 | T37: {=_xlfn.IFERROR(R37/'flujos - Gasto mensual'!$C37,0)} -> 1.5994715 | U37: {=E37+H37+K37} -> 620974 | V37: {=F37+O37+I37+L37} -> 1.5994715
A38: 43952 | E38: {='net worth - retiro'!B40} -> 400000 | F38: {=_xlfn.IFERROR(E38/'flujos - Gasto mensual'!C38,0)} -> 0 | H38: {='net worth - brokerage'!B39} -> 0 | I38: {=_xlfn.IFERROR(H38/'flujos - Gasto mensual'!$C38,0)} -> 0 | K38: {='net worth - cash and cash equiv'!D40} -> 150000 | L38: {=_xlfn.IFERROR(K38/'flujos - Gasto mensual'!$C38,0)} -> 0 | N38: {='net worth - criptomonedas'!B40} -> 0 | O38: {=_xlfn.IFERROR(N38/'flujos - Gasto mensual'!$C38,0)} -> 0 | Q38: {=R38-B38} -> 550000 | R38: {=K38+H38+N38+E38} -> 550000 | S38: {=R38/'variables - Table 1-1'!B37} -> 680.60884 | T38: {=_xlfn.IFERROR(R38/'flujos - Gasto mensual'!$C38,0)} -> 0 | U38: {=E38+H38+K38} -> 550000 | V38: {=F38+O38+I38+L38} -> 0
A39: 43983 | E39: {='net worth - retiro'!B41} -> 0 | F39: {=_xlfn.IFERROR(E39/'flujos - Gasto mensual'!C39,0)} -> 0 | H39: {='net worth - brokerage'!B40} -> 0 | I39: {=_xlfn.IFERROR(H39/'flujos - Gasto mensual'!$C39,0)} -> 0 | K39: {='net worth - cash and cash equiv'!D41} -> 0 | L39: {=_xlfn.IFERROR(K39/'flujos - Gasto mensual'!$C39,0)} -> 0 | N39: {='net worth - criptomonedas'!B41} -> 0 | O39: {=_xlfn.IFERROR(N39/'flujos - Gasto mensual'!$C39,0)} -> 0 | Q39: {=R39-B39} -> 0 | R39: {=K39+H39+N39+E39} -> 0 | S39: {=R39/'variables - Table 1-1'!B38} -> 0 | T39: {=_xlfn.IFERROR(R39/'flujos - Gasto mensual'!$C39,0)} -> 0 | U39: {=E39+H39+K39} -> 0 | V39: {=F39+O39+I39+L39} -> 0
A40: 44013 | E40: {='net worth - retiro'!B42} -> 50131 | F40: {=_xlfn.IFERROR(E40/'flujos - Gasto mensual'!C40,0)} -> 0 | H40: {='net worth - brokerage'!B41} -> 0 | I40: {=_xlfn.IFERROR(H40/'flujos - Gasto mensual'!$C40,0)} -> 0 | K40: {='net worth - cash and cash equiv'!D42} -> 0 | L40: {=_xlfn.IFERROR(K40/'flujos - Gasto mensual'!$C40,0)} -> 0 | N40: {='net worth - criptomonedas'!B42} -> 0 | O40: {=_xlfn.IFERROR(N40/'flujos - Gasto mensual'!$C40,0)} -> 0 | Q40: {=R40-B40} -> 50131 | R40: {=K40+H40+N40+E40} -> 50131 | S40: {=R40/'variables - Table 1-1'!B39} -> 65.875164 | T40: {=_xlfn.IFERROR(R40/'flujos - Gasto mensual'!$C40,0)} -> 0 | U40: {=E40+H40+K40} -> 50131 | V40: {=F40+O40+I40+L40} -> 0
A41: 44044 | E41: {='net worth - retiro'!B43} -> 278001 | F41: {=_xlfn.IFERROR(E41/'flujos - Gasto mensual'!C41,0)} -> 0.11000056 | H41: {='net worth - brokerage'!B42} -> 0 | I41: {=_xlfn.IFERROR(H41/'flujos - Gasto mensual'!$C41,0)} -> 0 | K41: {='net worth - cash and cash equiv'!D43} -> 0 | L41: {=_xlfn.IFERROR(K41/'flujos - Gasto mensual'!$C41,0)} -> 0 | N41: {='net worth - criptomonedas'!B43} -> 0 | O41: {=_xlfn.IFERROR(N41/'flujos - Gasto mensual'!$C41,0)} -> 0 | Q41: {=R41-B41} -> 278001 | R41: {=K41+H41+N41+E41} -> 278001 | S41: {=R41/'variables - Table 1-1'!B40} -> 356.86906 | T41: {=_xlfn.IFERROR(R41/'flujos - Gasto mensual'!$C41,0)} -> 0.11000056 | U41: {=E41+H41+K41} -> 278001 | V41: {=F41+O41+I41+L41} -> 0.11000056
A42: 44075 | E42: {='net worth - retiro'!B44} -> 278001 | F42: {=_xlfn.IFERROR(E42/'flujos - Gasto mensual'!C42,0)} -> 0.11453653 | H42: {='net worth - brokerage'!B43} -> -3000000 | I42: {=_xlfn.IFERROR(H42/'flujos - Gasto mensual'!$C42,0)} -> -1.2360013 | K42: {='net worth - cash and cash equiv'!D44} -> 0 | L42: {=_xlfn.IFERROR(K42/'flujos - Gasto mensual'!$C42,0)} -> 0 | N42: {='net worth - criptomonedas'!B44} -> 0 | O42: {=_xlfn.IFERROR(N42/'flujos - Gasto mensual'!$C42,0)} -> 0 | Q42: {=R42-B42} -> -2721999 | R42: {=K42+H42+N42+E42} -> -2721999 | S42: {=R42/'variables - Table 1-1'!B41} -> -3471.4947 | T42: {=_xlfn.IFERROR(R42/'flujos - Gasto mensual'!$C42,0)} -> -1.1214647 | U42: {=E42+H42+K42} -> -2721999 | V42: {=F42+O42+I42+L42} -> -1.1214647
A43: 44105 | E43: {='net worth - retiro'!B45} -> 878001 | F43: {=_xlfn.IFERROR(E43/'flujos - Gasto mensual'!C43,0)} -> 0.36194272 | H43: {='net worth - brokerage'!B44} -> 0 | I43: {=_xlfn.IFERROR(H43/'flujos - Gasto mensual'!$C43,0)} -> 0 | K43: {='net worth - cash and cash equiv'!D45} -> 0 | L43: {=_xlfn.IFERROR(K43/'flujos - Gasto mensual'!$C43,0)} -> 0 | N43: {='net worth - criptomonedas'!B45} -> 0 | O43: {=_xlfn.IFERROR(N43/'flujos - Gasto mensual'!$C43,0)} -> 0 | Q43: {=R43-B43} -> 878001 | R43: {=K43+H43+N43+E43} -> 878001 | S43: {=R43/'variables - Table 1-1'!B42} -> 1138.0441 | T43: {=_xlfn.IFERROR(R43/'flujos - Gasto mensual'!$C43,0)} -> 0.36194272 | U43: {=E43+H43+K43} -> 878001 | V43: {=F43+O43+I43+L43} -> 0.36194272
A44: 44136 | E44: {='net worth - retiro'!B46} -> 2278001 | F44: {=_xlfn.IFERROR(E44/'flujos - Gasto mensual'!C44,0)} -> 0.93903799 | H44: {='net worth - brokerage'!B45} -> 0 | I44: {=_xlfn.IFERROR(H44/'flujos - Gasto mensual'!$C44,0)} -> 0 | K44: {='net worth - cash and cash equiv'!D46} -> 0 | L44: {=_xlfn.IFERROR(K44/'flujos - Gasto mensual'!$C44,0)} -> 0 | N44: {='net worth - criptomonedas'!B46} -> 0 | O44: {=_xlfn.IFERROR(N44/'flujos - Gasto mensual'!$C44,0)} -> 0 | Q44: {=R44-B44} -> 2278001 | R44: {=K44+H44+N44+E44} -> 2278001 | S44: {=R44/'variables - Table 1-1'!B43} -> 2965.3749 | T44: {=_xlfn.IFERROR(R44/'flujos - Gasto mensual'!$C44,0)} -> 0.93903799 | U44: {=E44+H44+K44} -> 2278001 | V44: {=F44+O44+I44+L44} -> 0.93903799
A45: 44166 | E45: {='net worth - retiro'!B47} -> 819422 | F45: {=_xlfn.IFERROR(E45/'flujos - Gasto mensual'!C45,0)} -> 0.33647129 | H45: {='net worth - brokerage'!B46} -> 0 | I45: {=_xlfn.IFERROR(H45/'flujos - Gasto mensual'!$C45,0)} -> 0 | K45: {='net worth - cash and cash equiv'!D47} -> 0 | L45: {=_xlfn.IFERROR(K45/'flujos - Gasto mensual'!$C45,0)} -> 0 | N45: {='net worth - criptomonedas'!B47} -> 0 | O45: {=_xlfn.IFERROR(N45/'flujos - Gasto mensual'!$C45,0)} -> 0 | Q45: {=R45-B45} -> 819422 | R45: {=K45+H45+N45+E45} -> 819422 | S45: {=R45/'variables - Table 1-1'!B44} -> 1152.4923 | T45: {=_xlfn.IFERROR(R45/'flujos - Gasto mensual'!$C45,0)} -> 0.33647129 | U45: {=E45+H45+K45} -> 819422 | V45: {=F45+O45+I45+L45} -> 0.33647129
A46: 44197 | E46: {='net worth - retiro'!B48} -> 278053 | F46: {=_xlfn.IFERROR(E46/'flujos - Gasto mensual'!C46,0)} -> 0.088061459 | H46: {='net worth - brokerage'!B47} -> 0 | I46: {=_xlfn.IFERROR(H46/'flujos - Gasto mensual'!$C46,0)} -> 0 | K46: {='net worth - cash and cash equiv'!D48} -> 400000 | L46: {=_xlfn.IFERROR(K46/'flujos - Gasto mensual'!$C46,0)} -> 0.12668298 | N46: {='net worth - criptomonedas'!B48} -> -2200000 | O46: {=_xlfn.IFERROR(N46/'flujos - Gasto mensual'!$C46,0)} -> -0.69675641 | Q46: {=R46-B46} -> -1521947 | R46: {=K46+H46+N46+E46} -> -1521947 | S46: {=R46/'variables - Table 1-1'!B45} -> -2069.2685 | T46: {=_xlfn.IFERROR(R46/'flujos - Gasto mensual'!$C46,0)} -> -0.48201197 | U46: {=E46+H46+K46} -> 678053 | V46: {=F46+O46+I46+L46} -> -0.48201197
A47: 44228 | E47: {='net worth - retiro'!B49} -> 102304 | F47: {=_xlfn.IFERROR(E47/'flujos - Gasto mensual'!C47,0)} -> 0.02413798 | H47: {='net worth - brokerage'!B48} -> 0 | I47: {=_xlfn.IFERROR(H47/'flujos - Gasto mensual'!$C47,0)} -> 0 | K47: {='net worth - cash and cash equiv'!D49} -> 1000000 | L47: {=_xlfn.IFERROR(K47/'flujos - Gasto mensual'!$C47,0)} -> 0.23594366 | N47: {='net worth - criptomonedas'!B49} -> -1500000 | O47: {=_xlfn.IFERROR(N47/'flujos - Gasto mensual'!$C47,0)} -> -0.35391548 | Q47: {=R47-B47} -> -397696 | R47: {=K47+H47+N47+E47} -> -397696 | S47: {=R47/'variables - Table 1-1'!B46} -> -555.82949 | T47: {=_xlfn.IFERROR(R47/'flujos - Gasto mensual'!$C47,0)} -> -0.093833848 | U47: {=E47+H47+K47} -> 1102304 | V47: {=F47+O47+I47+L47} -> -0.093833848
A48: 44256 | E48: {='net worth - retiro'!B50} -> 230355 | F48: {=_xlfn.IFERROR(E48/'flujos - Gasto mensual'!C48,0)} -> 0.074154636 | H48: {='net worth - brokerage'!B49} -> 0 | I48: {=_xlfn.IFERROR(H48/'flujos - Gasto mensual'!$C48,0)} -> 0 | K48: {='net worth - cash and cash equiv'!D50} -> 1500000 | L48: {=_xlfn.IFERROR(K48/'flujos - Gasto mensual'!$C48,0)} -> 0.48287189 | N48: {='net worth - criptomonedas'!B50} -> 0 | O48: {=_xlfn.IFERROR(N48/'flujos - Gasto mensual'!$C48,0)} -> 0 | Q48: {=R48-B48} -> 1730355 | R48: {=K48+H48+N48+E48} -> 1730355 | S48: {=R48/'variables - Table 1-1'!B47} -> 2374.2522 | T48: {=_xlfn.IFERROR(R48/'flujos - Gasto mensual'!$C48,0)} -> 0.55702653 | U48: {=E48+H48+K48} -> 1730355 | V48: {=F48+O48+I48+L48} -> 0.55702653
A49: 44287 | E49: {='net worth - retiro'!B51} -> 0 | F49: {=_xlfn.IFERROR(E49/'flujos - Gasto mensual'!C49,0)} -> 0 | H49: {='net worth - brokerage'!B50} -> 600000 | I49: {=_xlfn.IFERROR(H49/'flujos - Gasto mensual'!$C49,0)} -> 0.19314876 | K49: {='net worth - cash and cash equiv'!D51} -> 814182 | L49: {=_xlfn.IFERROR(K49/'flujos - Gasto mensual'!$C49,0)} -> 0.26209707 | N49: {='net worth - criptomonedas'!B51} -> 0 | O49: {=_xlfn.IFERROR(N49/'flujos - Gasto mensual'!$C49,0)} -> 0 | Q49: {=R49-B49} -> 1414182 | R49: {=K49+H49+N49+E49} -> 1414182 | S49: {=R49/'variables - Table 1-1'!B48} -> 1994.8963 | T49: {=_xlfn.IFERROR(R49/'flujos - Gasto mensual'!$C49,0)} -> 0.45524582 | U49: {=E49+H49+K49} -> 1414182 | V49: {=F49+O49+I49+L49} -> 0.45524582
... A84: 45352 | E84: {='net worth - retiro'!B86} -> 744683 | F84: {=_xlfn.IFERROR(E84/'flujos - Gasto mensual'!C84,0)} -> 0.1958364 | H84: {='net worth - brokerage'!B85} -> 0 | I84: {=_xlfn.IFERROR(H84/'flujos - Gasto mensual'!$C84,0)} -> 0 | K84: {='net worth - cash and cash equiv'!D86} -> -10100000 | L84: {=_xlfn.IFERROR(K84/'flujos - Gasto mensual'!$C84,0)} -> -2.6560935 | N84: {='net worth - criptomonedas'!B86} -> 0 | O84: {=_xlfn.IFERROR(N84/'flujos - Gasto mensual'!$C84,0)} -> 0 | Q84: {=R84-B84} -> -9355317 | R84: {=K84+H84+N84+E84} -> -9355317 | S84: {=R84/'variables - Table 1-1'!B83} -> -9541.763 | T84: {=_xlfn.IFERROR(R84/'flujos - Gasto mensual'!$C84,0)} -> -2.4602571 | U84: {=E84+H84+K84} -> -9355317 | V84: {=F84+O84+I84+L84} -> -2.4602571
A85: 45383 | B85: {='depto - dividendos'!C5} -> 53827132 | E85: {='net worth - retiro'!B87} -> 1096108 | F85: {=_xlfn.IFERROR(E85/'flujos - Gasto mensual'!C85,0)} -> 0.28824027 | H85: {='net worth - brokerage'!B86} -> 0 | I85: {=_xlfn.IFERROR(H85/'flujos - Gasto mensual'!$C85,0)} -> 0 | K85: {='net worth - cash and cash equiv'!B87} -> -38099733 | L85: {=_xlfn.IFERROR(K85/'flujos - Gasto mensual'!$C85,0)} -> -10.018974 | N85: {='net worth - criptomonedas'!B87} -> 0 | O85: {=_xlfn.IFERROR(N85/'flujos - Gasto mensual'!$C85,0)} -> 0 | Q85: {=R85-B85} -> -37003625 | R85: {=K85+H85+N85+E85+B85} -> 16823507 | S85: {=R85/'variables - Table 1-1'!B84} -> 17868.075 | T85: {=_xlfn.IFERROR(R85/'flujos - Gasto mensual'!$C85,0)} -> 4.4240278 | U85: {=B85+E85+H85+K85} -> 16823507 | V85: {=F85+O85+I85+L85} -> -9.7307336
A86: 45413 | B86: {='depto - dividendos'!C6} -> 0 | E86: {='net worth - retiro'!B88} -> 397601 | F86: {=_xlfn.IFERROR(E86/'flujos - Gasto mensual'!C86,0)} -> 0.10455268 | H86: {='net worth - brokerage'!B87} -> 0 | I86: {=_xlfn.IFERROR(H86/'flujos - Gasto mensual'!$C86,0)} -> 0 | K86: {='net worth - cash and cash equiv'!B88} -> 0 | L86: {=_xlfn.IFERROR(K86/'flujos - Gasto mensual'!$C86,0)} -> 0 | N86: {='net worth - criptomonedas'!B88} -> 0 | O86: {=_xlfn.IFERROR(N86/'flujos - Gasto mensual'!$C86,0)} -> 0 | Q86: {=R86-B86} -> 397601 | R86: {=K86+H86+N86+E86+B86} -> 397601 | S86: {=R86/'variables - Table 1-1'!B85} -> 433.66454 | T86: {=_xlfn.IFERROR(R86/'flujos - Gasto mensual'!$C86,0)} -> 0.10455268 | U86: {=B86+E86+H86+K86} -> 397601 | V86: {=F86+O86+I86+L86} -> 0.10455268
A87: 45444 | B87: {='depto - dividendos'!C7} -> 1200000 | C87: {=_xlfn.IFERROR(B87/'flujos - Gasto mensual'!$C87,0)} -> 0.31553804 | E87: {='net worth - retiro'!B89} -> 598725 | F87: {=_xlfn.IFERROR(E87/'flujos - Gasto mensual'!$C87,0)} -> 0.15743376 | H87: {='net worth - brokerage'!B88} -> 0 | I87: {=_xlfn.IFERROR(H87/'flujos - Gasto mensual'!$C87,0)} -> 0 | K87: {='net worth - cash and cash equiv'!B89} -> 377786 | L87: {=_xlfn.IFERROR(K87/'flujos - Gasto mensual'!$C87,0)} -> 0.099338212 | N87: {='net worth - criptomonedas'!B89} -> 0 | O87: {=_xlfn.IFERROR(N87/'flujos - Gasto mensual'!$C87,0)} -> 0 | Q87: {=R87-B87} -> 976511 | R87: {=K87+H87+N87+E87+B87} -> 2176511 | S87: {=R87/'variables - Table 1-1'!B86} -> 2281.1472 | T87: {=_xlfn.IFERROR(R87/'flujos - Gasto mensual'!$C87,0)} -> 0.57231001 | U87: {=E87+H87+K87+B87} -> 2176511 | V87: {=F87+O87+I87+L87} -> 0.25677197
A88: 45474 | B88: {='depto - dividendos'!C8} -> 3011141 | C88: {=_xlfn.IFERROR(B88/'flujos - Gasto mensual'!$C88,0)} -> 0.76933421 | E88: {='net worth - retiro'!B90} -> 401226 | F88: {=_xlfn.IFERROR(E88/'flujos - Gasto mensual'!$C88,0)} -> 0.1025116 | H88: {='net worth - brokerage'!B89} -> 0 | I88: {=_xlfn.IFERROR(H88/'flujos - Gasto mensual'!$C88,0)} -> 0 | K88: {='net worth - cash and cash equiv'!B90} -> -377786 | L88: {=_xlfn.IFERROR(K88/'flujos - Gasto mensual'!$C88,0)} -> -0.096522777 | N88: {='net worth - criptomonedas'!B90} -> 0 | O88: {=_xlfn.IFERROR(N88/'flujos - Gasto mensual'!$C88,0)} -> 0 | Q88: {=R88-B88} -> 23440 | R88: {=K88+H88+N88+E88+B88} -> 3034581 | S88: {=R88/'variables - Table 1-1'!B87} -> 3175.776 | T88: {=_xlfn.IFERROR(R88/'flujos - Gasto mensual'!$C88,0)} -> 0.77532303 | U88: {=E88+H88+K88+B88} -> 3034581 | V88: {=F88+O88+I88+L88} -> 0.0059888241
A89: 45505 | B89: {='depto - dividendos'!C9} -> 3009576 | C89: {=_xlfn.IFERROR(B89/'flujos - Gasto mensual'!$C89,0)} -> 0.78806931 | E89: {='net worth - retiro'!B91} -> 400615 | F89: {=_xlfn.IFERROR(E89/'flujos - Gasto mensual'!$C89,0)} -> 0.10490261 | H89: {='net worth - brokerage'!B90} -> 0 | I89: {=_xlfn.IFERROR(H89/'flujos - Gasto mensual'!$C89,0)} -> 0 | K89: {='net worth - cash and cash equiv'!B91} -> 295600 | L89: {=_xlfn.IFERROR(K89/'flujos - Gasto mensual'!$C89,0)} -> 0.077404022 | N89: {='net worth - criptomonedas'!B91} -> 0 | O89: {=_xlfn.IFERROR(N89/'flujos - Gasto mensual'!$C89,0)} -> 0 | Q89: {=R89-B89} -> 696215 | R89: {=K89+H89+N89+E89+B89} -> 3705791 | S89: {=R89/'variables - Table 1-1'!B88} -> 4051.9047 | T89: {=_xlfn.IFERROR(R89/'flujos - Gasto mensual'!$C89,0)} -> 0.97037594 | U89: {=E89+H89+K89+B89} -> 3705791 | V89: {=F89+O89+I89+L89} -> 0.18230663
A90: 45536 | B90: {='depto - dividendos'!C10} -> 3030085 | C90: {=_xlfn.IFERROR(B90/'flujos - Gasto mensual'!$C90,0)} -> 0.79339562 | E90: {='net worth - retiro'!B92} -> 401934 | F90: {=_xlfn.IFERROR(E90/'flujos - Gasto mensual'!$C90,0)} -> 0.10524216 | H90: {='net worth - brokerage'!B91} -> 0 | I90: {=_xlfn.IFERROR(H90/'flujos - Gasto mensual'!$C90,0)} -> 0 | K90: {='net worth - cash and cash equiv'!B92} -> 8300000 | L90: {=_xlfn.IFERROR(K90/'flujos - Gasto mensual'!$C90,0)} -> 2.173267 | N90: {='net worth - criptomonedas'!B92} -> 0 | O90: {=_xlfn.IFERROR(N90/'flujos - Gasto mensual'!$C90,0)} -> 0 | Q90: {=R90-B90} -> 8701934 | R90: {=K90+H90+N90+E90+B90} -> 11732019 | S90: {=R90/'variables - Table 1-1'!B89} -> 13039.199 | T90: {=_xlfn.IFERROR(R90/'flujos - Gasto mensual'!$C90,0)} -> 3.0719048 | U90: {=E90+H90+K90+B90} -> 11732019 | V90: {=F90+O90+I90+L90} -> 2.2785091
A91: 45566 | B91: {='depto - dividendos'!C11} -> 3038359 | C91: {=_xlfn.IFERROR(B91/'flujos - Gasto mensual'!$C91,0)} -> 0.79554292 | E91: {='net worth - retiro'!B93} -> 452450 | F91: {=_xlfn.IFERROR(E91/'flujos - Gasto mensual'!$C91,0)} -> 0.11846638 | H91: {='net worth - brokerage'!B92} -> 450000 | I91: {=_xlfn.IFERROR(H91/'flujos - Gasto mensual'!$C91,0)} -> 0.11782489 | K91: {='net worth - cash and cash equiv'!B93} -> 6852410 | L91: {=_xlfn.IFERROR(K91/'flujos - Gasto mensual'!$C91,0)} -> 1.7941877 | N91: {='net worth - criptomonedas'!B93} -> 0 | O91: {=_xlfn.IFERROR(N91/'flujos - Gasto mensual'!$C91,0)} -> 0 | Q91: {=R91-B91} -> 7754860 | R91: {=K91+H91+N91+E91+B91} -> 10793219 | S91: {=R91/'variables - Table 1-1'!B90} -> 11227.265 | T91: {=_xlfn.IFERROR(R91/'flujos - Gasto mensual'!$C91,0)} -> 2.8260219 | U91: {=E91+H91+K91+B91} -> 10793219 | V91: {=F91+O91+I91+L91} -> 2.0304789
A92: 45597 | B92: {=SUM('depto - dividendos'!C12:C13)} -> 22825709 | C92: {=_xlfn.IFERROR(B92/'flujos - Gasto mensual'!$C92,0)} -> 5.9771221 | E92: {='net worth - retiro'!B94} -> 446533 | F92: {=_xlfn.IFERROR(E92/'flujos - Gasto mensual'!$C92,0)} -> 0.11692878 | H92: {='net worth - brokerage'!B93} -> 0 | I92: {=_xlfn.IFERROR(H92/'flujos - Gasto mensual'!$C92,0)} -> 0 | K92: {='net worth - cash and cash equiv'!B94} -> -13500000 | L92: {=_xlfn.IFERROR(K92/'flujos - Gasto mensual'!$C92,0)} -> -3.5350993 | N92: {='net worth - criptomonedas'!B94} -> -600000 | O92: {=_xlfn.IFERROR(N92/'flujos - Gasto mensual'!$C92,0)} -> -0.15711553 | Q92: {=R92-B92} -> -13653467 | R92: {=K92+H92+N92+E92+B92} -> 9172242 | S92: {=R92/'variables - Table 1-1'!B91} -> 9383.9438 | T92: {=_xlfn.IFERROR(R92/'flujos - Gasto mensual'!$C92,0)} -> 2.4018361 | U92: {=E92+H92+K92+B92} -> 9772242 | V92: {=F92+O92+I92+L92} -> -3.5752861
A93: 45627 | B93: {='depto - dividendos'!C14} -> 3071042 | C93: {=_xlfn.IFERROR(B93/'flujos - Gasto mensual'!$C93,0)} -> 0.80411683 | E93: {='net worth - retiro'!B95} -> 406202 | F93: {=_xlfn.IFERROR(E93/'flujos - Gasto mensual'!$C93,0)} -> 0.1063593 | H93: {='net worth - brokerage'!B94} -> -2900000 | I93: {=_xlfn.IFERROR(H93/'flujos - Gasto mensual'!$C93,0)} -> -0.75933146 | K93: {='net worth - cash and cash equiv'!B95} -> 9000000 | L93: {=_xlfn.IFERROR(K93/'flujos - Gasto mensual'!$C93,0)} -> 2.3565459 | N93: {='net worth - criptomonedas'!B95} -> 0 | O93: {=_xlfn.IFERROR(N93/'flujos - Gasto mensual'!$C93,0)} -> 0 | Q93: {=R93-B93} -> 6506202 | R93: {=K93+H93+N93+E93+B93} -> 9577244 | S93: {=R93/'variables - Table 1-1'!B92} -> 9641.359 | T93: {=_xlfn.IFERROR(R93/'flujos - Gasto mensual'!$C93,0)} -> 2.5076906 | U93: {=E93+H93+K93+B93} -> 9577244 | V93: {=F93+O93+I93+L93} -> 1.7035738
A94: 45658 | B94: {='depto - dividendos'!C15} -> 3071622 | C94: {=_xlfn.IFERROR(B94/'flujos - Gasto mensual'!$C94,0)} -> 0.80307685 | E94: {='net worth - retiro'!B96} -> 406055 | F94: {=_xlfn.IFERROR(E94/'flujos - Gasto mensual'!$C94,0)} -> 0.10616325 | H94: {='net worth - brokerage'!B95} -> -4000000 | I94: {=_xlfn.IFERROR(H94/'flujos - Gasto mensual'!$C94,0)} -> -1.0458017 | K94: {='net worth - cash and cash equiv'!B96} -> 20500000 | L94: {=_xlfn.IFERROR(K94/'flujos - Gasto mensual'!$C94,0)} -> 5.3597336 | N94: {='net worth - criptomonedas'!B96} -> -900000 | O94: {=_xlfn.IFERROR(N94/'flujos - Gasto mensual'!$C94,0)} -> -0.23530538 | Q94: {=R94-B94} -> 16006055 | R94: {=K94+H94+N94+E94+B94} -> 19077677 | S94: {=R94/'variables - Table 1-1'!B93} -> 19392.416 | T94: {=_xlfn.IFERROR(R94/'flujos - Gasto mensual'!$C94,0)} -> 4.9878666 | U94: {=E94+H94+K94+B94} -> 19977677 | V94: {=F94+O94+I94+L94} -> 4.1847898
A95: 45689 | B95: {='depto - dividendos'!C17+'depto - dividendos'!C16} -> 18672815 | C95: {=_xlfn.IFERROR(B95/'flujos - Gasto mensual'!$C95,0)} -> 4.8714898 | E95: {='net worth - retiro'!B97} -> 421984 | F95: {=_xlfn.IFERROR(E95/'flujos - Gasto mensual'!$C95,0)} -> 0.11009003 | H95: {='net worth - brokerage'!B96} -> -10000000 | I95: {=_xlfn.IFERROR(H95/'flujos - Gasto mensual'!$C95,0)} -> -2.6088674 | K95: {='net worth - cash and cash equiv'!B97} -> -15000000 | L95: {=_xlfn.IFERROR(K95/'flujos - Gasto mensual'!$C95,0)} -> -3.9133011 | N95: {='net worth - criptomonedas'!B97} -> -3000000 | O95: {=_xlfn.IFERROR(N95/'flujos - Gasto mensual'!$C95,0)} -> -0.78266022 | Q95: {=R95-B95} -> -27578016 | R95: {=K95+H95+N95+E95+B95} -> -8905201 | S95: {=R95/'variables - Table 1-1'!B94} -> -9351.8451 | T95: {=_xlfn.IFERROR(R95/'flujos - Gasto mensual'!$C95,0)} -> -2.3232488 | U95: {=E95+H95+K95+B95} -> -5905201 | V95: {=F95+O95+I95+L95} -> -7.1947386
A96: 45717 | B96: {='depto - dividendos'!C18+'depto - Table 4-1'!B14} -> 27658932 | C96: {=_xlfn.IFERROR(B96/'flujos - Gasto mensual'!$C96,0)} -> 6.9681193 | E96: {='net worth - retiro'!B98} -> 427144 | F96: {=_xlfn.IFERROR(E96/'flujos - Gasto mensual'!$C96,0)} -> 0.10761046 | H96: {='net worth - brokerage'!B97} -> -6500000 | I96: {=_xlfn.IFERROR(H96/'flujos - Gasto mensual'!$C96,0)} -> -1.6375461 | K96: {='net worth - cash and cash equiv'!B98} -> -3550000 | L96: {=_xlfn.IFERROR(K96/'flujos - Gasto mensual'!$C96,0)} -> -0.89435208 | N96: {='net worth - criptomonedas'!B98} -> -2939581 | O96: {=_xlfn.IFERROR(N96/'flujos - Gasto mensual'!$C96,0)} -> -0.74056912 | Q96: {=R96-B96} -> -12562437 | R96: {=K96+H96+N96+E96+B96} -> 15096495 | S96: {=R96/'variables - Table 1-1'!B95} -> 16474.86 | T96: {=_xlfn.IFERROR(R96/'flujos - Gasto mensual'!$C96,0)} -> 3.8032625 | U96: {=E96+H96+K96+B96} -> 18036076 | V96: {=F96+O96+I96+L96} -> -3.1648568
A97: 45748 | B97: {='depto - dividendos'!C19} -> 1519135 | C97: {=_xlfn.IFERROR(B97/'flujos - Gasto mensual'!$C97,0)} -> 0.38270176 | E97: {='net worth - retiro'!B99} -> 428739 | F97: {=_xlfn.IFERROR(E97/'flujos - Gasto mensual'!$C97,0)} -> 0.10800829 | H97: {='net worth - brokerage'!B98} -> -1100000 | I97: {=_xlfn.IFERROR(H97/'flujos - Gasto mensual'!$C97,0)} -> -0.27711292 | K97: {='net worth - cash and cash equiv'!B99} -> -3700000 | L97: {=_xlfn.IFERROR(K97/'flujos - Gasto mensual'!$C97,0)} -> -0.93210708 | N97: {='net worth - criptomonedas'!B99} -> 0 | O97: {=_xlfn.IFERROR(N97/'flujos - Gasto mensual'!$C97,0)} -> 0 | Q97: {=R97-B97} -> -4371261 | R97: {=K97+H97+N97+E97+B97} -> -2852126 | S97: {=R97/'variables - Table 1-1'!B96} -> -3017.5161 | T97: {=_xlfn.IFERROR(R97/'flujos - Gasto mensual'!$C97,0)} -> -0.71850996 | U97: {=E97+H97+K97+B97} -> -2852126 | V97: {=F97+O97+I97+L97} -> -1.1012117
A98: 45778 | B98: {='depto - dividendos'!C20} -> 1565558 | C98: {=_xlfn.IFERROR(B98/'flujos - Gasto mensual'!$C98,0)} -> 0.39437859 | E98: {='net worth - retiro'!B100} -> 429744 | F98: {=_xlfn.IFERROR(E98/'flujos - Gasto mensual'!$C98,0)} -> 0.1082565 | H98: {='net worth - brokerage'!B99} -> 0 | I98: {=_xlfn.IFERROR(H98/'flujos - Gasto mensual'!$C98,0)} -> 0 | K98: {='net worth - cash and cash equiv'!B100} -> -1000000 | L98: {=_xlfn.IFERROR(K98/'flujos - Gasto mensual'!$C98,0)} -> -0.25190928 | N98: {='net worth - criptomonedas'!B100} -> 0 | O98: {=_xlfn.IFERROR(N98/'flujos - Gasto mensual'!$C98,0)} -> 0 | Q98: {=R98-B98} -> -570256 | R98: {=K98+H98+N98+E98+B98} -> 995302 | S98: {=R98/'variables - Table 1-1'!B97} -> 1060.6033 | T98: {=_xlfn.IFERROR(R98/'flujos - Gasto mensual'!$C98,0)} -> 0.25072581 | U98: {=E98+H98+K98+B98} -> 995302 | V98: {=F98+O98+I98+L98} -> -0.14365278
A99: 45809 | B99: {='depto - dividendos'!C21} -> 1568696 | C99: {=_xlfn.IFERROR(B99/'flujos - Gasto mensual'!$C99,0)} -> 0.39516162 | E99: {='net worth - retiro'!B101} -> 430428 | F99: {=_xlfn.IFERROR(E99/'flujos - Gasto mensual'!$C99,0)} -> 0.10842676 | H99: {='net worth - brokerage'!B100} -> 0 | I99: {=_xlfn.IFERROR(H99/'flujos - Gasto mensual'!$C99,0)} -> 0 | K99: {='net worth - cash and cash equiv'!B101} -> -1050000 | L99: {=_xlfn.IFERROR(K99/'flujos - Gasto mensual'!$C99,0)} -> -0.26449975 | N99: {='net worth - criptomonedas'!B101} -> 0 | O99: {=_xlfn.IFERROR(N99/'flujos - Gasto mensual'!$C99,0)} -> 0 | Q99: {=R99-B99} -> -619572 | R99: {=K99+H99+N99+E99+B99} -> 949124 | S99: {=R99/'variables - Table 1-1'!B98} -> 1032.6619 | T99: {=_xlfn.IFERROR(R99/'flujos - Gasto mensual'!$C99,0)} -> 0.23908863 | U99: {=E99+H99+K99+B99} -> 949124 | V99: {=F99+O99+I99+L99} -> -0.15607299
A100: 45839 | B100: {='depto - dividendos'!C22} -> 800000 | C100: {=_xlfn.IFERROR(B100/'flujos - Gasto mensual'!$C100,0)} -> 0.19896964 | E100: {='net worth - retiro'!B102} -> 430775 | F100: {=_xlfn.IFERROR(E100/'flujos - Gasto mensual'!$C100,0)} -> 0.10713893 | H100: {='net worth - brokerage'!B101} -> 0 | I100: {=_xlfn.IFERROR(H100/'flujos - Gasto mensual'!$C100,0)} -> 0 | K100: {='net worth - cash and cash equiv'!B102} -> -4300000 | L100: {=_xlfn.IFERROR(K100/'flujos - Gasto mensual'!$C100,0)} -> -1.0694618 | N100: {='net worth - criptomonedas'!B102} -> 250000 | O100: {=_xlfn.IFERROR(N100/'flujos - Gasto mensual'!$C100,0)} -> 0.062178011 | Q100: {=R100-B100} -> -3619225 | R100: {=K100+H100+N100+E100+B100} -> -2819225 | S100: {=R100/'variables - Table 1-1'!B99} -> -2872.5686 | T100: {=_xlfn.IFERROR(R100/'flujos - Gasto mensual'!$C100,0)} -> -0.70117521 | U100: {=E100+H100+K100+B100} -> -3069225 | V100: {=F100+O100+I100+L100} -> -0.90014485
A101: 45870 | B101: {='depto - dividendos'!C23} -> 821802 | C101: {=_xlfn.IFERROR(B101/'flujos - Gasto mensual'!$C101,0)} -> 0.20664111 | E101: {='net worth - retiro'!B103} -> 435063 | F101: {=_xlfn.IFERROR(E101/'flujos - Gasto mensual'!$C101,0)} -> 0.10939606 | H101: {='net worth - brokerage'!B102} -> 0 | I101: {=_xlfn.IFERROR(H101/'flujos - Gasto mensual'!$C101,0)} -> 0 | K101: {='net worth - cash and cash equiv'!B103} -> -4400000 | L101: {=_xlfn.IFERROR(K101/'flujos - Gasto mensual'!$C101,0)} -> -1.1063747 | N101: {='net worth - criptomonedas'!B103} -> 0 | O101: {=_xlfn.IFERROR(N101/'flujos - Gasto mensual'!$C101,0)} -> 0 | Q101: {=R101-B101} -> -3964937 | R101: {=K101+H101+N101+E101+B101} -> -3143135 | S101: {=R101/'variables - Table 1-1'!B100} -> -3247.6442 | T101: {=_xlfn.IFERROR(R101/'flujos - Gasto mensual'!$C101,0)} -> -0.79033748 | U101: {=E101+H101+K101+B101} -> -3143135 | V101: {=F101+O101+I101+L101} -> -0.99697859
A102: 45901 | B102: {=SUM('depto - dividendos'!C24)} -> 1385591 | C102: {=_xlfn.IFERROR(B102/'flujos - Gasto mensual'!$C103,0)} -> 0.34838371 | E102: {='net worth - retiro'!B104} -> 435980 | F102: {=_xlfn.IFERROR(E102/'flujos - Gasto mensual'!$C103,0)} -> 0.10961989 | H102: {='net worth - brokerage'!B103} -> 0 | I102: {=_xlfn.IFERROR(H102/'flujos - Gasto mensual'!$C103,0)} -> 0 | K102: {='net worth - cash and cash equiv'!B104} -> 1750000 | L102: {=_xlfn.IFERROR(K102/'flujos - Gasto mensual'!$C103,0)} -> 0.44000827 | N102: {='net worth - criptomonedas'!B104} -> 0 | O102: {=_xlfn.IFERROR(N102/'flujos - Gasto mensual'!$C103,0)} -> 0 | Q102: {=R102-B102} -> 2185980 | R102: {=SUM(K102,H102,N102,E102,B102)} -> 3571571 | S102: {=R102/'variables - Table 1-1'!B101} -> 3701.34 | T102: {=_xlfn.IFERROR(R102/'flujos - Gasto mensual'!$C103,0)} -> 0.89801187 | U102: {=E102+H102+K102+B102} -> 3571571 | V102: {=F102+O102+I102+L102} -> 0.54962816
A103: 45931 | B103: {=SUM('depto - dividendos'!C25)} -> 816537 | C103: {=_xlfn.IFERROR(B103/'flujos - Gasto mensual'!$C104,0)} -> 0.20528152 | E103: {='net worth - retiro'!B105} -> 436970 | F103: {=_xlfn.IFERROR(E103/'flujos - Gasto mensual'!$C104,0)} -> 0.10985646 | H103: {='net worth - brokerage'!B104} -> 0 | I103: {=_xlfn.IFERROR(H103/'flujos - Gasto mensual'!$C104,0)} -> 0 | K103: {='net worth - cash and cash equiv'!B105} -> -50000 | L103: {=_xlfn.IFERROR(K103/'flujos - Gasto mensual'!$C104,0)} -> -0.012570252 | N103: {='net worth - criptomonedas'!B105} -> 0 | O103: {=_xlfn.IFERROR(N103/'flujos - Gasto mensual'!$C104,0)} -> 0 | Q103: {=R103-B103} -> 386970 | R103: {=K103+H103+N103+E103+B103} -> 1203507 | S103: {=R103/'variables - Table 1-1'!B102} -> 1279.6323 | T103: {=_xlfn.IFERROR(R103/'flujos - Gasto mensual'!$C104,0)} -> 0.30256773 | U103: {=E103+H103+K103+B103} -> 1203507 | V103: {=F103+O103+I103+L103} -> 0.097286208
A104: 45962 | B104: {='depto - dividendos'!C26} -> 1015871 | C104: {=_xlfn.IFERROR(B104/'flujos - Gasto mensual'!$C105,0)} -> 0.25538642 | E104: {='net worth - retiro'!B106} -> 437388 | F104: {=_xlfn.IFERROR(E104/'flujos - Gasto mensual'!$C105,0)} -> 0.10995782 | H104: {='net worth - brokerage'!B105} -> 0 | I104: {=_xlfn.IFERROR(H104/'flujos - Gasto mensual'!$C105,0)} -> 0 | K104: {='net worth - cash and cash equiv'!B106} -> -550000 | L104: {=_xlfn.IFERROR(K104/'flujos - Gasto mensual'!$C105,0)} -> -0.13826808 | N104: {='net worth - criptomonedas'!B106} -> 0 | O104: {=_xlfn.IFERROR(N104/'flujos - Gasto mensual'!$C105,0)} -> 0 | Q104: {=R104-B104} -> -112612 | R104: {=K104+H104+N104+E104+B104} -> 903259 | S104: {=R104/'variables - Table 1-1'!B103} -> 974.51558 | T104: {=_xlfn.IFERROR(R104/'flujos - Gasto mensual'!$C105,0)} -> 0.22707616 | U104: {=E104+H104+K104+B104} -> 903259 | V104: {=F104+O104+I104+L104} -> -0.028310264
A105: 45992 | B105: {='depto - dividendos'!C27} -> 855091 | C105: {=_xlfn.IFERROR(B105/'flujos - Gasto mensual'!$C106,0)} -> 0.21496689 | E105: {='net worth - retiro'!B107} -> 438139 | F105: {=_xlfn.IFERROR(E105/'flujos - Gasto mensual'!$C106,0)} -> 0.11014661 | H105: {='net worth - brokerage'!B106} -> 0 | I105: {=_xlfn.IFERROR(H105/'flujos - Gasto mensual'!$C106,0)} -> 0 | K105: {='net worth - cash and cash equiv'!B107} -> 650000 | L105: {=_xlfn.IFERROR(K105/'flujos - Gasto mensual'!$C106,0)} -> 0.16340773 | N105: {='net worth - criptomonedas'!B107} -> 0 | O105: {=_xlfn.IFERROR(N105/'flujos - Gasto mensual'!$C106,0)} -> 0 | Q105: {=R105-B105} -> 1088139 | R105: {=K105+H105+N105+E105+B105} -> 1943230 | S105: {=R105/'variables - Table 1-1'!B104} -> 2159.2884 | T105: {=_xlfn.IFERROR(R105/'flujos - Gasto mensual'!$C106,0)} -> 0.48852124 | U105: {=E105+H105+K105+B105} -> 1943230 | V105: {=F105+O105+I105+L105} -> 0.27355434
A106: 46023 | B106: {='depto - dividendos'!C28} -> 972618 | C106: {=_xlfn.IFERROR(B106/'flujos - Gasto mensual'!$C106,0)} -> 0.24451277 | E106: {='net worth - retiro'!B108} -> 446453 | F106: {=_xlfn.IFERROR(E106/'flujos - Gasto mensual'!$C106,0)} -> 0.11223673 | H106: {='net worth - brokerage'!B107} -> 0 | I106: {=_xlfn.IFERROR(H106/'flujos - Gasto mensual'!$C106,0)} -> 0 | K106: {='net worth - cash and cash equiv'!B108} -> -200000 | L106: {=_xlfn.IFERROR(K106/'flujos - Gasto mensual'!$C106,0)} -> -0.050279302 | N106: {='net worth - criptomonedas'!B108} -> 0 | O106: {=_xlfn.IFERROR(N106/'flujos - Gasto mensual'!$C106,0)} -> 0 | Q106: {=R106-B106} -> 246453 | R106: {=K106+H106+N106+E106+B106} -> 1219071 | S106: {=R106/'variables - Table 1-1'!B105} -> 1418.9103 | T106: {=_xlfn.IFERROR(R106/'flujos - Gasto mensual'!$C106,0)} -> 0.30647019 | U106: {=E106+H106+K106+B106} -> 1219071 | V106: {=F106+O106+I106+L106} -> 0.061957423
